Workbook

Sheet Company Scorecard
A1: KPI | B1: Definition | C1: Benchmark | D1: Service Line | E1: 45505 | F1: 45536 | G1: 45566 | H1: 45597 | I1: 45627 | J1: 45658 | K1: 45690 | L1: =K1+7 -> 45697 | M1: =L1+7 -> 45704 | N1: =M1+7 -> 45711 | O1: 45689 | P1: 3/2-3/8 | Q1: 3/9-3/15 | R1: 3/16-3/22 | S1: 3/23-3/29 | T1: 45717 | U1: 3/30-4/5 | V1: 4/6-4/12 | W1: 4/13-4/19 | X1: 4/20-4/26 | Y1: 4/27-5/3 | Z1: 45748 | AA1: 5/4-5/10 | AB1: 5/11-5/17 | AC1: 5/18-5/24 | AD1: 5/25-5/31 | AE1: 45778 | AF1: 6/1-6/7 | AG1: 6/8-6/14 | AH1: 6/15-6/21 | AI1: 6/22-6/28 | AJ1: 45809 | AK1: 6/29-7/5 | AL1: 7/6-7/12 | AM1: 7/13-7/19 | AN1: 7/20-7/26 | AO1: 7/27-8/2 | AP1: 45839 | AQ1: 8/3-8/9 | AR1: 8/10-8/16 | AS1: 8/17-8/23 | AT1: 8/24-8/30 | AU1: 45870 | AV1: 8/31-9/6 | AW1: 9/7-9/13 | AX1: 9/14-9/20 | AY1: 9/21-9/27 | AZ1: 45901 | BA1: 9/28-10/4 | BB1: 10/5-10/11 | BC1: 10/12-10/18 | BD1: 10/19-10/25 | BE1: 10/26-11/1 | BF1: 45931 | BG1: 11/2-11/8 | BH1: 11/9-11/15 | BI1: 11/16-11/22 | BJ1: 11/23-11/29 | BK1: 45962 | BL1: 11/30-12/6 | BM1: 12/7-12/13 | BN1: 12/14-12/20 | BO1: 12/21-12/27 | BP1: 12/28-1/3 | BQ1: 45992 | BR1: 1/4-1/10 | BS1: 1/11-1/17 | BT1: 1/18-1/24 | BU1: 1/25-1/31 | BV1: 46023 | BW1: 2/1-2/7 | BX1: 2/8-2/14 | BY1: 2/15-2/21 | BZ1: 2/22-2/28 | CA1: 46054 | CB1: 3/1-3/7 | CC1: 3/8-3/14 | CD1: 3/15-3/21 | CE1: 3/22-3/28 | CF1: 46082 | CG1: 3/29-4/4 | CH1: 4/5-4/11 | CI1: 4/12-4/18 | CJ1: 4/19-4/25 | CK1: 4/26-5/2 | CL1: 46113 | CM1: 46168 | CN1: 46199 | CO1: 46229 | CP1: 46260 | CQ1: 46291 | CR1: 46321 | CS1: 46352 | CT1: 46382
A2: Revenue per period (Monthly)
B3: Month end close report summary | D3: HH | E3: 331506 | F3: 348407 | G3: 355740 | H3: 371615 | I3: 376565 | J3: 341632.41 | O3: 304984.36 | T3: 396523.82 | Z3: 281505.68 | AE3: 213896.51 | AJ3: 159729.23 | AP3: =146193.91-30578.04 -> 115615.87 | AU3: 27477.25 | AZ3: 92359.98 | BF3: 216827.32 | BK3: 367933.79 | BQ3: 394359 | BV3: 349827.72 | CA3: 294290.48 | CF3: 205186
B4: Month end close report summary | D4: Palliative | E4: 297594 | F4: 321259 | G4: 318712 | H4: 315344 | I4: 298592 | J4: 281929.78 | O4: 253187.03 | T4: 292861.01 | Z4: 378958 | AE4: 517157.25 | AJ4: 493731.61 | AP4: =555221.24-37061.99 -> 518159.25 | AU4: 458612.49 | AZ4: 473498.96 | BF4: 366553.37 | BK4: 281253.03 | BQ4: 248739 | BV4: 205332.16 | CA4: 277259.47 | CF4: 410644
B5: Month end close report summary | D5: Hospice | E5: 572472 | F5: 589928 | G5: 635995 | H5: 766813 | I5: 1614478 | J5: 1399891.4 | O5: 1286540.7 | T5: 1576946.4 | Z5: =1154052.3+394359.5 -> 1548411.8 | AE5: 1643627.9 | AJ5: 1715613.6 | AP5: =((2340147.62-331600.55)*0.97)-(208503.49-57934.79) -> 1797722 | AU5: =1357916+505467.59 -> 1863383.6 | AZ5: 1738676.5 | BF5: 1771967.7 | BK5: 1679318.2 | BQ5: 1802326 | BV5: 1804009.4 | CA5: 1620968.2 | CF5: 1805725
A6: Current ADC | C6: Benchmark | J6: =SUM(J3:J5) -> 2023453.6 | O6: =SUM(O3:O5) -> 1844712.1 | T6: =SUM(T3:T5) -> 2266331.3 | Z6: =SUM(Z3:Z5) -> 2208875.5 | AE6: =SUM(AE3:AE5) -> 2374681.7 | AF6: =SUM(AF3:AF5) -> 0 | AG6: =SUM(AG3:AG5) -> 0 | AH6: =SUM(AH3:AH5) -> 0 | AI6: =SUM(AI3:AI5) -> 0 | AJ6: =SUM(AJ3:AJ5) -> 2369074.5 | AP6: =SUM(AP3:AP5) -> 2431497.1 | AU6: =SUM(AU3:AU5) -> 2349473.3 | AZ6: =SUM(AZ3:AZ5) -> 2304535.4 | BF6: =SUM(BF3:BF5) -> 2355348.4 | BK6: =SUM(BK3:BK5) -> 2328505.1 | BQ6: =SUM(BQ3:BQ5) -> 2445424 | BV6: =SUM(BV3:BV5) -> 2359169.3 | BW6: =SUM(BW3:BW5) -> 0 | BX6: =SUM(BX3:BX5) -> 0 | BY6: =SUM(BY3:BY5) -> 0 | BZ6: =SUM(BZ3:BZ5) -> 0 | CA6: =SUM(CA3:CA5) -> 2192518.1 | CF6: =SUM(CF3:CF5) -> 2421555 | CL6: =SUM(CL3:CL5) -> 0
B7: Home Health WAAR report - weekly ending Sunday | C7: 170 | D7: HH | E7: 143 | F7: 149 | G7: 145 | H7: 154 | I7: 157 | J7: 155 | K7: 153 | L7: 152 | M7: 149 | N7: 150 | O7: 148 | P7: 150 | Q7: 153 | R7: 156 | S7: 162 | T7: 154 | U7: 156 | V7: 145 | W7: 137 | X7: 130 | Y7: 122 | Z7: 135 | AA7: 110 | AB7: 102 | AC7: 95 | AD7: 88 | AE7: 98 | AF7: 83 | AG7: 77 | AH7: 71 | AI7: 69 | AJ7: 72 | AK7: 65 | AL7: 64 | AM7: 63 | AN7: 61 | AO7: 58 | AP7: 59 | AQ7: 55 | AR7: 53 | AS7: 53 | AT7: 52 | AU7: 52 | AV7: 53 | AW7: 51 | AX7: 48 | AY7: 48 | AZ7: 49 | BA7: 57 | BB7: 72 | BC7: 83 | BD7: 92 | BE7: 107 | BF7: 83 | BG7: 118 | BH7: 136 | BI7: 148 | BJ7: 155 | BK7: 139 | BL7: 159 | BM7: 156 | BN7: 155 | BO7: 151 | BP7: 146 | BQ7: 152 | BR7: 143 | BS7: 145 | BT7: 148 | BU7: 152 | BV7: 145 | BW7: 158 | BX7: 148 | BY7: 135 | BZ7: 128 | CA7: 140 | CB7: 117 | CC7: 103 | CD7: 89 | CE7: 77 | CF7: 93 | CG7: 66 | CH7: 60 | CI7: 56 | CJ7: 52 | CK7: 49 | CL7: 55
B8: Home Health WAAR report - weekly ending Sunday | C8: 155 | D8: Palliative | E8: 125 | F8: 133 | G8: 133 | H8: 135 | I8: 122 | J8: 115 | K8: 113 | L8: 112 | M8: 113 | N8: 115 | O8: 113 | P8: 112 | Q8: 115 | R8: 118 | S8: 115 | T8: 114 | U8: 122 | V8: 133 | W8: 146 | X8: 157 | Y8: 176 | Z8: 144 | AA8: 182 | AB8: 190 | AC8: 194 | AD8: 198 | AE8: 187 | AF8: 194 | AG8: 190 | AH8: 192 | AI8: 200 | AJ8: 190 | AK8: 214 | AL8: 215 | AM8: 222 | AN8: 226 | AO8: 230 | AP8: 212 | AQ8: 236 | AR8: 235 | AS8: 229 | AT8: 222 | AU8: 222 | AV8: 217 | AW8: 219 | AX8: 223 | AY8: 217 | AZ8: 215 | BA8: 206 | BB8: 187 | BC8: 175 | BD8: 170 | BE8: 161 | BF8: 176 | BG8: 155 | BH8: 146 | BI8: 140 | BJ8: 132 | BK8: 143 | BL8: 129 | BM8: 123 | BN8: 115 | BO8: 110 | BP8: 102 | BQ8: 116 | BR8: 94 | BS8: 88 | BT8: 84 | BU8: 85 | BV8: 88 | BW8: 88 | BX8: 102 | BY8: 119 | BZ8: 129 | CA8: 108 | CB8: 138 | CC8: 154 | CD8: 167 | CE8: 171 | CF8: 159 | CG8: 179 | CH8: 181 | CI8: 182 | CJ8: 186 | CK8: 201 | CL8: 185
B9: Calculated | C9: =SUM(C7:C8) -> 325 | D9: Total HH & PAL | E9: =E7+E8 -> 268 | F9: =F7+F8 -> 282 | G9: =G7+G8 -> 278 | H9: =H7+H8 -> 289 | I9: =I7+I8 -> 279 | J9: =J7+J8 -> 270 | K9: =K7+K8 -> 266 | L9: =L7+L8 -> 264 | ... N9: =N7+N8 -> 265 | O9: =+O8+O7 -> 261 | P9: =P7+P8 -> 262 | Q9: =Q7+Q8 -> 268 | R9: =R7+R8 -> 274 | S9: =S7+S8 -> 277 | T9: =T7+T8 -> 268 | U9: =U7+U8 -> 278 | V9: =V7+V8 -> 278 | W9: =W7+W8 -> 283 | ... AI9: =AI7+AI8 -> 269 | AJ9: =+AJ8+AJ7 -> 262 | AK9: =AK7+AK8 -> 279 | AL9: =AL7+AL8 -> 279 | AM9: =AM7+AM8 -> 285 | AN9: =AN7+AN8 -> 287 | AO9: =AO7+AO8 -> 288 | AP9: =AP7+AP8 -> 271 | AQ9: =AQ7+AQ8 -> 291 | AR9: =AR7+AR8 -> 288 | ... CL9: =CL7+CL8 -> 240
B10: Hospice WAAR report - weekly ending Sunday | C10: 92 | D10: Hospice OC | E10: 84.5 | F10: 89.5 | G10: 87.9 | H10: 87.8 | I10: 88.6 | J10: 80.7 | K10: 78 | L10: 80 | M10: 81 | N10: 82 | O10: 79.1 | P10: 82 | Q10: 86 | R10: 88 | S10: 88 | T10: 85 | U10: 89 | V10: 89 | W10: 91 | X10: 92 | Y10: 88 | Z10: 89.2 | AA10: 88 | AB10: 93 | AC10: 92 | AD10: 94 | AE10: 90.9 | AF10: 93 | AG10: 95 | AH10: 98 | AI10: 98 | AJ10: =2+96.2 -> 98.2 | AK10: 99 | AL10: 94 | AM10: 96 | AN10: 100 | AO10: 101 | AP10: =97.8+2 -> 99.8 | AQ10: =100+2 -> 102 | AR10: 100 | AS10: 102 | AT10: =105+1 -> 106 | AU10: =100.5+1.8 -> 102.3 | AV10: 108 | AW10: 111 | AX10: 112 | AY10: 111 | AZ10: 108.6 | BA10: 108 | BB10: 110 | BC10: 114 | BD10: 110 | BE10: 113 | BF10: 110 | BG10: 110 | BH10: 112 | BI10: 112 | BJ10: 110 | BK10: 109.8 | BL10: 111 | BM10: 114 | BN10: 117 | BO10: 117 | BP10: 118 | BQ10: 114.7 | BR10: 117 | BS10: 117 | BT10: 117 | BU10: 115 | BV10: 115.4 | BW10: 116 | BX10: 121 | BY10: 122 | BZ10: 123 | CA10: 119.9 | CB10: 128 | CC10: 128 | CD10: 125 | CE10: 124 | CF10: 125.3 | CG10: 125 | CH10: 125 | CI10: 125 | CJ10: 120 | CK10: 120 | CL10: 123
B11: Hospice WAAR report - weekly ending Sunday | C11: 45 | D11: Hospice IE | E11: 35.58 | F11: 32.43 | G11: 35.94 | H11: 31.5 | I11: 32.2 | J11: 36.7 | K11: 36 | L11: 36 | M11: 38 | N11: 36.6 | O11: 36.6 | P11: 36.2 | Q11: 34 | R11: 34 | S11: 33 | T11: 35.4 | U11: 32 | V11: 32 | W11: 32 | X11: 33 | Y11: 33 | Z11: 33.3 | AA11: 31 | AB11: 31 | AC11: 33 | AD11: 35 | AE11: 33.8 | AF11: 35 | AG11: 37 | AH11: 37 | AI11: 38 | AJ11: =36.7+1 -> 37.7 | AK11: 37 | AL11: 39 | AM11: 39 | AN11: 39 | AO11: 39 | AP11: =38.9+1 -> 39.9 | AQ11: =40+2 -> 42 | AR11: 45 | AS11: =47+1 -> 48 | AT11: =46+1 -> 47 | AU11: =43.6+1.4 -> 45 | AV11: 46 | AW11: 46 | AX11: 48 | AY11: 47 | AZ11: 46.6 | BA11: 46 | BB11: 44 | BC11: 45 | BD11: 45 | BE11: 45 | BF11: 44.7 | BG11: 46 | BH11: 44 | BI11: 43 | BJ11: 43 | BK11: =1+42.7 -> 43.7 | BL11: 41 | BM11: 43 | BN11: 44 | BO11: 44 | BP11: 44 | BQ11: 43.2 | BR11: 42 | BS11: 40 | BT11: 39 | BU11: 38 | BV11: 40 | BW11: 39 | BX11: 42 | BY11: 42 | BZ11: 43 | CA11: 41.3 | CB11: 44 | CC11: 44 | CD11: 45 | CE11: 46 | CF11: 44.9 | CG11: 46 | CH11: 46 | CI11: 47 | CJ11: 50 | CK11: 52 | CL11: 48
B12: Hospice WAAR report - weekly ending Sunday | C12: 35 | D12: Hospice SGV | E12: 20.55 | F12: 22.87 | G12: 27.45 | H12: 22.33 | I12: 25.7 | J12: 25.6 | K12: 24.5 | L12: 25 | M12: 24 | N12: 26 | O12: 24.5 | P12: 23.8 | Q12: 25 | R12: 26 | S12: 27 | T12: 24.8 | U12: 29 | V12: 30 | W12: 28 | X12: 28 | Y12: 27 | Z12: 28 | AA12: 27 | AB12: 29 | AC12: 31 | AD12: 31 | AE12: =29.1+1.8 -> 30.9 | AF12: 31 | AG12: 32 | AH12: 35 | AI12: 34 | AJ12: =33.9+2 -> 35.9 | AK12: 34 | AL12: 33 | AM12: 36 | AN12: 37 | AO12: 39 | AP12: =35.6+1.9 -> 37.5 | AQ12: =37+1 -> 38 | AR12: =36+1 -> 37 | AS12: =36+1 -> 37 | AT12: 37 | AU12: =36.2+0.8 -> 37 | AV12: 35 | AW12: 32 | AX12: 32 | AY12: 31 | AZ12: 30.9 | BA12: 27 | BB12: 26 | BC12: 26 | BD12: 26 | BE12: 25 | BF12: 24.9 | BG12: 25 | BH12: 24 | BI12: 24 | BJ12: 25 | BK12: 23.6 | BL12: 26 | BM12: 26 | BN12: 25 | BO12: 24 | BP12: 25 | BQ12: 23.9 | BR12: 25 | BS12: 25 | BT12: 24 | BU12: 25 | BV12: 24.4 | BW12: 22 | BX12: 20 | BY12: 18 | BZ12: 18 | CA12: 19.6 | CB12: 17 | CC12: 18 | CD12: 18 | CE12: 19 | CF12: 18.1 | CG12: 19 | CH12: 20 | CI12: 18 | CJ12: 18 | CK12: 21 | CL12: 19
B13: Hospice WAAR report - weekly ending Sunday | C13: 93 | D13: Total Hospice Desert | E13: 60.32 | F13: 64.13 | G13: 72.61 | H13: 68.4 | I13: 73.1 | J13: 73 | K13: 75 | L13: 74 | M13: 74 | N13: 74 | O13: 71.1 | P13: 81 | Q13: 86 | R13: 84 | S13: 83 | T13: 83 | U13: 82 | V13: 85 | W13: 88 | X13: 89 | Y13: 92 | Z13: 86.3 | AA13: 89 | AB13: 90 | AC13: 93 | AD13: 98 | AE13: 92.6 | AF13: 100 | AG13: 100 | AH13: 98 | AI13: 97 | AJ13: 98.3 | AK13: 95 | AL13: 96 | AM13: 98 | AN13: 98 | AO13: 103 | AP13: 97.2 | AQ13: 101 | AR13: 99 | AS13: 97 | AT13: 96 | AU13: =24.7+73.9 -> 98.6 | AV13: 91 | AW13: 91 | AX13: 91 | AY13: 89 | AZ13: 89.7 | BA13: 86 | BB13: 90 | BC13: 92 | BD13: 93 | BE13: 95 | BF13: 91 | BG13: 94 | BH13: 92 | BI13: 90 | BJ13: 91 | BK13: =55.3+36.6 -> 91.9 | BL13: 91 | BM13: 90 | BN13: 96 | BO13: 96 | BP13: 98 | BQ13: 94 | BR13: 96 | BS13: 95 | BT13: 98 | BU13: 99 | BV13: 97 | BW13: 100 | BX13: 99 | BY13: 98 | BZ13: 97 | CA13: 98.5 | CB13: 97 | CC13: 92 | CD13: 91 | CE13: 91 | CF13: 92.6 | CG13: 92 | CH13: 86 | CI13: 86 | CJ13: 83 | CK13: 82 | CL13: 85.4
B15: Calculated | C15: =SUM(C10:C13) -> 265 | D15: Total Hospice | E15: =SUM(E10:E13) -> 200.95 | F15: =SUM(F10:F13) -> 208.93 | G15: =SUM(G10:G13) -> 223.9 | H15: =SUM(H10:H13) -> 210.03 | I15: =SUM(I10:I13) -> 219.6 | J15: =SUM(J10:J13) -> 216 | K15: =SUM(K10:K13) -> 213.5 | L15: =SUM(L10:L13) -> 215 | ... N15: =SUM(N10:N13) -> 218.6 | O15: =_xlfn.SINGLE(SUM(O10:O13)) -> 211.3 | P15: =SUM(P10:P13) -> 223 | Q15: =SUM(Q10:Q13) -> 231 | R15: =SUM(R10:R13) -> 232 | S15: =SUM(S10:S13) -> 231 | T15: =SUM(T10:T13) -> 228.2 | U15: =SUM(U10:U13) -> 232 | V15: =SUM(V10:V13) -> 236 | W15: =SUM(W10:W13) -> 239 | ... AI15: =SUM(AI10:AI13) -> 267 | AJ15: =+AJ13+AJ12+AJ11+AJ10 -> 270.1 | AK15: =SUM(AK10:AK13) -> 265 | AL15: =SUM(AL10:AL13) -> 262 | AM15: =SUM(AM10:AM13) -> 269 | AN15: =SUM(AN10:AN13) -> 274 | AO15: =SUM(AO10:AO13) -> 282 | AP15: =+AP13+AP12+AP11+AP10 -> 274.4 | AQ15: =SUM(AQ10:AQ13) -> 283 | AR15: =SUM(AR10:AR13) -> 281 | AS15: =SUM(AS10:AS13) -> 284 | AT15: =SUM(AT10:AT13) -> 286 | AU15: =+AU13+AU12+AU11+AU10 -> 282.9 | AV15: =SUM(AV10:AV13) -> 280 | AW15: =SUM(AW10:AW13) -> 280 | AX15: =SUM(AX10:AX13) -> 283 | AY15: =SUM(AY10:AY13) -> 278 | AZ15: =+AZ13+AZ12+AZ11+AZ10 -> 275.8 | BA15: =SUM(BA10:BA13) -> 267 | BB15: =SUM(BB10:BB13) -> 270 | BC15: =SUM(BC10:BC13) -> 277 | BD15: =SUM(BD10:BD13) -> 274 | BE15: =SUM(BE10:BE13) -> 278 | BF15: =+BF13+BF12+BF11+BF10 -> 270.6 | BG15: =SUM(BG10:BG13) -> 275 | BH15: =SUM(BH10:BH13) -> 272 | BI15: =SUM(BI10:BI13) -> 269 | BJ15: =SUM(BJ10:BJ13) -> 269 | BK15: =+BK13+BK12+BK11+BK10 -> 269 | BL15: =SUM(BL10:BL13) -> 269 | BM15: =SUM(BM10:BM13) -> 273 | BN15: =SUM(BN10:BN13) -> 282 | BO15: =SUM(BO10:BO13) -> 281 | BP15: =SUM(BP10:BP13) -> 285 | BQ15: =+BQ13+BQ12+BQ11+BQ10 -> 275.8 | BR15: =SUM(BR10:BR13) -> 280 | BS15: =SUM(BS10:BS13) -> 277 | BT15: =SUM(BT10:BT13) -> 278 | BU15: =SUM(BU10:BU13) -> 277 | BV15: =SUM(BV10:BV13) -> 276.8 | BW15: =SUM(BW10:BW13) -> 277 | BX15: =SUM(BX10:BX13) -> 282 | BY15: =SUM(BY10:BY13) -> 280 | ... CL15: =SUM(CL10:CL13) -> 275.4
A16: Hospice Census Equivalent (HCE) | C16: Benchmark Budget
B17: Calculated (avg.) | C17: =C9/2.5 -> 130 | D17: HH+Palliative | E17: =E9/2.5 -> 107.2 | F17: =F9/2.5 -> 112.8 | G17: =G9/2.5 -> 111.2 | H17: =H9/2.5 -> 115.6 | I17: =I9/2.5 -> 111.6 | J17: =J9/2.5 -> 108 | K17: =K9/2.5 -> 106.4 | L17: =L9/2.5 -> 105.6 | ... CL17: =CL9/2.5 -> 96
B18: Calculated (avg.) | C18: =C17+C15 -> 395 | D18: All Locations | E18: =E17+E15 -> 308.15 | F18: =F17+F15 -> 321.73 | G18: =G17+G15 -> 335.1 | H18: =H17+H15 -> 325.63 | I18: =I17+I15 -> 331.2 | J18: =J17+J15 -> 324 | K18: =K17+K15 -> 319.9 | L18: =L17+L15 -> 320.6 | ... CL18: =CL17+CL15 -> 371.4
A19: Weekly Admission (add house category) | C19: Benchmark Budget | D19: Budget | J19: 337 | O19: 341 | T19: 346 | Z19: 352 | AE19: 356 | AJ19: 363 | BV19: 381 | CA19: 383 | CF19: 390 | CG19: 402 | CH19: 402 | CI19: 402 | CJ19: 402 | CK19: 402 | CL19: 390 | CM19: 416 | CN19: 432 | CO19: 443 | CP19: 446 | CQ19: 449 | CR19: 455 | CS19: 462 | CT19: 466
B20: Home Health WAAR report - weekly ending Sunday | C20: 15 | D20: HH | E20: 39 | F20: 41 | G20: 42 | H20: 47 | I20: 42 | J20: 47 | K20: 9 | L20: 9 | M20: 9 | N20: 8 | O20: 33 | P20: 12 | Q20: 13 | R20: 13 | S20: 10 | T20: 50 | U20: 0 | V20: 0 | W20: 0 | X20: 1 | Y20: 0 | Z20: 1 | AA20: 0 | AB20: 0 | AC20: 0 | AD20: 0 | AE20: 0 | AF20: 0 | AG20: 0 | AH20: 0 | AI20: 0 | AJ20: 0 | AK20: 1 | AL20: 0 | AM20: 0 | AN20: 1 | AO20: 0 | AP20: 2 | AQ20: 0 | AR20: 1 | AS20: 1 | AT20: 1 | AU20: 3 | AV20: 3 | AW20: 0 | AX20: 1 | AY20: 6 | AZ20: 16 | BA20: 17 | BB20: 17 | BC20: 9 | BD20: 19 | BE20: 22 | BF20: 74 | BG20: 21 | BH20: 21 | BI20: 22 | BJ20: 13 | BK20: 83 | BL20: 19 | BM20: 14 | BN20: 18 | BO20: 6 | BP20: 8 | BQ20: 62 | BR20: 17 | BS20: 22 | BT20: 10 | BU20: 18 | BV20: 71 | BW20: 11 | BX20: 0 | BY20: 1 | BZ20: 0 | CA20: 11 | CB20: 0 | CC20: 0 | CD20: 0 | CE20: 0 | CF20: 0 | CG20: 0 | CH20: 0 | CI20: 2 | CJ20: 0 | CK20: 0 | CL20: 2
B21: Home Health WAAR report - weekly ending Sunday | C21: 10 | D21: Palliative | E21: 34 | F21: 32 | G21: 38 | H21: 26 | I21: 27 | J21: 44 | K21: 11 | L21: 10 | M21: 12 | N21: 10 | O21: 43 | P21: 9 | Q21: 7 | R21: 8 | S21: 5 | T21: 32 | U21: 28 | V21: 20 | W21: 19 | X21: 23 | Y21: 25 | Z21: 107 | AA21: 22 | AB21: 19 | AC21: 17 | AD21: 18 | AE21: 80 | AF21: 10 | AG21: 15 | AH21: 21 | AI21: 22 | AJ21: 72 | AK21: 17 | AL21: 11 | AM21: 18 | AN21: 14 | AO21: 17 | AP21: 65 | AQ21: 14 | AR21: 20 | AS21: 8 | AT21: 12 | AU21: 60 | AV21: 15 | AW21: 18 | AX21: 14 | AY21: 4 | AZ21: 55 | BA21: 6 | BB21: 1 | BC21: 6 | BD21: 4 | BE21: 3 | BF21: 15 | BG21: 2 | BH21: 1 | BI21: 0 | BJ21: 0 | BK21: 4 | BL21: 3 | BM21: 8 | BN21: 0 | BO21: 5 | BP21: 0 | BQ21: 16 | BR21: 7 | BS21: 2 | BT21: 8 | BU21: 3 | BV21: 20 | BW21: 15 | BX21: 20 | BY21: 22 | BZ21: 19 | CA21: 73 | CB21: 17 | CC21: 24 | CD21: 15 | CE21: 24 | CF21: 86 | CG21: 17 | CH21: 13 | CI21: 19 | CJ21: 18 | CK21: 22 | CL21: 74
C22: 25 | D22: Total Comb. HH-Pall | J22: =J20+J21 -> 91 | P22: =SUM(P20:P21) -> 21 | Q22: =SUM(Q20:Q21) -> 20 | R22: =SUM(R20:R21) -> 21 | S22: =SUM(S20:S21) -> 15 | T22: =SUM(T20:T21) -> 82 | U22: =SUM(U20:U21) -> 28 | V22: =SUM(V20:V21) -> 20 | W22: =SUM(W20:W21) -> 19 | ... AJ22: =SUM(AJ20:AJ21) -> 72 | AK22: =AK20+AK21 -> 18 | AL22: =AL20+AL21 -> 11 | AM22: =AM20+AM21 -> 18 | AN22: =AN20+AN21 -> 15 | AO22: =AO20+AO21 -> 17 | AP22: =AP20+AP21 -> 67 | AQ22: =AQ20+AQ21 -> 14 | AR22: =AR20+AR21 -> 21 | ... CL22: =CL20+CL21 -> 76
B23: Hospice WAAR report - weekly ending Sunday | C23: 7 | D23: Hospice OC | E23: 18 | F23: 20 | G23: 19 | H23: 17 | I23: 21 | J23: 23 | K23: 0 | L23: 8 | M23: 7 | N23: 3 | O23: 18 | P23: 7 | Q23: 7 | R23: 4 | S23: 10 | T23: 30 | U23: 5 | V23: 5 | W23: 9 | X23: 6 | Y23: 4 | Z23: 24 | AA23: 10 | AB23: 12 | AC23: 6 | AD23: 4 | AE23: 36 | AF23: 6 | AG23: 4 | AH23: 8 | AI23: 11 | AJ23: =1+30 -> 31 | AK23: 8 | AL23: 3 | AM23: 8 | AN23: 6 | AO23: 5 | AP23: 29 | AQ23: 7 | AR23: 10 | AS23: 6 | AT23: 8 | AU23: 32 | AV23: 7 | AW23: 8 | AX23: 5 | AY23: 5 | AZ23: 25 | BA23: 6 | BB23: 7 | BC23: 6 | BD23: 5 | BE23: 7 | BF23: 30 | BG23: 8 | BH23: 8 | BI23: 3 | BJ23: 2 | BK23: 21 | BL23: 9 | BM23: 6 | BN23: 9 | BO23: 5 | BP23: 4 | BQ23: 31 | BR23: 4 | BS23: 4 | BT23: 8 | BU23: 2 | BV23: 20 | BW23: 10 | BX23: 10 | BY23: 6 | BZ23: 10 | CA23: 36 | CB23: 9 | CC23: 4 | CD23: 9 | CE23: 5 | CF23: 28 | CG23: 3 | CH23: 4 | CI23: 5 | CJ23: 6 | CK23: 4 | CL23: 21
B24: Hospice WAAR report - weekly ending Sunday | C24: 5 | D24: Hospice IE | H24: 3 | I24: 7 | J24: 7 | K24: 2 | L24: 1 | M24: 1 | N24: 0 | O24: 4 | P24: 0 | Q24: 2 | R24: 0 | S24: 2 | T24: 4 | U24: 0 | V24: 2 | W24: 1 | X24: 1 | Y24: 1 | Z24: 5 | AA24: 1 | AB24: 2 | AC24: 3 | AD24: 0 | AE24: 6 | AF24: 4 | AG24: 2 | AH24: 3 | AI24: 2 | AJ24: 11 | AK24: 3 | AL24: 2 | AM24: 2 | AN24: 2 | AO24: 5 | AP24: 13 | AQ24: 2 | AR24: 4 | AS24: 3 | AT24: 1 | AU24: =11+1 -> 12 | AV24: 1 | AW24: 4 | AX24: 1 | AY24: 2 | AZ24: 8 | BA24: 1 | BB24: 1 | BC24: 4 | BD24: 1 | BE24: 5 | BF24: 11 | BG24: 2 | BH24: 3 | BI24: 1 | BJ24: 1 | BK24: =0+8 -> 8 | BL24: 2 | BM24: 4 | BN24: 1 | BO24: 2 | BP24: 1 | BQ24: 10 | BR24: 1 | BS24: 1 | BT24: 2 | BU24: 3 | BV24: 8 | BW24: 2 | BX24: 5 | BY24: 2 | BZ24: 5 | CA24: 14 | CB24: 1 | CC24: 1 | CD24: 1 | CE24: 3 | CF24: 6 | CG24: 0 | CH24: 0 | CI24: 5 | CJ24: 6 | CK24: 1 | CL24: 11
B25: Hospice WAAR report - weekly ending Sunday | C25: 3 | D25: Hospice SGV | H25: 5 | I25: 8 | J25: 7 | K25: 3 | L25: 2 | M25: 0 | N25: 3 | O25: 8 | P25: 0 | Q25: 3 | R25: 1 | S25: 3 | T25: 8 | U25: 5 | V25: 2 | W25: 2 | X25: 0 | Y25: 0 | Z25: 8 | AA25: 0.01 | AB25: 3 | AC25: 2 | AD25: 0 | AE25: 5 | AF25: 1 | AG25: 3 | AH25: 4 | AI25: 1 | AJ25: 11 | AK25: 1 | AL25: 1 | AM25: 4 | AN25: 2 | AO25: 2 | AP25: 9 | AQ25: 0 | AR25: 3 | AS25: 1 | AT25: 3 | AU25: =7 -> 7 | AV25: 0 | AW25: 0 | AX25: 0 | AY25: 1 | AZ25: 2 | BA25: 1 | BB25: 2 | BC25: 1 | BD25: 1 | BE25: 1 | BF25: 5 | BG25: 0 | BH25: 0 | BI25: 2 | BJ25: 3 | BK25: 5 | BL25: 0 | BM25: 0 | BN25: 0 | BO25: 0 | BP25: 2 | BQ25: 0 | BR25: 0 | BS25: 0 | BT25: 1 | BU25: 0 | BV25: 1 | BW25: 1 | BX25: 0 | BY25: 1 | BZ25: 1 | CA25: 3 | CB25: 0 | CC25: 1 | CD25: 1 | CE25: 1 | CF25: 3 | CG25: 3 | CH25: 0 | CI25: 0 | CJ25: 1 | CK25: 2 | CL25: 5
B26: Hospice WAAR report - weekly ending Sunday | C26: 10 | D26: Hospice Desert | H26: 54 | I26: 30 | J26: 31 | K26: 8 | L26: 10 | M26: 7 | N26: 6 | O26: 33 | P26: 12 | Q26: 10 | R26: 5 | S26: 6 | T26: 35 | U26: 9 | V26: 5 | W26: 9 | X26: 5 | Y26: 9 | Z26: 32 | AA26: 6 | AB26: 6 | AC26: 10 | AD26: 7 | AE26: 33 | AF26: 7 | AG26: 3 | AH26: 5 | AI26: 5 | AJ26: 21 | AK26: 2 | AL26: 10 | AM26: 3 | AN26: 8 | AO26: 8 | AP26: 29 | AQ26: 5 | AR26: 4 | AS26: 7 | AT26: 4 | AU26: =22 -> 22 | AV26: 4 | AW26: 2 | AX26: 7 | AY26: 3 | AZ26: 16 | BA26: 3 | BB26: 8 | BC26: 6 | BD26: 10 | BE26: 6 | BF26: 31 | BG26: 6 | BH26: 5 | BI26: 6 | BJ26: 4 | BK26: =0+22 -> 22 | BL26: 6 | BM26: 11 | BN26: 5 | BO26: 7 | BP26: 8 | BQ26: 31 | BR26: 7 | BS26: 4 | BT26: 10 | BU26: 11 | BV26: 34 | BW26: 7 | BX26: 6 | BY26: 3 | BZ26: 7 | CA26: 23 | CB26: 6 | CC26: 0 | CD26: 8 | CE26: 5 | CF26: 21 | CG26: 6 | CH26: 3 | CI26: 5 | CJ26: 4 | CK26: 7 | CL26: 21
C27: =C23+C24+C25+C26 -> 25 | D27: Total Hospice | H27: =+H26+H25+H24+H23 -> 79 | I27: =+I26+I25+I24+I23 -> 66 | J27: =+J26+J25+J24+J23 -> 68 | K27: =+K26+K25+K24+K23 -> 13 | L27: =+L26+L25+L24+L23 -> 21 | M27: =+M26+M25+M24+M23 -> 15 | N27: =+N26+N25+N24+N23 -> 12 | O27: =+O26+O25+O24+O23 -> 63 | ... R27: =+R26+R25+R24+R23 -> 10 | S27: =SUM(S23:S26) -> 21 | T27: =SUM(T23:T26) -> 77 | U27: =SUM(U23:U26) -> 19 | V27: =SUM(V23:V26) -> 14 | W27: =SUM(W23:W26) -> 21 | X27: =SUM(X23:X26) -> 12 | Y27: =SUM(Y23:Y26) -> 14 | Z27: =SUM(Z23:Z26) -> 69 | ... BU27: =SUM(BU23:BU26) -> 16 | BV27: =+BV26+BV25+BV24+BV23 -> 63 | BW27: =SUM(BW23:BW26) -> 20 | BX27: =SUM(BX23:BX26) -> 21 | BY27: =SUM(BY23:BY26) -> 12 | BZ27: =SUM(BZ23:BZ26) -> 23 | CA27: =+CA26+CA25+CA24+CA23 -> 76 | CB27: =SUM(CB23:CB26) -> 16 | CC27: =SUM(CC23:CC26) -> 6 | CD27: =SUM(CD23:CD26) -> 19 | CE27: =SUM(CE23:CE26) -> 14 | CF27: =+CF26+CF25+CF24+CF23 -> 58 | CG27: =SUM(CG23:CG26) -> 12 | CH27: =SUM(CH23:CH26) -> 7 | CI27: =SUM(CI23:CI26) -> 15 | CJ27: =SUM(CJ23:CJ26) -> 17 | CK27: =SUM(CK23:CK26) -> 14 | CL27: =+CL26+CL25+CL24+CL23 -> 58
A29: # of Recerts | C29: Benchmark Budget | D29: Budget | J29: 134 | O29: 136 | T29: 136 | Z29: 136 | AE29: 134 | AJ29: 159
B30: Home Health WAAR report - weekly ending Sunday | D30: HH | E30: 54 | F30: 39 | G30: 61 | H30: 40 | I30: 52 | J30: 48 | K30: 14 | L30: 10 | M30: 12 | N30: 12 | O30: 47 | P30: 13 | Q30: 11 | R30: 8 | S30: 13 | T30: 49 | U30: 8 | V30: 15 | W30: 12 | X30: 7 | Y30: 14 | Z30: 49 | AA30: 17 | AB30: 10 | AC30: 7 | AD30: 10 | AE30: 45 | AF30: 5 | AG30: 8 | AH30: 9 | AI30: 8 | AJ30: 30 | AK30: 6 | AL30: 10 | AM30: 4 | AN30: 8 | AO30: 3 | AP30: 28 | AQ30: 7 | AR30: 5 | AS30: 5 | AT30: 5 | AU30: 23 | AV30: 8 | AW30: 6 | AX30: 4 | AY30: 4 | AZ30: 23 | BA30: 2 | BB30: 2 | BC30: 3 | BD30: 4 | BE30: 3 | BF30: 14 | BG30: 8 | BH30: 2 | BI30: 8 | BJ30: 4 | BK30: 23 | BL30: 6 | BM30: 8 | BN30: 4 | BO30: 9 | BP30: 8 | BQ30: 32 | BR30: 9 | BS30: 9 | BT30: 9 | BU30: 8 | BV30: 37 | BW30: 9 | BX30: 8 | BY30: 10 | BZ30: 7 | CA30: 33 | CB30: 9 | CC30: 6 | CD30: 11 | CE30: 7 | CF30: 37 | CG30: 11 | CH30: 7 | CI30: 3 | CJ30: 4 | CK30: 6 | CL30: 26
B31: Home Health WAAR report - weekly ending Sunday | D31: Palliative | E31: 47 | F31: 43 | G31: 52 | H31: 43 | I31: 49 | J31: 25 | K31: 9 | L31: 8 | M31: 6 | N31: 5 | O31: 30 | P31: 7 | Q31: 9 | R31: 6 | S31: 9 | T31: 34 | U31: 7 | V31: 17 | W31: 3 | X31: 10 | Y31: 4 | Z31: 34 | AA31: 5 | AB31: 9 | AC31: 10 | AD31: 10 | AE31: 38 | AF31: 20 | AG31: 12 | AH31: 14 | AI31: 13 | AJ31: 59 | AK31: 10 | AL31: 14 | AM31: 14 | AN31: 18 | AO31: 19 | AP31: 69 | AQ31: 21 | AR31: 13 | AS31: 16 | AT31: 20 | AU31: 73 | AV31: 9 | AW31: 15 | AX31: 14 | AY31: 16 | AZ31: 58 | BA31: 19 | BB31: 13 | BC31: 17 | BD31: 16 | BE31: 15 | BF31: 74 | BG31: 14 | BH31: 16 | BI31: 16 | BJ31: 12 | BK31: 61 | BL31: 12 | BM31: 4 | BN31: 10 | BO31: 11 | BP31: 2 | BQ31: 37 | BR31: 7 | BS31: 12 | BT31: 11 | BU31: 8 | BV31: 40 | BW31: 4 | BX31: 5 | BY31: 6 | BZ31: 5 | CA31: 20 | CB31: 1 | CC31: 9 | CD31: 12 | CE31: 10 | CF31: 35 | CG31: 5 | CH31: 13 | CI31: 8 | CJ31: 12 | CK31: 8 | CL31: 42
A32: Recert % | C32: Benchmark
B33: Calculated for weekly; Analytics Leadership-> KPI alerts -> HH Medicare for monthly only | C33: 0.1 | D33: HH/Palliative | E33: =+E30/E7 -> 0.37762238 | F33: =+F30/F7 -> 0.26174497 | G33: =+G30/G7 -> 0.42068966 | H33: =+H30/H7 -> 0.25974026 | I33: =+I30/I7 -> 0.33121019 | J33: 0.529 | K33: =13/K7 -> 0.08496732 | L33: =14/L7 -> 0.092105263 | M33: =10/M7 -> 0.067114094 | N33: =12/N7 -> 0.08 | O33: 0.588 | P33: =P30/P7 -> 0.086666667 | Q33: =Q30/Q7 -> 0.071895425 | R33: =R30/R7 -> 0.051282051 | S33: =S30/S7 -> 0.080246914 | T33: 0.494 | U33: =U30/U7 -> 0.051282051 | V33: =V30/V8 -> 0.11278195 | W33: =W30/W8 -> 0.082191781 | X33: =X30/X8 -> 0.044585987 | Y33: =Y30/Y8 -> 0.079545455 | Z33: 0.974 | AA33: =AA30/AA7 -> 0.15454545 | AB33: =AB30/AB7 -> 0.098039216 | AC33: =AC30/AC7 -> 0.073684211 | AD33: =AD30/AD7 -> 0.11363636 | AE33: 1 | AF33: =AF30/AF7 -> 0.060240964 | AG33: =AG30/AG7 -> 0.1038961 | AH33: =AH30/AH7 -> 0.12676056 | AI33: =AI30/AI7 -> 0.11594203 | AJ33: 1 | AK33: =AK30/AK7 -> 0.092307692 | AL33: =AL30/AL7 -> 0.15625 | AM33: =AM30/AM7 -> 0.063492063 | AN33: =AN30/AN7 -> 0.13114754 | AO33: =AO30/AO7 -> 0.051724138 | AP33: 0.929 | AQ33: =AQ30/AQ7 -> 0.12727273 | AR33: =AR30/AR7 -> 0.094339623 | AS33: =AS30/AS7 -> 0.094339623 | AT33: =AT30/AT7 -> 0.096153846 | AU33: 0.9 | AV33: =AV30/AV7 -> 0.1509434 | AW33: =AW30/AW7 -> 0.11764706 | AX33: =AX30/AX7 -> 0.083333333 | AY33: =AY30/AY7 -> 0.083333333 | AZ33: 0.606 | BA33: =BA30/BA7 -> 0.035087719 | BB33: =BB30/BB7 -> 0.027777778 | BC33: =BC30/BC7 -> 0.036144578 | BD33: =BD30/BD7 -> 0.043478261 | BE33: =BE30/BE7 -> 0.028037383 | BF33: 0.14 | BG33: =BG30/BG7 -> 0.06779661 | BH33: =BH30/BH7 -> 0.014705882 | BI33: =BI30/BI7 -> 0.054054054 | BJ33: =BJ30/BJ7 -> 0.025806452 | BK33: 0.196 | BL33: =(BL30+BL31)/BL9 -> 0.0625 | BM33: =(BM30+BM31)/BM9 -> 0.043010753 | BN33: =(BN30+BN31)/BN9 -> 0.051851852 | BO33: =(BO30+BO31)/BO9 -> 0.076628352 | BP33: =(BP30+BP31)/BP9 -> 0.040322581 | BQ33: 0.478 | BR33: =(BR30+BR31)/BR9 -> 0.067510549 | BS33: =(BS30+BS31)/BS9 -> 0.090128755 | BT33: =(BT30+BT31)/BT9 -> 0.086206897 | BU33: =(BU30+BU31)/BU9 -> 0.067510549 | BV33: 0.453 | BW33: =(BW30+BW31)/BW9 -> 0.052845528 | BX33: =(BX30+BX31)/BX9 -> 0.052 | BY33: =(BY30+BY31)/BY9 -> 0.062992126 | BZ33: =(BZ30+BZ31)/BZ9 -> 0.046692607 | CA33: 0.376 | CB33: =(CB30+CB31)/CB9 -> 0.039215686 | CC33: =(CC30+CC31)/CC9 -> 0.058365759 | CD33: =(CD30+CD31)/CD9 -> 0.08984375 | CE33: =(CE30+CE31)/CE9 -> 0.068548387 | CF33: 0.452 | CG33: =(CG30+CG31)/CG9 -> 0.065306122 | CH33: =(CH30+CH31)/CH9 -> 0.082987552 | CI33: =(CI30+CI31)/CI9 -> 0.046218487 | CJ33: =(CJ30+CJ31)/CJ9 -> 0.067226891 | CK33: =(CK30+CK31)/CK9 -> 0.056 | CL33: 0.447
B34: Calculated for weekly; Analytics Leadership-> KPI alerts -> HH Medicare for monthly only | C34: 0.1 | D34: Palliative | E34: =+E31/E8 -> 0.376 | F34: =+F31/F8 -> 0.32330827 | G34: =+G31/G8 -> 0.39097744 | H34: =+H31/H8 -> 0.31851852 | I34: =+I31/I8 -> 0.40163934 | J34: 0.362 | K34: =4/K8 -> 0.03539823 | L34: =9/L8 -> 0.080357143 | M34: =8/M8 -> 0.07079646 | N34: =6/N8 -> 0.052173913 | O34: 0.403 | P34: =P31/P8 -> 0.0625 | Q34: =Q31/Q8 -> 0.07826087 | R34: =R31/R8 -> 0.050847458 | S34: =S31/S8 -> 0.07826087 | T34: 0.523 | U34: =U31/U8 -> 0.057377049 | V34: =V31/V9 -> 0.061151079 | W34: =W31/W9 -> 0.010600707 | X34: =X31/X9 -> 0.034843206 | Y34: =Y31/Y9 -> 0.013422819 | Z34: 0.241 | AA34: =AA31/AA8 -> 0.027472527 | AB34: =AB31/AB8 -> 0.047368421 | AC34: =AC31/AC8 -> 0.051546392 | AD34: =AD31/AD8 -> 0.050505051 | AE34: 0.319 | AF34: =AF31/AF8 -> 0.10309278 | AG34: =AG31/AG8 -> 0.063157895 | AH34: =AH31/AH8 -> 0.072916667 | AI34: =AI31/AI8 -> 0.065 | AJ34: 0.447 | AK34: =AK31/AK8 -> 0.046728972 | AL34: =AL31/AL8 -> 0.065116279 | AM34: =AM31/AM8 -> 0.063063063 | AN34: =AN31/AN8 -> 0.079646018 | AO34: =AO31/AO8 -> 0.082608696 | AP34: 0.519 | AQ34: =AQ31/AQ8 -> 0.088983051 | AR34: =AR31/AR8 -> 0.055319149 | AS34: =AS31/AS8 -> 0.069868996 | AT34: =AT31/AT8 -> 0.09009009 | AU34: 0.552 | AV34: =AV31/AV8 -> 0.041474654 | AW34: =AW31/AW8 -> 0.068493151 | AX34: =AX31/AX8 -> 0.062780269 | AY34: =AY31/AY8 -> 0.073732719 | AZ34: 0.514 | BA34: =BA31/BA8 -> 0.09223301 | BB34: =BB31/BB8 -> 0.069518717 | BC34: =BC31/BC8 -> 0.097142857 | BD34: =BD31/BD8 -> 0.094117647 | BE34: =BE31/BE8 -> 0.093167702 | BF34: 0.83 | BG34: =BG31/BG8 -> 0.090322581 | BH34: =BH31/BH8 -> 0.10958904 | BI34: =BI31/BI8 -> 0.11428571 | BJ34: =BJ31/BJ8 -> 0.090909091 | BK34: 0.938
A35: Total Discharges | C35: Benchmark
B36: Home Health WAAR report - weekly ending Sunday | C36: 5 | D36: HH | H36: 6 | I36: 10 | J36: 52 | K36: 10 | L36: 8 | M36: 9 | N36: 8 | O36: 37 | P36: 8 | Q36: 9 | R36: 5 | S36: 9 | T36: 38 | U36: 13 | V36: 8 | W36: 8 | X36: 6 | Y36: 10 | Z36: 39 | AA36: 9 | AB36: 6 | AC36: 7 | AD36: 7 | AE36: 32 | AF36: 3 | AG36: 7 | AH36: 2 | AI36: 3 | AJ36: 18 | AK36: 2 | AL36: 1 | AM36: 2 | AN36: 3 | AO36: 4 | AP36: 9 | AQ36: 0 | AR36: 2 | AS36: 2 | AT36: 1 | AU36: 7 | AV36: 3 | AW36: 3 | AX36: 3 | AY36: 3 | AZ36: 13 | BA36: 3 | BB36: 4 | BC36: 1 | BD36: 3 | BE36: 9 | BF36: 19 | BG36: 8 | BH36: 4 | BI36: 12 | BJ36: 8 | BK36: 34 | BL36: 18 | BM36: 10 | BN36: 18 | BO36: 10 | BP36: 16 | BQ36: 69 | BR36: 15 | BS36: 13 | BT36: 8 | BU36: 10 | BV36: 49 | BW36: 11 | BX36: 15 | BY36: 8 | BZ36: 7 | CA36: 41 | CB36: 13 | CC36: 18 | CD36: 11 | CE36: 12 | CF36: 54 | CG36: 7 | CH36: 6 | CI36: 3 | CJ36: 5 | CK36: 3 | CL36: 18
B37: Home Health WAAR report - weekly ending Sunday | C37: 5 | D37: Palliative | H37: 4 | I37: 10 | J37: 44 | K37: 14 | L37: 9 | M37: 12 | N37: 8 | O37: 45 | P37: 8 | Q37: 4 | R37: 8 | S37: 9 | T37: 35 | U37: 11 | V37: 10 | W37: 8 | X37: 8 | Y37: 8 | Z37: 40 | AA37: 11 | AB37: 14 | AC37: 15 | AD37: 9 | AE37: 53 | AF37: 22 | AG37: 12 | AH37: 17 | AI37: 7 | AJ37: 67 | AK37: 8 | AL37: 5 | AM37: 13 | AN37: 7 | AO37: 11 | AP37: 42 | AQ37: 12 | AR37: 20 | AS37: 17 | AT37: 16 | AU37: 64 | AV37: 17 | AW37: 9 | AX37: 15 | AY37: 11 | AZ37: 54 | BA37: 19 | BB37: 19 | BC37: 10 | BD37: 10 | BE37: 12 | BF37: 64 | BG37: 8 | BH37: 4 | BI37: 6 | BJ37: 4 | BK37: 24 | BL37: 7 | BM37: 15 | BN37: 6 | BO37: 10 | BP37: 9 | BQ37: 40 | BR37: 12 | BS37: 10 | BT37: 6 | BU37: 5 | BV37: 35 | BW37: 6 | BX37: 3 | BY37: 4 | BZ37: 10 | CA37: 23 | CB37: 8 | CC37: 6 | CD37: 11 | CE37: 11 | CF37: 36 | CG37: 12 | CH37: 15 | CI37: 18 | CJ37: 7 | CK37: 8 | CL37: 54
D38: Total | J38: =+J37+J36 -> 96 | O38: =+O37+O36 -> 82 | T38: =+T37+T36 -> 73 | Z38: =+Z37+Z36 -> 79 | AA38: =+AA37+AA36 -> 20 | AB38: =+AB37+AB36 -> 20 | AC38: =+AC37+AC36 -> 22 | AD38: =+AD37+AD36 -> 16 | AE38: =+AE37+AE36 -> 85 | AF38: =+AF37+AF36 -> 25 | AG38: =+AG37+AG36 -> 19 | ... AJ38: =+AJ37+AJ36 -> 85 | AK38: =AK36+AK37 -> 10 | AL38: =AL36+AL37 -> 6 | AM38: =AM36+AM37 -> 15 | AN38: =AN36+AN37 -> 10 | AO38: =AO36+AO37 -> 15 | AP38: =+AP37+AP36 -> 51 | AQ38: =AQ36+AQ37 -> 12 | AR38: =AR36+AR37 -> 22 | AS38: =AS36+AS37 -> 19 | AT38: =AT36+AT37 -> 17 | AU38: =+AU37+AU36 -> 71 | AV38: =AV36+AV37 -> 20 | AW38: =AW36+AW37 -> 12 | AX38: =AX36+AX37 -> 18 | AY38: =AY36+AY37 -> 14 | AZ38: =+AZ37+AZ36 -> 67 | BA38: =BA36+BA37 -> 22 | BB38: =BB36+BB37 -> 23 | BC38: =BC36+BC37 -> 11 | BD38: =BD36+BD37 -> 13 | BE38: =BE36+BE37 -> 21 | BF38: =+BF37+BF36 -> 83 | BG38: =BG36+BG37 -> 16 | BH38: =BH36+BH37 -> 8 | BI38: =BI36+BI37 -> 18 | BJ38: =BJ36+BJ37 -> 12 | BK38: =+BK37+BK36 -> 58 | BL38: =BL36+BL37 -> 25 | BM38: =BM36+BM37 -> 25 | BN38: =BN36+BN37 -> 24 | BO38: =BO36+BO37 -> 20 | BP38: =BP36+BP37 -> 25 | BQ38: =+BQ37+BQ36 -> 109 | BR38: =BR36+BR37 -> 27 | BS38: =BS36+BS37 -> 23 | BT38: =BT36+BT37 -> 14 | BU38: =BU36+BU37 -> 15 | BV38: =+BV37+BV36 -> 84 | BW38: =BW36+BW37 -> 17 | BX38: =BX36+BX37 -> 18 | BY38: =BY36+BY37 -> 12 | BZ38: =BZ36+BZ37 -> 17 | CA38: =+CA37+CA36 -> 64 | CB38: =CB36+CB37 -> 21 | CC38: =CC36+CC37 -> 24 | CD38: =CD36+CD37 -> 22 | CE38: =CE36+CE37 -> 23 | CF38: =+CF37+CF36 -> 90 | CG38: =CG36+CG37 -> 19 | CH38: =CH36+CH37 -> 21 | CI38: =CI36+CI37 -> 21 | CJ38: =CJ36+CJ37 -> 12 | CK38: =CK36+CK37 -> 11 | CL38: =+CL37+CL36 -> 72
B39: Hospice WAAR report - weekly ending Sunday | C39: 2 | D39: Hospice OC | E39: 14 | F39: 20 | G39: 17 | H39: 17 | I39: 28 | J39: 26 | K39: 1 | L39: 7 | M39: 4 | N39: 5 | O39: 17 | P39: 3 | Q39: 1 | R39: 8 | S39: 8 | T39: 22 | U39: 4 | V39: 5 | W39: 8 | X39: 5 | Y39: 10 | Z39: 28 | AA39: 6 | AB39: 10 | AC39: 3 | AD39: 5 | AE39: 27 | AF39: 5 | AG39: 2 | AH39: 11 | AI39: 7 | AJ39: 25 | AK39: 11 | AL39: 3 | AM39: 3 | AN39: 6 | AO39: 5 | AP39: 26 | AQ39: 9 | AR39: =7 -> 7 | AS39: 4 | AT39: 3 | AU39: 28 | AV39: 7 | AW39: 5 | AX39: 4 | AY39: 9 | AZ39: 26 | BA39: 5 | BB39: 3 | BC39: 8 | BD39: 7 | BE39: 6 | BF39: 24 | BG39: 7 | BH39: 6 | BI39: 7 | BJ39: 3 | BK39: 25 | BL39: 3 | BM39: 6 | BN39: 7 | BO39: 3 | BP39: 5 | BQ39: 19 | BR39: 5 | BS39: 5 | BT39: 6 | BU39: 6 | BV39: 24 | BW39: 5 | BX39: 5 | BY39: 5 | BZ39: 7 | CA39: 23 | CB39: 6 | CC39: 9 | CD39: 8 | CE39: 6 | CF39: 29 | CG39: 2 | CH39: 3 | CI39: 10 | CJ39: 7 | CK39: 6 | CL39: 26
B40: Hospice WAAR report - weekly ending Sunday | C40: 1 | D40: Hospice IE | H40: 3 | I40: 3 | J40: 6 | K40: 1 | L40: 0 | M40: 1 | N40: 1 | O40: 2 | P40: 0 | Q40: 4 | R40: 0 | S40: 3 | T40: 9 | U40: 1 | V40: 2 | W40: 1 | X40: 0 | Y40: 3 | Z40: 4 | AA40: 1 | AB40: 1 | AC40: 0 | AD40: 0 | AE40: 4 | AF40: 2 | AG40: 2 | AH40: 2 | AI40: 2 | AJ40: 10 | AK40: 3 | AL40: 0 | AM40: 3 | AN40: 3 | AO40: 4 | AP40: 11 | AQ40: 0 | AR40: 1 | AS40: 2 | AT40: 2 | AU40: =4+1 -> 5 | AV40: 2 | AW40: 2 | AX40: 1 | AY40: 2 | AZ40: 9 | BA40: 3 | BB40: 2 | BC40: 3 | BD40: 3 | BE40: 2 | BF40: 11 | BG40: 3 | BH40: 4 | BI40: 2 | BJ40: 4 | BK40: =0+13 -> 13 | BL40: 1 | BM40: 1 | BN40: 1 | BO40: 1 | BP40: 4 | BQ40: 4 | BR40: 2 | BS40: 2 | BT40: 5 | BU40: 2 | BV40: 13 | BW40: 1 | BX40: 3 | BY40: 2 | BZ40: 3 | CA40: 9 | CB40: 1 | CC40: 0 | CD40: 1 | CE40: 2 | CF40: 4 | CG40: 0 | CH40: 1 | CI40: 1 | CJ40: 2 | CK40: 3 | CL40: 6
B41: Hospice WAAR report - weekly ending Sunday | C41: 1 | D41: Hospice SGV | H41: 1 | I41: 6 | J41: 10 | K41: 3 | L41: 1 | M41: 2 | N41: 1 | O41: 7 | P41: 2 | Q41: 1 | R41: 1 | S41: 2 | T41: 6 | U41: 2 | V41: 4 | W41: 1 | X41: 1 | Y41: 1 | Z41: 8 | AA41: 0 | AB41: 0 | AC41: 1 | AD41: 0 | AE41: 1 | AF41: 1 | AG41: 0 | AH41: 2 | AI41: 5 | AJ41: 8 | AK41: 1 | AL41: 1 | AM41: 1 | AN41: 0 | AO41: 3 | AP41: =5+1 -> 6 | AQ41: 2 | AR41: 1 | AS41: 3 | AT41: =3+1 -> 4 | AU41: =10+1 -> 11 | AV41: 1 | AW41: 2 | AX41: 1 | AY41: 4 | AZ41: 9 | BA41: 3 | BB41: 2 | BC41: 2 | BD41: 1 | BE41: 1 | BF41: 8 | BG41: 1 | BH41: 1 | BI41: 0 | BJ41: 2 | BK41: 4 | BL41: 1 | BM41: 1 | BN41: 0 | BO41: 1 | BP41: 0 | BQ41: 2 | BR41: 1 | BS41: 0 | BT41: 0 | BU41: 1 | BV41: 2 | BW41: 3 | BX41: 1 | BY41: 3 | BZ41: 2 | CA41: 9 | CB41: 0 | CC41: 0 | CD41: 0 | CE41: 1 | CF41: 2 | CG41: 1 | CH41: 3 | CI41: 0 | CJ41: 0 | CK41: 1 | CL41: 4
B42: Hospice WAAR report - weekly ending Sunday | C42: 4 | D42: Hospice Desert | H42: 5 | I42: 20 | J42: 37 | K42: 7 | L42: 10 | M42: 9 | N42: 0 | O42: 26 | P42: 5 | Q42: 11 | R42: 4 | S42: 8 | T42: 31 | U42: 9 | V42: 2 | W42: 7 | X42: 2 | Y42: 8 | Z42: 20 | AA42: 8 | AB42: 2 | AC42: 6 | AD42: 6 | AE42: 27 | AF42: 3 | AG42: 4 | AH42: 8 | AI42: 5 | AJ42: 21 | AK42: 7 | AL42: 2 | AM42: 6 | AN42: 3 | AO42: 7 | AP42: 22 | AQ42: 9 | AR42: 5 | AS42: 8 | AT42: 7 | AU42: 33 | AV42: 6 | AW42: 3 | AX42: 7 | AY42: 7 | AZ42: 22 | BA42: 2 | BB42: 4 | BC42: 8 | BD42: 3 | BE42: 8 | BF42: 23 | BG42: 7 | BH42: 9 | BI42: 5 | BJ42: 4 | BK42: =4+22 -> 26 | BL42: 8 | BM42: 6 | BN42: 3 | BO42: 7 | BP42: 5 | BQ42: 24 | BR42: 11 | BS42: 5 | BT42: 2 | BU42: 14 | BV42: 35 | BW42: 7 | BX42: 5 | BY42: 8 | BZ42: 3 | CA42: 23 | CB42: 10 | CC42: 4 | CD42: 8 | CE42: 3 | CF42: 29 | CG42: 8 | CH42: 9 | CI42: 4 | CJ42: 8 | CK42: 8 | CL42: 30
D43: Total | J43: =SUM(J39:J42) -> 79 | O43: =SUM(O39:O42) -> 52 | T43: =SUM(T39:T42) -> 68 | Z43: =SUM(Z39:Z42) -> 60 | AA43: =SUM(AA39:AA42) -> 15 | AB43: =SUM(AB39:AB42) -> 13 | AC43: =SUM(AC39:AC42) -> 10 | AD43: =SUM(AD39:AD42) -> 11 | AE43: =SUM(AE39:AE42) -> 59 | AF43: =SUM(AF39:AF42) -> 11 | AG43: =SUM(AG39:AG42) -> 8 | ... BY43: =SUM(BY39:BY42) -> 18 | BZ43: =SUM(BZ39:BZ41) -> 12 | CA43: =SUM(CA39:CA42) -> 64 | CB43: =SUM(CB39:CB41) -> 7 | CC43: =SUM(CC39:CC41) -> 9 | CD43: =SUM(CD39:CD41) -> 9 | CE43: =SUM(CE39:CE41) -> 9 | CF43: =SUM(CF39:CF42) -> 64 | CG43: =SUM(CG39:CG41) -> 3 | CH43: =SUM(CH39:CH41) -> 7 | CI43: =SUM(CI39:CI41) -> 11 | CJ43: =SUM(CJ39:CJ41) -> 9 | CK43: =SUM(CK39:CK41) -> 10 | CL43: =SUM(CL39:CL42) -> 66
A44: Live Discharge | C44: Benchmark
B45: Hospice WAAR report - weekly ending Sunday; Key Metrics Report - Monthly | D45: Hospice OC | E45: 3 | F45: 5 | G45: 6 | H45: 7 | I45: 11 | J45: 9 | K45: 0 | L45: 3 | M45: 0 | N45: 1 | O45: 5 | P45: 0 | Q45: 0 | R45: 3 | S45: 2 | T45: 5 | U45: 0 | V45: 0 | W45: 1 | X45: 2 | Y45: 1 | Z45: 4 | AA45: 0.01 | AB45: 5 | AC45: 1 | AD45: 1 | AE45: 7 | AF45: 3 | AG45: 0 | AH45: 5 | AI45: 2 | AJ45: 10 | AK45: 4 | AL45: 1 | AM45: 1 | AN45: 2 | AO45: 3 | AP45: 9 | AQ45: 1 | AR45: 2 | AS45: 1 | AT45: 2 | AU45: 10 | AV45: 3 | AW45: 2 | AX45: 2 | AY45: 1 | AZ45: 9 | BA45: 3 | BB45: 1 | BC45: 1 | BD45: 2 | BE45: 2 | BF45: 6 | BG45: 1 | BH45: 0 | BI45: 3 | BJ45: 0 | BK45: 5 | BL45: 1 | BM45: 2 | BN45: 3 | BO45: 1 | BP45: 1 | BQ45: 7 | BR45: 1 | BS45: 1 | BT45: 1 | BU45: 0 | BV45: 3 | BW45: 4 | BX45: 2 | BY45: 1 | BZ45: 4 | CA45: 11 | CB45: 2 | CC45: 3 | CD45: 4 | CE45: 1 | CF45: 10 | CG45: 1 | CH45: 0 | CI45: 2 | CJ45: 1 | CK45: 1 | CL45: 5
B46: Hospice WAAR report - weekly ending Sunday; Key Metrics Report - Monthly | D46: Hospice IE | H46: 0 | I46: 1 | J46: 0 | K46: 0 | L46: 0 | M46: 0 | N46: 0 | O46: 0 | P46: 0 | Q46: 1 | R46: 0 | S46: 0 | T46: 1 | U46: 0 | V46: 1 | W46: 0 | X46: 0 | Y46: 1 | Z46: 1 | AA46: 1 | AB46: 0 | AC46: 0 | AD46: 0 | AE46: 2 | AF46: 0 | AG46: 1 | AH46: 0 | AI46: 0 | AJ46: 1 | AK46: 0 | AL46: 0 | AM46: 1 | AN46: 1 | AO46: 1 | AP46: 3 | AQ46: 0 | AR46: 0 | AS46: 1 | AT46: 1 | AU46: =2 -> 2 | AV46: 0 | AW46: 2 | AX46: 0 | AY46: 0 | AZ46: 2 | BA46: 0 | BB46: 0 | BC46: 1 | BD46: 1 | BE46: 0 | BF46: 2 | BG46: 1 | BH46: 1 | BI46: 0 | BJ46: 0 | BK46: =0+2 -> 2 | BL46: 0 | BM46: 0 | BN46: 1 | BO46: 0 | BP46: 1 | BQ46: 1 | BR46: 0 | BS46: 1 | BT46: 1 | BU46: 0 | BV46: 3 | BW46: 0 | BX46: 1 | BY46: 0 | BZ46: 0 | CA46: 1 | CB46: 1 | CC46: 0 | CD46: 0 | CE46: 1 | CF46: 2 | CG46: 0 | CH46: 0 | CI46: 0 | CJ46: 1 | CK46: 3 | CL46: 3
B47: Hospice WAAR report - weekly ending Sunday; Key Metrics Report - Monthly | D47: Hospice SGV | I47: 4 | J47: 4 | K47: 0 | L47: 0 | M47: 0 | N47: 0 | O47: 0 | P47: 0 | Q47: 1 | R47: 1 | S47: 0 | T47: 2 | U47: 0 | V47: 0 | W47: 0 | X47: 0 | Y47: 0 | Z47: 0 | AA47: 0 | AB47: 0 | AC47: 0 | AD47: 0 | AE47: 0 | AF47: 0 | AG47: 0 | AH47: 0 | AI47: 1 | AJ47: =1+0 -> 1 | AK47: 0 | AL47: 0 | AM47: 0 | AN47: 0 | AO47: 0 | AP47: =1+0 -> 1 | AQ47: 0 | AR47: 1 | AS47: 2 | AT47: 0 | AU47: =3 -> 3 | AV47: 0 | AW47: 0 | AX47: 1 | AY47: 0 | AZ47: 2 | BA47: 2 | BB47: 2 | BC47: 0 | BD47: 0 | BE47: 1 | BF47: 4 | BG47: 0 | BH47: 0 | BI47: 0 | BJ47: 0 | BK47: 0 | BL47: 0 | BM47: 0 | BN47: 0 | BO47: 0 | BP47: 0 | BQ47: 0 | BR47: 0 | BS47: 0 | BT47: 0 | BU47: 0 | BV47: 0 | BW47: 3 | BX47: 0 | BY47: 0 | BZ47: 0 | CA47: 3 | CB47: 0 | CC47: 0 | CD47: 0 | CE47: 0 | CF47: 0 | CG47: 0 | CH47: 1 | CI47: 0 | CJ47: 0 | CK47: 0 | CL47: 1
B48: Hospice WAAR report - weekly ending Sunday; Key Metrics Report - Monthly | D48: Hospice Desert | H48: 2 | I48: 4 | J48: 5 | K48: 2 | L48: 3 | M48: 0 | N48: 0 | O48: 5 | P48: 1 | Q48: 1 | R48: 0 | S48: 2 | T48: 5 | U48: 2 | V48: 0 | W48: 3 | X48: 0 | Y48: 3 | Z48: 6 | AA48: 0 | AB48: 0 | AC48: 1 | AD48: 1 | AE48: 3 | AF48: 1 | AG48: 0 | AH48: 2 | AI48: 0 | AJ48: 3 | AK48: 2 | AL48: 1 | AM48: 0 | AN48: 0 | AO48: 1 | AP48: 3 | AQ48: 2 | AR48: 0 | AS48: 3 | AT48: 3 | AU48: =11 -> 11 | AV48: 5 | AW48: 1 | AX48: 3 | AY48: 2 | AZ48: 10 | BA48: 1 | BB48: 0 | BC48: 0 | BD48: 0 | BE48: 2 | BF48: 2 | BG48: 1 | BH48: 5 | BI48: 0 | BJ48: 2 | BK48: =3+5 -> 8 | BL48: 2 | BM48: 1 | BN48: 1 | BO48: 1 | BP48: 0 | BQ48: 5 | BR48: 2 | BS48: 1 | BT48: 2 | BU48: 2 | BV48: 7 | BW48: 1 | BX48: 0 | BY48: 3 | BZ48: 0 | CA48: 4 | CB48: 3 | CC48: 2 | CD48: 2 | CE48: 0 | CF48: 7 | CG48: 2 | CH48: 3 | CI48: 1 | CJ48: 2 | CK48: 1 | CL48: 9
A49: Total Patient Days | C49: Benchmark
B50: multiply ADC by days in month or weekly - 7 | D50: Hospice OC | E50: =+E10*31 -> 2619.5 | F50: =+F10*30 -> 2685 | G50: =+G10*31 -> 2724.9 | H50: =+H10*30 -> 2634 | I50: =+I10*31 -> 2746.6 | J50: 2503 | K50: =+K10*7 -> 546 | L50: =+L10*7 -> 560 | M50: =+M10*7 -> 567 | N50: =+N10*7 -> 574 | O50: 2214 | P50: =+P10*7 -> 574 | Q50: =+Q10*7 -> 602 | R50: =+R10*7 -> 616 | S50: =+S10*7 -> 616 | T50: 2634 | U50: =+U10*7 -> 623 | V50: =+V10*7 -> 623 | W50: =+W10*7 -> 637 | X50: =+X10*7 -> 644 | Y50: =+Y10*7 -> 616 | Z50: 2675 | AA50: =+AA10*7 -> 616 | AB50: =+AB10*7 -> 651 | AC50: =+AC10*7 -> 644 | AD50: =+AD10*7 -> 658 | AE50: 2816 | AF50: =+AF10*7 -> 651 | AG50: =+AG10*7 -> 665 | AH50: =+AH10*7 -> 686 | AI50: =+AI10*7 -> 686 | AJ50: =2885+60 -> 2945 | AK50: =+AK10*7 -> 693 | AL50: =+AL10*7 -> 658 | AM50: =+AM10*7 -> 672 | AN50: =+AN10*7 -> 700 | AO50: =+AO10*7 -> 707 | AP50: 3077 | AQ50: =+AQ10*7 -> 714 | AR50: =+AR10*7 -> 700 | AS50: =+AS10*7 -> 714 | AT50: =+AT10*7 -> 742 | AU50: 3164 | AV50: =+AV10*7 -> 756 | AW50: =+AW10*7 -> 777 | AX50: =+AX10*7 -> 784 | AY50: =+AY10*7 -> 777 | AZ50: 3260 | BA50: =+BA10*7 -> 756 | BB50: =+BB10*7 -> 770 | BC50: =+BC10*7 -> 798 | BD50: =+BD10*7 -> 770 | BE50: =+BE10*7 -> 791 | BF50: 3414 | BG50: =+BG10*7 -> 770 | BH50: =+BH10*7 -> 784 | BI50: =+BI10*7 -> 784 | BJ50: =+BJ10*7 -> 770 | BK50: 3295 | BL50: =+BL10*7 -> 777 | BM50: =+BM10*7 -> 798 | BN50: =+BN10*7 -> 819 | BO50: =+BO10*7 -> 819 | BP50: =+BP10*7 -> 826 | BQ50: 3555 | BR50: =+BR10*7 -> 819 | BS50: =+BS10*7 -> 819 | BT50: =+BT10*7 -> 819 | BU50: =+BU10*7 -> 805 | BV50: 3578 | BW50: =+BW10*7 -> 812 | BX50: =+BX10*7 -> 847 | BY50: =+BY10*7 -> 854 | BZ50: =+BZ10*7 -> 861 | CA50: 3359 | CB50: =+CB10*7 -> 896 | CC50: =+CC10*7 -> 896 | CD50: =+CD10*7 -> 875 | CE50: =+CE10*7 -> 868 | CF50: 3881 | CG50: =+CG10*7 -> 875 | CH50: =+CH10*7 -> 875 | CI50: =+CI10*7 -> 875 | CJ50: =+CJ10*7 -> 840 | CK50: =+CK10*7 -> 840 | CL50: 3697
B51: multiply ADC by days in month or weekly - 7 | D51: Hospice IE | E51: =+E11*31 -> 1102.98 | F51: =+F11*30 -> 972.9 | G51: =+G11*31 -> 1114.14 | H51: =+H11*30 -> 945 | I51: =+I11*31 -> 998.2 | J51: 1136 | K51: =+K11*7 -> 252 | L51: =+L11*7 -> 252 | M51: =+M11*7 -> 266 | N51: =+N11*7 -> 256.2 | O51: 1054 | P51: =+P11*7 -> 253.4 | Q51: =+Q11*7 -> 238 | R51: =+R11*7 -> 238 | S51: =+S11*7 -> 231 | T51: 1096 | U51: =+U11*7 -> 224 | V51: =+V11*7 -> 224 | W51: =+W11*7 -> 224 | X51: =+X11*7 -> 231 | Y51: =+Y11*7 -> 231 | Z51: 999 | AA51: =+AA11*7 -> 217 | AB51: =+AB11*7 -> 217 | AC51: =+AC11*7 -> 231 | AD51: =+AD11*7 -> 245 | AE51: 1048 | AF51: =+AF11*7 -> 245 | AG51: =+AG11*7 -> 259 | AH51: =+AH11*7 -> 259 | AI51: =+AI11*7 -> 266 | AJ51: =1102+30 -> 1132 | AK51: =+AK11*7 -> 259 | AL51: =+AL11*7 -> 273 | AM51: =+AM11*7 -> 273 | AN51: =+AN11*7 -> 273 | AO51: =+AO11*7 -> 273 | AP51: =1205+31 -> 1236 | AQ51: =+AQ11*7 -> 294 | AR51: =+AR11*7 -> 315 | AS51: =+AS11*7 -> 336 | AT51: =+AT11*7 -> 329 | AU51: =1352+43 -> 1395 | AV51: =+AV11*7 -> 322 | AW51: =+AW11*7 -> 322 | AX51: =+AX11*7 -> 336 | AY51: =+AY11*7 -> 329 | AZ51: =1369+30 -> 1399 | BA51: =+BA11*7 -> 322 | BB51: =+BB11*7 -> 308 | BC51: =+BC11*7 -> 315 | BD51: =+BD11*7 -> 315 | BE51: =+BE11*7 -> 315 | BF51: 1387 | BG51: =+BG11*7 -> 322 | BH51: =+BH11*7 -> 308 | BI51: =+BI11*7 -> 301 | BJ51: =+BJ11*7 -> 301 | BK51: =30+1282 -> 1312 | BL51: =+BL11*7 -> 287 | BM51: =+BM11*7 -> 301 | BN51: =+BN11*7 -> 308 | BO51: =+BO11*7 -> 308 | BP51: =+BP11*7 -> 308 | BQ51: 1340 | BR51: =+BR11*7 -> 294 | BS51: =+BS11*7 -> 280 | BT51: =+BT11*7 -> 273 | BU51: =+BU11*7 -> 266 | BV51: =1209+31 -> 1240 | BW51: =+BW11*7 -> 273 | BX51: =+BX11*7 -> 294 | BY51: =+BY11*7 -> 294 | BZ51: =+BZ11*7 -> 301 | CA51: 1157 | CB51: =+CB11*7 -> 308 | CC51: =+CC11*7 -> 308 | CD51: =+CD11*7 -> 315 | CE51: =+CE11*7 -> 322 | CF51: 1393 | CG51: =+CG11*7 -> 322 | CH51: =+CH11*7 -> 322 | CI51: =+CI11*7 -> 329 | CJ51: =+CJ11*7 -> 350 | CK51: =+CK11*7 -> 364 | CL51: 1443
B52: multiply ADC by days in month or weekly - 7 | D52: Hospice SGV | E52: =+E12*31 -> 637.05 | F52: =+F12*30 -> 686.1 | G52: =+G12*31 -> 850.95 | H52: =+H12*30 -> 669.9 | I52: =+I12*31 -> 796.7 | J52: =+J12*31 -> 793.6 | K52: =+K12*7 -> 171.5 | L52: =+L12*7 -> 175 | M52: =+M12*7 -> 168 | N52: =+N12*7 -> 182 | O52: 680 | P52: =+P12*7 -> 166.6 | Q52: =+Q12*7 -> 175 | R52: =+R12*7 -> 182 | S52: =+S12*7 -> 189 | T52: 770 | U52: =+U12*7 -> 203 | V52: =+V12*7 -> 210 | W52: =+W12*7 -> 196 | X52: =+X12*7 -> 196 | Y52: =+Y12*7 -> 189 | Z52: 864 | AA52: =+AA12*7 -> 189 | AB52: =+AB12*7 -> 203 | AC52: =+AC12*7 -> 217 | AD52: =+AD12*7 -> 217 | AE52: 958 | AF52: =+AF12*7 -> 217 | AG52: =+AG12*7 -> 224 | AH52: =+AH12*7 -> 245 | AI52: =+AI12*7 -> 238 | AJ52: =1018+60 -> 1078 | AK52: =+AK12*7 -> 238 | AL52: =+AL12*7 -> 231 | AM52: =+AM12*7 -> 252 | AN52: =+AN12*7 -> 259 | AO52: =+AO12*7 -> 273 | AP52: =1104+58 -> 1162 | AQ52: =+AQ12*7 -> 266 | AR52: =+AR12*7 -> 259 | AS52: =+AS12*7 -> 259 | AT52: =+AT12*7 -> 259 | AU52: =1123+26 -> 1149 | AV52: =+AV12*7 -> 245 | AW52: =+AW12*7 -> 224 | AX52: =+AX12*7 -> 224 | AY52: =+AY12*7 -> 217 | AZ52: 927 | BA52: =+BA12*7 -> 189 | BB52: =+BB12*7 -> 182 | BC52: =+BC12*7 -> 182 | BD52: =+BD12*7 -> 182 | BE52: =+BE12*7 -> 175 | BF52: 773 | BG52: =+BG12*7 -> 175 | BH52: =+BH12*7 -> 168 | BI52: =+BI12*7 -> 168 | BJ52: =+BJ12*7 -> 175 | BK52: 707 | BL52: =+BL12*7 -> 182 | BM52: =+BM12*7 -> 182 | BN52: =+BN12*7 -> 175 | BO52: =+BO12*7 -> 168 | BP52: =+BP12*7 -> 175 | BQ52: 741 | BR52: =+BR12*7 -> 175 | BS52: =+BS12*7 -> 175 | BT52: =+BT12*7 -> 168 | BU52: =+BU12*7 -> 175 | BV52: 756 | BW52: =+BW12*7 -> 154 | BX52: =+BX12*7 -> 140 | BY52: =+BY12*7 -> 126 | BZ52: =+BZ12*7 -> 126 | CA52: 549 | CB52: =+CB12*7 -> 119 | CC52: =+CC12*7 -> 126 | CD52: =+CD12*7 -> 126 | CE52: =+CE12*7 -> 133 | CF52: 561 | CG52: =+CG12*7 -> 133 | CH52: =+CH12*7 -> 140 | CI52: =+CI12*7 -> 126 | CJ52: =+CJ12*7 -> 126 | CK52: =+CK12*7 -> 147 | CL52: 566
B53: multiply ADC by days in month or weekly - 7 | D53: Hospice Desert | E53: =+E13*31 -> 1869.92 | F53: =+F13*30 -> 1923.9 | G53: =+G13*31 -> 2250.91 | H53: =+H13*30 -> 2052 | I53: =+I13*31 -> 2266.1 | J53: =+J13*31 -> 2263 | K53: =+K13*7 -> 525 | L53: =+L13*7 -> 518 | M53: =+M13*7 -> 518 | N53: =+N13*7 -> 518 | O53: =+O13*28 -> 1990.8 | P53: =+P13*7 -> 567 | Q53: =+Q13*7 -> 602 | R53: =+R13*7 -> 588 | S53: =+S13*7 -> 581 | T53: 2573 | U53: =+U13*7 -> 574 | V53: =+V13*7 -> 595 | W53: =+W13*7 -> 616 | X53: =+X13*7 -> 623 | Y53: =+Y13*7 -> 644 | Z53: 2588 | AA53: =+AA13*7 -> 623 | AB53: =+AB13*7 -> 630 | AC53: =+AC13*7 -> 651 | AD53: =+AD13*7 -> 686 | AE53: 2869 | AF53: =+AF13*7 -> 700 | AG53: =+AG13*7 -> 700 | AH53: =+AH13*7 -> 686 | AI53: =+AI13*7 -> 679 | AJ53: 2949 | AK53: =+AK13*7 -> 665 | AL53: =+AL13*7 -> 672 | AM53: =+AM13*7 -> 686 | AN53: =+AN13*7 -> 686 | AO53: =+AO13*7 -> 721 | AP53: 3013 | AQ53: =+AQ13*7 -> 707 | AR53: =+AR13*7 -> 693 | AS53: =+AS13*7 -> 679 | AT53: =+AT13*7 -> 672 | AU53: =2290+764 -> 3054 | AV53: =+AV13*7 -> 637 | AW53: =+AW13*7 -> 637 | AX53: =+AX13*7 -> 637 | AY53: =+AY13*7 -> 623 | AZ53: 2690 | BA53: =+BA13*7 -> 602 | BB53: =+BB13*7 -> 630 | BC53: =+BC13*7 -> 644 | BD53: =+BD13*7 -> 651 | BE53: =+BE13*7 -> 665 | BF53: 2834 | BG53: =+BG13*7 -> 658 | BH53: =+BH13*7 -> 644 | BI53: =+BI13*7 -> 630 | BJ53: =+BJ13*7 -> 637 | BK53: =1658+1098 -> 2756 | BL53: =+BL13*7 -> 637 | BM53: =+BM13*7 -> 630 | BN53: =+BN13*7 -> 672 | BO53: =+BO13*7 -> 672 | BP53: =+BP13*7 -> 686 | BQ53: 2915 | BR53: =+BR13*7 -> 672 | BS53: =+BS13*7 -> 665 | BT53: =+BT13*7 -> 686 | BU53: =+BU13*7 -> 693 | BV53: 3019 | BW53: =+BW13*7 -> 700 | BX53: =+BX13*7 -> 693 | BY53: =+BY13*7 -> 686 | BZ53: =+BZ13*7 -> 679 | CA53: 2756 | CB53: =+CB13*7 -> 679 | CC53: =+CC13*7 -> 644 | CD53: =+CD13*7 -> 637 | CE53: =+CE13*7 -> 637 | CF53: 2873 | CG53: =+CG13*7 -> 644 | CH53: =+CH13*7 -> 602 | CI53: =+CI13*7 -> 602 | CJ53: =+CJ13*7 -> 581 | CK53: =+CK13*7 -> 574 | CL53: 2561
B54: multiply ADC by days in month or weekly - 7 | D54: All Locations | E54: =SUM(E50:E53) -> 6229.45 | F54: =SUM(F50:F53) -> 6267.9 | G54: =SUM(G50:G53) -> 6940.9 | H54: =SUM(H50:H53) -> 6300.9 | I54: =SUM(I50:I53) -> 6807.6 | J54: =SUM(J50:J53) -> 6695.6 | K54: =SUM(K50:K53) -> 1494.5 | L54: =SUM(L50:L53) -> 1505 | ... N54: =SUM(N50:N53) -> 1530.2 | O54: =+O53+O52+O51+O50 -> 5938.8 | P54: =SUM(P50:P53) -> 1561 | Q54: =SUM(Q50:Q53) -> 1617 | R54: =SUM(R50:R53) -> 1624 | S54: =SUM(S50:S53) -> 1617 | T54: =T50+T51+T52+T53 -> 7073 | U54: =SUM(U50:U53) -> 1624 | V54: =SUM(V50:V53) -> 1652 | W54: =SUM(W50:W53) -> 1673 | X54: =SUM(X50:X53) -> 1694 | Y54: =SUM(Y50:Y53) -> 1680 | Z54: =Z50+Z51+Z52+Z53 -> 7126 | AA54: =SUM(AA50:AA53) -> 1645 | AB54: =SUM(AB50:AB53) -> 1701 | AC54: =SUM(AC50:AC53) -> 1743 | AD54: =SUM(AD50:AD53) -> 1806 | AE54: =AE50+AE51+AE52+AE53 -> 7691 | AF54: =SUM(AF50:AF53) -> 1813 | AG54: =SUM(AG50:AG53) -> 1848 | AH54: =SUM(AH50:AH53) -> 1876 | AI54: =SUM(AI50:AI53) -> 1869 | AJ54: =AJ50+AJ51+AJ52+AJ53 -> 8104 | AK54: =SUM(AK50:AK53) -> 1855 | AL54: =SUM(AL50:AL53) -> 1834 | AM54: =SUM(AM50:AM53) -> 1883 | AN54: =SUM(AN50:AN53) -> 1918 | AO54: =SUM(AO50:AO53) -> 1974 | AP54: =AP50+AP51+AP52+AP53 -> 8488 | AQ54: =SUM(AQ50:AQ53) -> 1981 | AR54: =SUM(AR50:AR53) -> 1967 | AS54: =SUM(AS50:AS53) -> 1988 | AT54: =SUM(AT50:AT53) -> 2002 | AU54: =AU50+AU51+AU52+AU53 -> 8762 | AV54: =SUM(AV50:AV53) -> 1960 | AW54: =SUM(AW50:AW53) -> 1960 | AX54: =SUM(AX50:AX53) -> 1981 | AY54: =SUM(AY50:AY53) -> 1946 | AZ54: =AZ50+AZ51+AZ52+AZ53 -> 8276 | BA54: =SUM(BA50:BA53) -> 1869 | BB54: =SUM(BB50:BB53) -> 1890 | BC54: =SUM(BC50:BC53) -> 1939 | BD54: =SUM(BD50:BD53) -> 1918 | BE54: =SUM(BE50:BE53) -> 1946 | BF54: =BF50+BF51+BF52+BF53 -> 8408 | BG54: =SUM(BG50:BG53) -> 1925 | BH54: =SUM(BH50:BH53) -> 1904 | BI54: =SUM(BI50:BI53) -> 1883 | BJ54: =SUM(BJ50:BJ53) -> 1883 | BK54: =BK50+BK51+BK52+BK53 -> 8070 | BL54: =SUM(BL50:BL53) -> 1883 | BM54: =SUM(BM50:BM53) -> 1911 | BN54: =SUM(BN50:BN53) -> 1974 | BO54: =SUM(BO50:BO53) -> 1967 | BP54: =SUM(BP50:BP53) -> 1995 | BQ54: =BQ50+BQ51+BQ52+BQ53 -> 8551 | BR54: =SUM(BR50:BR53) -> 1960 | BS54: =SUM(BS50:BS53) -> 1939 | BT54: =SUM(BT50:BT53) -> 1946 | BU54: =SUM(BU50:BU53) -> 1939 | BV54: =SUM(BV50:BV53) -> 8593 | BW54: =SUM(BW50:BW53) -> 1939 | BX54: =SUM(BX50:BX53) -> 1974 | BY54: =SUM(BY50:BY53) -> 1960 | ... CL54: =SUM(CL50:CL53) -> 8267
A55: Revenue per Patient Day | C55: Benchmark
B56: Calculated | D56: HH | E56: =+E3/(E7*31) -> 74.781412 | F56: =+F3/(F7*30) -> 77.9434 | G56: =+G3/(G7*31) -> 79.141268 | H56: =+H3/(H7*30) -> 80.436147 | I56: =+I3/(I7*31) -> 77.37107 | J56: =+J3/(J7*31) -> 71.099357 | O56: =+O3/(O7*28) -> 73.596612 | T56: =+T3/(T7*31) -> 83.059032 | Z56: =+Z3/(Z7*30) -> 69.507575 | AE56: =+AE3/(AE7*31) -> 70.407014 | AJ56: =+AJ3/(AJ7*30) -> 73.948718 | AP56: =+AP3/(AP7*31) -> 63.212613 | AQ56: =+AQ3/(AQ7*30) -> 0 | AR56: =+AR3/(AR7*30) -> 0 | AS56: =+AS3/(AS7*30) -> 0 | AT56: =+AT3/(AT7*30) -> 0 | AU56: =+AU3/(AU7*31) -> 17.04544 | AZ56: =+AZ3/(AZ7*30) -> 62.829918 | BF56: 88.16 | BK56: =BK3/(BK7*30) -> 88.233523 | BQ56: =BQ3/(BQ7*31) -> 83.692487 | BV56: =+BV3/(BV7*31) -> 77.825967 | CA56: =+CA3/(CA7*28) -> 75.074102 | CF56: =+CF3/(CF7*28) -> 78.796467 | CL56: =+CL3/(CL7*28) -> 0
B57: Calculated | D57: Palliative | E57: =+E4/(E8*31) -> 76.798452 | F57: =+F4/(F8*30) -> 80.51604 | G57: =+G4/(G8*31) -> 77.300994 | H57: =+H4/(H8*30) -> 77.862716 | I57: =+I4/(I8*31) -> 78.95082 | J57: =+J4/(J8*31) -> 79.082687 | O57: =+O4/(O8*28) -> 80.021185 | T57: =+T4/(T8*31) -> 82.869556 | Z57: =+Z4/(Z8*30) -> 87.721759 | AE57: =+AE4/(AE8*31) -> 89.211187 | AJ57: =+AJ4/(AJ8*30) -> 86.619581 | AP57: =+AP4/(AP8*31) -> 78.843465 | AQ57: =+AQ4/(AQ8*30) -> 0 | AR57: =+AR4/(AR8*30) -> 0 | AS57: =+AS4/(AS8*30) -> 0 | AT57: =+AT4/(AT8*30) -> 0 | AU57: =+AU4/(AU8*31) -> 66.63942 | AZ57: =+AZ4/(AZ8*30) -> 73.410691 | BF57: 66.8 | BK57: =BK4/(BK8*30) -> 65.560147 | BQ57: =BQ4/(BQ8*31) -> 69.171023 | BV57: =+BV4/(BV8*31) -> 75.268387 | CA57: =+CA4/(CA8*28) -> 91.686333 | CF57: =+CF4/(CF8*28) -> 92.238095 | CL57: =+CL4/(CL8*28) -> 0
B58: Calculated | D58: Hospice | E58: =+E5/(E15*31) -> 91.89768 | F58: =+F5/(F15*30) -> 94.118923 | G58: =+G5/(G15*31) -> 91.630048 | H58: =+H5/(H15*30) -> 121.69896 | I58: =+I5/(I15*31) -> 237.15818 | J58: =+J5/(J15*31) -> 209.06382 | O58: =+O5/(O15*28) -> 217.4533 | T58: =+T5/T54 -> 222.95298 | Z58: =+Z5/Z54 -> 217.29046 | AE58: =+AE5/AE54 -> 213.70796 | AJ58: =+AJ5/AJ54 -> 211.69961 | AP58: =+AP5/AP54 -> 211.79571 | AQ58: =+AQ5/AQ54 -> 0 | AR58: =+AR5/AR54 -> 0 | AS58: =+AS5/AS54 -> 0 | AT58: =+AT5/AT54 -> 0 | AU58: =+AU5/AU54 -> 212.66647 | AZ58: =+AZ5/AZ54 -> 210.08658 | BF58: =BF5/BF54 -> 210.74783 | BK58: =BK5/BK54 -> 208.09396 | BQ58: =BQ5/BQ54 -> 210.77371 | BV58: =+BV5/BV54 -> 209.93941 | CA58: =+CA5/CA54 -> 207.25843 | CF58: =+CF5/CF54 -> 207.36392 | CL58: =+CL5/CL54 -> 0
A59: Medicare Discharge Total LOS - Monthly | C59: Benchmark
B60: HCHB Analytics - Hospice Key Metrics - LOS | D60: Hospice OC | E60: 28.4 | F60: 49.7 | G60: 57.7 | H60: 59 | I60: 71.9 | J60: 69.1 | K60: 291.62 | L60: 277.32 | M60: 265.03 | N60: 270.69 | O60: 71.4 | P60: 272.45 | Q60: 262.95 | R60: 260.29 | S60: 247.36 | T60: 90 | U60: 245.25 | V60: 247.39 | W60: 242.62 | X60: 251.91 | Y60: 262.32 | Z60: 48.7 | AA60: 248.15 | AB60: 231.11 | AC60: 235.23 | AD60: 238.79 | AE60: 69.4 | AJ60: 53.8 | AP60: 72.2 | AU60: 32.3 | AZ60: 73 | BF60: 89.3 | BK60: 116.1 | BQ60: 84.6 | BV60: 116.8 | CA60: 111.1 | CF60: 101.9
B61: HCHB Analytics - Hospice Key Metrics - LOS | D61: Hospice IE | H61: 7 | I61: 16 | J61: 33.2 | K61: 264.14 | L61: 270.89 | M61: 270.68 | N61: 284.54 | O61: 17 | P61: 298.36 | Q61: 295.84 | R61: 305.71 | S61: 295.14 | T61: 78 | U61: 318.27 | V61: 311.18 | W61: 322.24 | X61: 329 | Y61: 326.09 | Z61: 46.3 | AA61: 351.75 | AB61: 344.52 | AC61: 329.71 | AD61: 336.71 | AE61: 53.3 | AJ61: 77.5 | AP61: 93.7 | AU61: 66.8 | AZ61: 97.4 | BF61: 72.6 | BK61: 44.2 | BQ61: 20.3 | BV61: 128.1 | CA61: 189.3 | CF61: 10
B62: HCHB Analytics - Hospice Key Metrics - LOS | D62: Hospice SGV | H62: 4 | I62: 13.8 | J62: 39.1 | K62: 174.74 | L62: 184.52 | M62: 180.24 | N62: 179.27 | O62: 42.3 | P62: 200.04 | Q62: 182.65 | R62: 188.85 | S62: 181.75 | T62: 32 | U62: 175.73 | V62: 174.35 | W62: 191.48 | X62: 200.61 | Y62: 214.37 | Z62: 21.8 | AA62: 221.37 | AB62: 205.9 | AC62: 199.72 | AD62: 213.1 | AE62: 0 | AJ62: 56.3 | AP62: 131.6 | AU62: 55.9 | AZ62: 183.8 | BF62: 93.1 | BK62: 112.2 | BQ62: 203.5 | BV62: 164.5 | CA62: 126 | CF62: 135.5
B63: HCHB Analytics - Hospice Key Metrics - LOS | D63: Hospice Desert | H63: 5.4 | I63: 14.6 | J63: 23.9 | K63: 73.01 | L63: 75.76 | M63: 76.84 | N63: 84.5 | O63: 27.2 | P63: 83.22 | Q63: 81.1 | R63: 89.18 | S63: 92.43 | T63: 24.5 | U63: 86.58 | V63: 90.64 | W63: 88.77 | X63: 95.2 | Y63: 95.71 | Z63: 31.3 | AA63: 101.97 | AB63: 106.2 | AC63: 103.51 | AD63: 107.44 | AE63: 36.3 | AJ63: 91.8 | AP63: 40.4 | AU63: 77.2 | AZ63: 51.9 | BF63: 67 | BK63: 56.4 | BQ63: 101.1 | BV63: 71.1 | CA63: 65.5 | CF63: 96.3
A64: Lupa % | C64: Benchmark
A65: Monthly Only | B65: KPI Alerts - HH Medicare | C65: 0.05 | D65: HH | E65: 0.053 | F65: 0.068 | G65: 0.075 | H65: 0.069 | I65: 0.072 | J65: 0.065 | K65: 0.075 | L65: 0.0556 | M65: 0.1538 | N65: 0.0541 | O65: 0.052 | P65: 0 | Q65: 0.0714 | R65: 0.0385 | S65: 0.0345 | T65: 0.047 | U65: 0.0645 | V65: 0.068 | W65: 0.055 | X65: 0.052 | Y65: 0.053 | Z65: 0.045 | AA65: 0.048 | AB65: 0.057 | AC65: 0.049 | AD65: 0.0001 | AE65: 0.017 | AF65: 0.027 | AG65: 0.019 | AH65: 0.018 | AI65: 0.02 | AJ65: 0.003 | AK65: 0.019 | AL65: 0.017 | AM65: 0.029 | AN65: 0.042 | AO65: 0.031 | AP65: 0.042 | AQ65: 0.037 | AR65: 0.037 | AS65: 0.041 | AT65: 0.034 | AU65: 0.034 | AV65: 0.027 | AW65: 0.049 | AX65: 0.068 | AY65: 0.068 | AZ65: 0.066 | BA65: 0.061 | BB65: NA | BC65: NA | BD65: NA | BE65: 0.02 | BF65: 0.041 | BG65: 0.034 | BH65: 0.056 | BI65: 0.06 | BJ65: 0.036 | BK65: 0.096 | BL65: 0.091 | BM65: 0.087 | BN65: 0.061 | BO65: 0.067 | BP65: 0.039 | BQ65: 0.105 | BR65: 0.039 | BS65: 0.029 | BT65: 0.081 | BU65: 0.065 | BV65: 0.078 | BW65: 0.019 | BX65: 0.045 | BY65: 0.036 | BZ65: 0.036 | CA65: 0.055 | CB65: 0.032 | CC65: 0.043 | CD65: 0.035 | CE65: 0.038 | CF65: 0.062 | CG65: 0.021 | CH65: 0.012 | CI65: 0.014 | CJ65: 0.016 | CK65: 0.021 | CL65: 0.076
A66: Client Mgmt - Home Health LUPA | B66: KPI Alerts - HH Medicare | C66: 0.05 | D66: Palliative | E66: 0.064 | F66: 0.032 | G66: 0.059 | H66: 0.054 | I66: 0.081 | J66: 0.073 | K66: 0 | L66: 0.0417 | M66: 0.0435 | N66: 0 | O66: 0.047 | P66: 0.0313 | Q66: 0.0385 | R66: 0.0357 | S66: 0.1071 | T66: 0.059 | U66: 0.0857 | V66: 0.081 | W66: 0.055 | X66: 0.058 | Y66: 0.039 | Z66: 0.046 | AA66: 0.05 | AB66: 0.05 | AC66: 0.049 | AD66: 0.06 | AE66: 0.046 | AF66: 0.041 | AG66: 0.036 | AH66: 0.042 | AI66: 0.055 | AJ66: 0.048 | AK66: 0.077 | AL66: 0.071 | AM66: 0.068 | AN66: 0.079 | AO66: 0.049 | AP66: 0.05 | AQ66: 0.072 | AR66: 0.072 | AS66: 0.077 | AT66: 0.076 | AU66: 0.058 | AV66: 0.053 | AW66: 0.054 | AX66: 0.046 | AY66: 0.039 | AZ66: 0.055 | BA66: 0.055 | BB66: 0.06 | BC66: 0.066 | BD66: 0.054 | BE66: 0.039 | BF66: 0.062 | BG66: 0.027 | BH66: 0.034 | BI66: 0.036 | BJ66: 0.032 | BK66: 0.047 | BL66: 0.016 | BM66: 0.018 | BN66: 0.031 | BO66: 0.042 | BP66: 0.031 | BQ66: 0.036 | BR66: 0.011 | BS66: 0.011 | BT66: 0.044 | BU66: 0.061 | BV66: 0.072 | BW66: 0.053 | BX66: 0.048 | BY66: 0 | BZ66: 0 | CA66: 0.03 | CB66: 0.014 | CC66: 0.022 | CD66: 0.011 | CE66: 0.01 | CF66: 0.049 | CG66: 0.019 | CH66: 0.032 | CI66: 0.044 | CJ66: 0.041 | CK66: 0.025 | CL66: 0.045
A67: % of Workers Achieving expected Points | C67: Benchmark
A68: (FT only ) | B68: Field Operations/Field Productivity - Worker Points | D68: HH + Palliative | K68: =9/10 -> 0.9 | L68: =9/10 -> 0.9 | M68: =9/10 -> 0.9 | N68: =9/10 -> 0.9
B69: Field Operations/Field Productivity - Worker Points | D69: Hospice OC | K69: 1 | L69: =11/12 -> 0.91666667 | M69: =11/12 -> 0.91666667 | N69: =11/12 -> 0.91666667
B70: Field Operations/Field Productivity - Worker Points | D70: Hospice IE | K70: 1 | L70: 1 | M70: 1 | N70: 1
B71: Field Operations/Field Productivity - Worker Points | D71: Hospice SGV | K71: 1 | L71: =5/6 -> 0.83333333 | M71: 1 | N71: 1
B72: Field Operations/Field Productivity - Worker Points | D72: Hospice Desert | K72: 1 | L72: 1 | M72: 1 | N72: 1
A73: Unbilled Claims | C73: Benchmark
B74: AR Aging by Patient Report | D74: HH | K74: 253336 | L74: 195640 | M74: 161510 | N74: 170289 | P74: 160595 | Q74: 120772 | R74: 170130 | S74: 162625 | U74: 144812 | V74: 142949 | W74: 206734 | X74: 229600 | Y74: 252866 | AA74: 283275 | AB74: 233298 | AC74: 191756 | AD74: 170755 | AF74: 97245 | AG74: 193922 | AH74: 178173 | AI74: 168717 | AK74: 159423 | AL74: 161285 | AM74: 144260 | AN74: 123471 | AO74: 121912 | AQ74: 109780 | AR74: 83607 | AS74: 84937 | AT74: 84917 | AV74: 80050 | AW74: 70326 | AX74: 70879 | AY74: 73355 | BA74: 86737 | BB74: 52239 | BC74: 54417 | BD74: 85902 | BE74: 121183 | BG74: 119448 | BH74: 90830 | BI74: 158894 | BJ74: 188122 | BL74: 231065 | BM74: 209513 | BN74: 253918 | BO74: 314491 | BP74: 268650 | BR74: 243584 | BS74: 233680 | BT74: 225424 | BU74: 216663 | BW74: 249294 | BX74: 252880 | BY74: 214460 | BZ74: 182680 | CB74: 206972 | CC74: 167235 | CD74: 168455 | CE74: 168053 | CG74: 156186 | CH74: 139545 | CI74: 106155 | CJ74: 115119 | CK74: 99570
B75: AR Aging by Patient Report | D75: Palliative | K75: 190226 | L75: 182029 | M75: 182715 | N75: 163540 | P75: 149286 | Q75: 89021 | R75: 196885 | S75: 137147 | U75: 112013 | V75: 109720 | W75: 157877 | X75: 276159 | Y75: 384712 | AA75: 384375 | AB75: 388374 | AC75: 394841 | AD75: 347165 | AF75: 310930 | AG75: 448770 | AH75: 499177 | AI75: 540872 | AK75: 597099 | AL75: 616379 | AM75: 442974 | AN75: 459907 | AO75: 439409 | AQ75: 456019 | AR75: 388596 | AS75: 383788 | AT75: 399328 | AV75: 406375 | AW75: 351753 | AX75: 314451 | AY75: 287752 | BA75: 329928 | BB75: 335388 | BC75: 286474 | BD75: 258879 | BE75: 215932 | BG75: 232783 | BH75: 225121 | BI75: 234495 | BJ75: 224078 | BL75: 233712 | BM75: 232974 | BN75: 249207 | BO75: 287275 | BP75: 244145 | BR75: 214597 | BS75: 171954 | BT75: 142905 | BU75: 80056 | BW75: 120642 | BX75: 128119 | BY75: 178494 | BZ75: 170377 | CB75: 193462 | CC75: 216918 | CD75: 256052 | CE75: 270740 | CG75: 252350 | CH75: 277838 | CI75: 301209 | CJ75: 326195 | CK75: 257772
B76: AR Aging by Patient Report | D76: Hospice OC | K76: 417389 | L76: 201120 | M76: 155358 | N76: 566267 | P76: 119559 | Q76: 25501 | R76: 47286 | S76: 630856 | U76: 421685 | V76: 83389 | W76: 88051 | X76: 51911 | Y76: 535316 | AA76: 189618 | AB76: 30581 | AC76: 32672 | AD76: 639868 | AF76: 92573 | AG76: 157198 | AH76: 149226 | AI76: 702971 | AK76: =241226+7821 -> 249047 | AL76: =249098+7821 -> 256919 | AM76: =233711+7821 -> 241532 | AN76: =65422+7821 -> 73243 | AO76: =380805+16317 -> 397122 | AQ76: =85580+16317 -> 101897 | AR76: =73327+8497 -> 81824 | AS76: =72545+969 -> 73514 | AT76: =579738+12149 -> 591887 | AV76: =443701+6811 -> 450512 | AW76: =436402+6811 -> 443213 | AX76: =93351+6811 -> 100162 | AY76: =775773+6811 -> 782584 | BA76: =64813+6811 -> 71624 | BB76: =17397+6811 -> 24208 | BC76: =6811+15833 -> 22644 | BD76: =17826+6811 -> 24637 | BE76: =521948+6811 -> 528759 | BG76: =183479+6811 -> 190290 | BH76: =33116+6811 -> 39927 | BI76: =22716+6811 -> 29527 | BJ76: =641616+6811 -> 648427 | BL76: =6811+111204 -> 118015 | BM76: =64765+6811 -> 71576 | BN76: =6811+22789 -> 29600 | BO76: =6811+22789 -> 29600 | BP76: =6811+592274 -> 599085 | BR76: =6811+564129 -> 570940 | BS76: =86342+6811 -> 93153 | BT76: =6811+63830 -> 70641 | BU76: =6811+585300 -> 592111 | BW76: =6811+501436 -> 508247 | BX76: =6811+108658 -> 115469 | BY76: =16138+6811 -> 22949 | BZ76: =582109+6811 -> 588920 | CB76: =6811+494713 -> 501524 | CC76: =107776 -> 107776 | CD76: 63642 | CE76: 80716 | CG76: 643745 | CH76: 495513 | CI76: 473830 | CJ76: 16584 | CK76: 697074
B77: AR Aging by Patient Report | D77: Hospice IE | K77: 200688 | L77: 88909 | M77: 39823 | N77: 272845 | P77: 88035 | Q77: 32675 | R77: 30615 | S77: =14943+288867 -> 303810 | U77: =108176+14943 -> 123119 | V77: 35174 | W77: 28502 | X77: 15665 | Y77: 28264 | AA77: 28933 | AB77: 0 | AC77: 436 | AD77: 209936 | AF77: 28725 | AG77: 32925 | AH77: 32925 | AI77: =250262+8543 -> 258805 | AK77: =15102+854 -> 15956 | AL77: 15716 | AM77: =3427+145 -> 3572 | AN77: =323+145 -> 468 | AO77: =51551+8973 -> 60524 | AQ77: =145 -> 145 | AR77: 0 | AS77: 0 | AT77: =56704+9919 -> 66623 | AV77: 0 | AW77: 0 | AX77: 0 | AY77: =324329+1473 -> 325802 | BA77: 8543 | BB77: 8543 | BC77: 8543 | BD77: 8543 | BE77: =23658+3345 -> 27003 | BG77: =23658+1317 -> 24975 | BH77: =23658 -> 23658 | BI77: 17370 | BJ77: =17370+22264 -> 39634 | BL77: =18462+6085 -> 24547 | BM77: =18462 -> 18462 | BN77: 18462 | BO77: 18462 | BP77: =27289+12815 -> 40104 | BR77: 6288 | BS77: 0 | BT77: 0 | BU77: =8828+35131 -> 43959 | BW77: =8828+28292 -> 37120 | BX77: =8828 -> 8828 | BY77: 0 | BZ77: =23589+7973 -> 31562 | CB77: =7973 -> 7973 | CC77: 0 | CD77: 0 | CE77: 0 | CG77: 25727 | CH77: 0 | CI77: 0 | CJ77: 0 | CK77: =192672+6085 -> 198757
B78: AR Aging by Patient Report | D78: Hospice SGV | K78: 143112 | L78: 67988 | M78: 48787 | N78: 194531 | P78: 103190 | Q78: 21926 | R78: 47119 | S78: 227239 | U78: 135141 | V78: 22702 | W78: 59012 | X78: 43561 | Y78: 79810 | AA78: 9930 | AB78: 6348 | AC78: 6348 | AD78: 207383 | AF78: 8328 | AG78: 14676 | AH78: 14676 | AI78: =245567+18197 -> 263764 | AK78: =76620+12695 -> 89315 | AL78: =48194+6348 -> 54542 | AM78: =8328 -> 8328 | AN78: 14901 | AO78: =129637 -> 129637 | AQ78: 13366 | AR78: 13366 | AS78: 13366 | AT78: =99399 -> 99399 | AV78: 26279 | AW78: 26279 | AX78: 26279 | AY78: =229958 -> 229958 | BA78: 20257 | BB78: 19720 | BC78: 19720 | BD78: 19720 | BE78: 20536 | BG78: 20442 | BH78: =19720 -> 19720 | BI78: 19720 | BJ78: 44914 | BL78: 19865 | BM78: =19865 -> 19865 | BN78: 19865 | BO78: 19720 | BP78: 65432 | BR78: =27180 -> 27180 | BS78: 27180 | BT78: 27180 | BU78: 114827 | BW78: 44794 | BX78: =8142 -> 8142 | BY78: 0 | BZ78: 32686 | CB78: =6002 -> 6002 | CC78: 6002 | CD78: 0 | CE78: 0 | CG78: 24833 | CH78: 0 | CI78: 0 | CJ78: 0 | CK78: 70747
B79: AR Aging by Patient Report | D79: Hospice Desert | K79: =74563+112637 -> 187200 | L79: =29365 -> 29365 | M79: 767 | N79: =320592+173847 -> 494439 | P79: =92349+44574 -> 136923 | Q79: 9719 | R79: =14972 -> 14972 | S79: =208757+414929 -> 623686 | U79: =54244+26695 -> 80939 | V79: =697+13151 -> 13848 | W79: =9065+13151 -> 22216 | X79: 1007 | Y79: =46985+115510 -> 162495 | AA79: =32635+45047 -> 77682 | AB79: =11254+32635 -> 43889 | AC79: =32635+2382 -> 35017 | AD79: =501794+167458 -> 669252 | AF79: =7929+51999 -> 59928 | AG79: =10311+78993 -> 89304 | AH79: =10311+48990 -> 59301 | AI79: =194157+148620 -> 342777 | AK79: =33696+110635 -> 144331 | AL79: =19382+20048 -> 39430 | AM79: =10457 -> 10457 | AN79: 0 | AO79: =21148+45739 -> 66887 | AQ79: 18202 | AR79: 6245 | AS79: 6245 | AT79: =103171+25014 -> 128185 | AV79: =7655 -> 7655 | AW79: 7655 | AX79: 7655 | AY79: =454054+147801 -> 601855 | BA79: =13312 -> 13312 | BB79: 13312 | BC79: 13312 | BD79: =13312 -> 13312 | BE79: =420514+41213 -> 461727 | BG79: =420514+13473 -> 433987 | BH79: =386981+498 -> 387479 | BI79: 42900 | BJ79: =137968+89782 -> 227750 | BL79: =70217+772 -> 70989 | BM79: =68426+1801 -> 70227 | BN79: =49986 -> 49986 | BO79: 49986 | BP79: =206573+63065 -> 269638 | BR79: =46315+2665 -> 48980 | BS79: =6485+33602 -> 40087 | BT79: =31028+2665 -> 33693 | BU79: =155681+39805 -> 195486 | BW79: =67889+29520 -> 97409 | BX79: =31046 -> 31046 | BY79: =20841 -> 20841 | BZ79: =199495+57929 -> 257424 | CB79: =168487+24570 -> 193057 | CC79: =5679+36916 -> 42595 | CD79: =5679+36144 -> 41823 | CE79: =19106 -> 19106 | CG79: =199406+45469 -> 244875 | CH79: =2434+31712 -> 34146 | CI79: =17889+2434 -> 20323 | CJ79: =17889+2434 -> 20323 | CK79: =230970+52452 -> 283422
D80: Total Unbilled Claims | K80: =SUM(K74:K79) -> 1391951 | L80: =SUM(L74:L79) -> 765051 | M80: =SUM(M74:M79) -> 588960 | N80: =SUM(N74:N79) -> 1861911 | P80: =SUM(P74:P79) -> 757588 | Q80: =SUM(Q74:Q79) -> 299614 | R80: =SUM(R74:R79) -> 507007 | S80: =SUM(S74:S79) -> 2085363 | U80: =SUM(U74:U79) -> 1017709 | V80: =SUM(V74:V79) -> 407782 | W80: =SUM(W74:W79) -> 562392 | X80: =SUM(X74:X79) -> 617903 | Y80: =SUM(Y74:Y79) -> 1443463 | AA80: =SUM(AA74:AA79) -> 973813 | AB80: =SUM(AB74:AB79) -> 702490 | AC80: =SUM(AC74:AC79) -> 661070 | AD80: =SUM(AD74:AD79) -> 2244359 | AF80: =SUM(AF74:AF79) -> 597729 | AG80: =SUM(AG74:AG79) -> 936795 | AH80: =SUM(AH74:AH79) -> 933478 | AI80: =SUM(AI74:AI79) -> 2277906 | AK80: =SUM(AK74:AK79) -> 1255171 | AL80: =SUM(AL74:AL79) -> 1144271 | AM80: =SUM(AM74:AM79) -> 851123 | AN80: =SUM(AN74:AN79) -> 671990 | AO80: =SUM(AO74:AO79) -> 1215491 | AQ80: =SUM(AQ74:AQ79) -> 699409 | AR80: =SUM(AR74:AR79) -> 573638 | AS80: =SUM(AS74:AS79) -> 561850 | AT80: =SUM(AT74:AT79) -> 1370339 | AV80: =SUM(AV74:AV79) -> 970871 | AW80: =SUM(AW74:AW79) -> 899226 | AX80: =SUM(AX74:AX79) -> 519426 | AY80: =SUM(AY74:AY79) -> 2301306 | BA80: =SUM(BA74:BA79) -> 530401 | BB80: =SUM(BB74:BB79) -> 453410 | BC80: =SUM(BC74:BC79) -> 405110 | BD80: =SUM(BD74:BD79) -> 410993 | BE80: =SUM(BE74:BE79) -> 1375140 | BG80: =SUM(BG74:BG79) -> 1021925 | BH80: =SUM(BH74:BH79) -> 786735 | BI80: =SUM(BI74:BI79) -> 502906 | BJ80: =SUM(BJ74:BJ79) -> 1372925 | BL80: =SUM(BL74:BL79) -> 698193 | BM80: =SUM(BM74:BM79) -> 622617 | BN80: =SUM(BN74:BN79) -> 621038 | BO80: =SUM(BO74:BO79) -> 719534 | BP80: =SUM(BP74:BP79) -> 1487054 | BR80: =SUM(BR74:BR79) -> 1111569 | BS80: =SUM(BS74:BS79) -> 566054 | BT80: =SUM(BT74:BT79) -> 499843 | BU80: =SUM(BU74:BU79) -> 1243102 | BW80: =SUM(BW74:BW79) -> 1057506 | BX80: =SUM(BX74:BX79) -> 544484 | BY80: =SUM(BY74:BY79) -> 436744 | BZ80: =SUM(BZ74:BZ79) -> 1263649 | CB80: =SUM(CB74:CB79) -> 1108990 | CC80: =SUM(CC74:CC79) -> 540526 | CD80: =SUM(CD74:CD79) -> 529972 | CE80: =SUM(CE74:CE79) -> 538615 | CG80: =SUM(CG74:CG79) -> 1347716 | CH80: =SUM(CH74:CH79) -> 947042 | CI80: =SUM(CI74:CI79) -> 901517 | CJ80: =SUM(CJ74:CJ79) -> 478221 | CK80: =SUM(CK74:CK79) -> 1607342
A81: FTE
A82: As calcuated from Payroll system on payweek | B82: Stephanie's calculation every payroll week | D82: Midco | Q82: 51.22 | S82: 51.5 | U82: 52.26 | W82: 49.01 | Y82: 48.8 | AB82: 46.88 | AD82: 46.41 | AG82: 47.75 | AI82: 49.88 | AL82: 48.82 | AN82: 48.93 | AQ82: 50.2 | AS82: 49.22 | AV82: 50.6 | AX82: 51.96 | BA82: 53.75 | BC82: 54.32 | BE82: 52.93 | BH82: 54.41 | BJ82: 55.84 | BM82: 54.5 | BO82: 54.77 | BR82: 53.65 | BT82: 53.59 | BW82: 54.3 | BY82: 51.79 | CB82: 50.35 | CD82: 50.65 | CG82: 51.32 | CI82: 53.41
B83: Stephanie's calculation every payroll week | D83: HH | Q83: 8.68 | S83: 9.34 | U83: 9.47 | W83: 9.32 | Y83: 8.94 | AB83: 8.78 | AD83: 8.58 | AG83: 8.32 | AI83: 8.07 | AL83: 8.21 | AN83: 8.14 | AQ83: 7.99 | AS83: 7.99 | AV83: 8.08 | AX83: 8.11 | BA83: 8.51 | BC83: 7.56 | BE83: 8.15 | BH83: 9.52 | BJ83: 9.51 | BM83: 9.8
B84: Stephanie's calculation every payroll week | D84: Palliative | Q84: 8 | S84: 8.58 | U84: 9.55 | W84: 10.31 | Y84: 10.36 | AB84: 9.4 | AD84: 9.9 | AG84: 10.21 | AI84: 11.6 | AL84: 10.88 | AN84: 10.74 | AQ84: 11.78 | AS84: 12.44 | AV84: 13.12 | AX84: 13.28 | BA84: 13.97 | BC84: 13.25 | BE84: 13.22 | BH84: 12.38 | BJ84: 10.49 | BM84: 12.24 | BO84: 21.63 | BR84: 19.62 | BT84: 21.1 | BW84: 21.2 | BY84: 21.56 | CB84: 21.68 | CD84: 21.29 | CG84: 21.37 | CI84: 20.93
B85: Stephanie's calculation every payroll week | D85: Hospice/Living Stones | Q85: 50.23 | S85: 51.12 | U85: 51.77 | W85: 51.79 | Y85: 53.28 | AB85: 52.07 | AD85: 52.45 | AG85: 55.6 | AI85: 56.32 | AL85: 52.66 | AN85: 55.14 | AQ85: 57.85 | AS85: 57.69 | AV85: 56.48 | AX85: 55.86 | BA85: 52.83 | BC85: 51.78 | BE85: 51.95 | BH85: 54.3 | BJ85: 53.73 | BM85: 53.35 | BO85: 55.98 | BR85: 54.37 | BT85: 53.47 | BW85: 54.81 | BY85: 53.46 | CB85: 56.56 | CD85: 54.27 | CG85: 55.6 | CI85: 55.27
D86: Total | U86: =SUM(U82:U85) -> 123.05 | W86: =SUM(W82:W85) -> 120.43 | Y86: =SUM(Y82:Y85) -> 121.38 | AB86: =SUM(AB82:AB85) -> 117.13 | AD86: =SUM(AD82:AD85) -> 117.34 | AG86: =SUM(AG82:AG85) -> 121.88 | AI86: =SUM(AI82:AI85) -> 125.87 | AL86: =SUM(AL82:AL85) -> 120.57 | AN86: =SUM(AN82:AN85) -> 122.95 | AQ86: =SUM(AQ82:AQ85) -> 127.82 | AS86: =SUM(AS82:AS85) -> 127.34 | AV86: =SUM(AV82:AV85) -> 128.28 | AX86: =SUM(AX82:AX85) -> 129.21 | BA86: =SUM(BA82:BA85) -> 129.06 | BC86: =SUM(BC82:BC85) -> 126.91 | BE86: =SUM(BE82:BE85) -> 126.25 | BH86: =SUM(BH82:BH85) -> 130.61 | BJ86: =SUM(BJ82:BJ85) -> 129.57 | BM86: =SUM(BM82:BM85) -> 129.89 | BO86: =SUM(BO82:BO85) -> 132.38 | BR86: =SUM(BR82:BR85) -> 127.64 | BT86: =SUM(BT82:BT85) -> 128.16 | BW86: =SUM(BW82:BW85) -> 130.31 | BY86: =SUM(BY82:BY85) -> 126.81 | CB86: =SUM(CB82:CB85) -> 128.59 | CD86: =SUM(CD82:CD85) -> 126.21 | CG86: =SUM(CG82:CG85) -> 128.29 | CI86: =SUM(CI82:CI85) -> 129.61
A87: Total Employee Count
B88: From Paychex | D88: Total Combined | AA88: 154
A89: Census per EE (Make sure headcount is based on FTE = 1 / PT or PRN=.3) | C89: Benchmark
D90: HH+Palliative | Y90: =Y7/Y83 -> 13.646532 | AG90: =AG9/(AG83+AG84) -> 14.409066 | AI90: =AI9/(AI83+AI84) -> 13.675648 | AL90: =AL9/(AL83+AL84) -> 14.614982 | AN90: =AN9/(AN83+AN84) -> 15.201271 | AV90: =+AV9/(AV83+AV84) -> 12.735849 | AX90: =+AX9/(AX83+AX84) -> 12.669472 | BA90: =+BA9/(BA83+BA84) -> 11.699288 | BC90: =+BC9/(BC83+BC84) -> 12.397886 | BE90: =+BE9/(BE83+BE84) -> 12.540945 | BF90: =AVERAGE(BA90:BE90) -> 12.212706 | BH90: =+BH9/(BH83+BH84) -> 12.876712 | BJ90: =+BJ9/(BJ83+BJ84) -> 14.35 | BK90: =AVERAGE(BG90:BJ90) -> 13.613356 | BM90: =+BM9/(BM83+BM84) -> 12.658802 | BO90: =+BO9/(BO83+BO84) -> 12.066574 | BQ90: =AVERAGE(BL90:BP90) -> 12.362688 | BR90: =+BR9/(BR83+BR84) -> 12.079511 | BT90: =+BT9/(BT83+BT84) -> 10.995261 | BV90: =AVERAGE(BR90:BU90) -> 11.537386 | BW90: =+BW9/(BW83+BW84) -> 11.603774 | BY90: =+BY9/(BY83+BY84) -> 11.781076 | CA90: =AVERAGE(BW90:BZ90) -> 11.692425 | CB90: =+CB9/(CB83+CB84) -> 11.761993 | CD90: =+CD9/(CD83+CD84) -> 12.024425 | CF90: =AVERAGE(CB90:CE90) -> 11.893209 | CG90: =+CG9/(CG83+CG84) -> 11.46467 | CI90: =+CI9/(CI83+CI84) -> 11.371237 | CK90: =+CK9/(CK83+CK84) -> #DIV/0! | CL90: =AVERAGE(CG90:CJ90) -> 11.417954
D91: Hospice/Living Stones | Y91: =Y15/Y85 -> 4.5045045 | AG91: =AG15/AG85 -> 4.7482014 | AI91: =AI15/AI85 -> 4.740767 | AL91: =AL15/AL85 -> 4.9753133 | AN91: =AN15/AN85 -> 4.9691694 | AV91: =+AV15/AV85 -> 4.9575071 | AX91: =+AX15/AX85 -> 5.066237 | BA91: =+BA15/BA85 -> 5.0539466 | BC91: =+BC15/BC85 -> 5.3495558 | BE91: =+BE15/BE85 -> 5.3512993 | BF91: =AVERAGE(BA91:BE91) -> 5.2516006 | BH91: =+BH15/BH85 -> 5.0092081 | BJ91: =+BJ15/BJ85 -> 5.0065141 | BK91: =AVERAGE(BG91:BJ91) -> 5.0078611 | BM91: =+BM15/BM85 -> 5.1171509 | BO91: =+BO15/BO85 -> 5.0196499 | BQ91: =AVERAGE(BL91:BP91) -> 5.0684004 | BR91: =+BR15/BR85 -> 5.1498988 | BT91: =+BT15/BT85 -> 5.1991771 | BV91: =AVERAGE(BR91:BU91) -> 5.174538 | BW91: =+BW15/BW85 -> 5.0538223 | BY91: =+BY15/BY85 -> 5.2375608 | CA91: =AVERAGE(BW91:BZ91) -> 5.1456915 | CB91: =+CB15/CB85 -> 5.0565771 | CD91: =+CD15/CD85 -> 5.1409619 | CF91: =AVERAGE(CB91:CE91) -> 5.0987695 | CG91: =+CG15/CG85 -> 5.0719424 | CI91: =+CI15/CI85 -> 4.9936675 | CK91: =+CK15/CK85 -> #DIV/0! | CL91: =AVERAGE(CG91:CJ91) -> 5.0328049
A92: Contribution Margin (Monthly) | C92: Benchmark
B93: Financial Statements | D93: HH & PAL | J93: 0.361 | O93: 0.322 | T93: 0.41 | Z93: 0.425 | AE93: 0.44 | AJ93: 0.435 | AP93: 0.37 | AU93: 0.19 | AZ93: 0.185 | BF93: 0.17 | BK93: 0.31 | BQ93: 0.28 | BV93: 0.2 | CA93: 0.24 | CF93: 0.25
B94: Financial Statements | D94: Hospice | J94: 0.263 | O94: 0.305 | T94: 0.391 | Z94: 0.386 | AE94: 0.402 | AJ94: 0.427 | AP94: 0.445 | AU94: 0.415 | AZ94: 0.466 | BF94: 0.43 | BK94: 0.42 | BQ94: 0.38 | BV94: 0.42 | CA94: 0.46 | CF94: 0.45
O99: 28 | T99: 31 | Z99: 30 | AE99: 31 | AJ99: 30
O100: =+O6/O18 -> 5843.2439 | P100: =+P6/P18 -> 0 | Q100: =+Q6/Q18 -> 0 | R100: =+R6/R18 -> 0 | S100: =+S6/S18 -> 0 | T100: =+T6/T18 -> 6757.0998 | U100: =+U6/U18 -> 0 | V100: =+V6/V18 -> 0 | ... AJ100: =+AJ6/AJ18 -> 6319.217 | AP100: =+AP6/385 -> 6315.5768 | BF100: 732345
D101: Montherized | O101: =+O100/28*31 -> 6469.3057 | T101: =+T100 -> 6757.0998 | Z101: =+Z100/30*31 -> 6551.3911 | AE101: =+AE100 -> 6556.2719 | AJ101: =+AJ100/30*31 -> 6529.8576 | BF101: =+BF10*30 -> 3300
AJ102: =+AJ100*10 -> 63192.17 | BF102: =+BF100/BF101 -> 221.92273

Sheet Financial
A1: KPI | B1: Definition | C1: Benchmark | D1: Service Line | E1: 45505 | F1: 45536 | G1: 45566 | H1: 45597 | I1: 45627 | J1: 45658 | K1: 45689 | L1: 45717 | M1: 3/30-4/5 | N1: 4/6-4/12 | O1: 4/13-4/19 | P1: 4/20-4/26 | Q1: 4/27-5/3 | R1: 45748 | S1: 5/4-5/10 | T1: 5/11-5/17 | U1: 5/18-5/24 | V1: 5/25-5/31 | W1: 45778 | X1: 6/1-6/7 | Y1: 6/8-6/14 | Z1: 6/15-6/21 | AA1: 6/22-6/28 | AB1: 45809 | AC1: 45839 | AD1: 45870 | AE1: 45901 | AF1: 45931 | AG1: 45962 | AH1: 45992 | AI1: 46023 | AJ1: 46054 | AK1: 46082
A2: Total HCHB Aging | B2: Over 120 days | BQ2: =+'Company Scorecard'!CJ3 -> 0 | BR2: =+'Company Scorecard'!#REF! -> #REF! | BS2: =+'Company Scorecard'!CM3 -> 0 | BT2: =+'Company Scorecard'!CN3 -> 0 | BU2: =+'Company Scorecard'!CO3 -> 0 | BV2: =+'Company Scorecard'!CP3 -> 0 | BW2: =+'Company Scorecard'!CQ3 -> 0 | BX2: =+'Company Scorecard'!CR3 -> 0 | BY2: =+'Company Scorecard'!CS3 -> 0 | BZ2: =+'Company Scorecard'!CT3 -> 0 | ... DE2: =+'Company Scorecard'!DY3 -> 0
B3: AR Aging Report | D3: HH | J3: 56376.4 | K3: 74117.61 | L3: 77595.09 | R3: 77577.32 | W3: 58680.68 | AB3: 81638.79 | AC3: 90838.75 | AD3: 28757.08 | AE3: 29488.24 | AF3: 28178.49 | AG3: 29666.35 | AH3: 37176.61 | AI3: 38331.37 | AJ3: 35725.72 | AK3: 43011.89
D4: PAL | J4: 78266.24 | K4: 69991.63 | L4: 80079.7 | R4: 77669.32 | W4: 90096.88 | AB4: 93329.09 | AC4: 89450.47 | AD4: 23813.63 | AE4: 31632.84 | AF4: 28525.43 | AG4: 32558.69 | AH4: 48246.48 | AI4: 73681.75 | AJ4: 85957.62 | AK4: 110278.71
D5: HOSP | J5: 218196.55 | K5: 239016.32 | L5: 284511.57 | R5: 363189.05 | W5: 410882.67 | AB5: 391076.55 | AC5: 340833.24 | AD5: 383413.84 | AE5: 384798 | AF5: 502579.24 | AG5: 439015 | AH5: 436239 | AI5: 499145 | AJ5: 528096 | AK5: 419895
D6: Hospice OC | J6: 218196.55 | K6: 239016.32 | L6: 271878.91 | R6: 237033.61 | W6: 236199.39 | AB6: 239905.51 | AC6: 179347.65 | AD6: 199798.98 | AE6: =230.19+231883.66 -> 232113.85 | AF6: =254055.98+7366.08 -> 261422.06 | AG6: =14174+196682.87 -> 210856.87 | AH6: =19250.4+188650.1 -> 207900.5 | AI6: =19250.4+193216.19 -> 212466.59 | AJ6: 206430.88 | AK6: 147874.74
D7: Hospice IE | J7: 0 | K7: 0 | L7: 1550.2 | R7: 11231.39 | W7: 22848.47 | AB7: 17477.94 | AC7: 9102.13 | AD7: 11657.28 | AE7: =244.29+19456.79 -> 19701.08 | AF7: =28185.81+7328.7 -> 35514.51 | AG7: =14942.26+27015.26 -> 41957.52 | AH7: =22845.92+3712.65 -> 26558.57 | AI7: =29884.62+8489.69 -> 38374.31 | AJ7: =37213.42+14022.81 -> 51236.23 | AK7: =44826.98+18051.59 -> 62878.57
D8: Hospice SGV | J8: 0 | K8: 0 | L8: 1540.2 | R8: 20530.31 | W8: 38170.14 | AB8: 32281.62 | AC8: 50396.72 | AD8: 73419.3 | AE8: 71842.09 | AF8: 102865.17 | AG8: 100933.19 | AH8: 71014.97 | AI8: 90998.59 | AJ8: 80430.71 | AK8: 88116.29
D9: Hospice Desert | J9: 0 | K9: 0 | L9: =8764.6+777.66 -> 9542.26 | R9: =49845.85+44547.89 -> 94393.74 | W9: =20853.53+92811.14 -> 113664.67 | AB9: =85260.89+16150.59 -> 101411.48 | AC9: =16430.77+85555.97 -> 101986.74 | AD9: =23591.47+74946.81 -> 98538.28 | AE9: =36814.8+24326.55 -> 61141.35 | AF9: =78450.95+24326.55 -> 102777.5 | AG9: =72225.26+13042.54 -> 85267.8 | AH9: =128821.57+1943.15 -> 130764.72 | AI9: =155792.72+1512.83 -> 157305.55 | AJ9: =176823.9+13173.86 -> 189997.76 | AK9: =103643.72+17381.54 -> 121025.26
A10: Accounts Receivable Aging
D11: HH | J11: 480654.02 | K11: 413017.85 | L11: 636508.95 | R11: 591191.52 | W11: 534929.66 | AB11: 407582.89 | AC11: 352097.21 | AD11: 219089.02 | AE11: 194335.03 | AF11: 323403.86 | AG11: =544029.35-17773.64 -> 526255.71 | AH11: =695501.69-17773.64 -> 677728.05 | AI11: =702552.08-26913.69 -> 675638.39
D12: PAL | J12: 358555.43 | K12: 330187.83 | L12: 554479.19 | R12: 668405.41 | W12: 1027342.9 | AB12: 1063435.9 | AC12: 1263951.1 | AD12: 1060551.8 | AE12: 950179.49 | AF12: 822844.28 | AG12: =596367.73-32644.02 -> 563723.71 | AH12: =561322.22-32644.02 -> 528678.2 | AI12: =483611.54-29272.91 -> 454338.63
D13: HOSP | J13: 2895764.3 | K13: 2728862.3 | L13: 2930241 | R13: 2821017.5 | W13: 2875274.1 | AB13: 2882383.6 | AC13: 3097251.4 | AD13: 2957038.2 | AE13: 3148026.9 | AF13: 2899516.3 | AG13: =2246646.19+984612.94-84689.81-61034.92 -> 3085534.4 | AH13: =2143900.72+711921.02-84689.81-61034.92 -> 2710097 | AI13: =2555482.06+844526.15-241601.84-77040.96 -> 3081365.4
B14: Total | J14: =+J13+J12+J11 -> 3734973.8 | K14: =+K13+K12+K11 -> 3472068 | L14: =+L13+L12+L11 -> 4121229.2 | M14: =+M13+M12+M11 -> 0 | N14: =+N13+N12+N11 -> 0 | O14: =+O13+O12+O11 -> 0 | P14: =+P13+P12+P11 -> 0 | Q14: =+Q13+Q12+Q11 -> 0 | ... AC14: =+AC13+AC12+AC11 -> 4713299.7 | AD14: 4236679 | AE14: 4292541.4 | AF14: 4045764.4 | AG14: =SUM(AG11:AG13) -> 4175513.8 | AH14: =SUM(AH11:AH13) -> 3916503.3 | AI14: =SUM(AI11:AI13) -> 4211342.4
A15: Average Revenue per day in trailing 3 months
D16: HH | L16: =(+'Company Scorecard'!T3+'Company Scorecard'!O3+'Company Scorecard'!J3)/91 -> 11463.083 | M16: =(+'Company Scorecard'!U3+'Company Scorecard'!O3+'Company Scorecard'!J3)/91 -> 7105.6788 | N16: =(+'Company Scorecard'!V3+'Company Scorecard'!P3+'Company Scorecard'!K3)/91 -> 0 | O16: =(+'Company Scorecard'!W3+'Company Scorecard'!Q3+'Company Scorecard'!L3)/91 -> 0 | P16: =(+'Company Scorecard'!X3+'Company Scorecard'!R3+'Company Scorecard'!M3)/91 -> 0 | Q16: =(+'Company Scorecard'!Y3+'Company Scorecard'!S3+'Company Scorecard'!N3)/91 -> 0 | R16: =(+'Company Scorecard'!Z3+'Company Scorecard'!T3+'Company Scorecard'!O3)/91 -> 10802.35 | S16: =(+'Company Scorecard'!AA3+'Company Scorecard'!V3+'Company Scorecard'!P3)/91 -> 0 | T16: =(+'Company Scorecard'!AB3+'Company Scorecard'!W3+'Company Scorecard'!Q3)/91 -> 0 | U16: =(+'Company Scorecard'!AC3+'Company Scorecard'!X3+'Company Scorecard'!R3)/91 -> 0 | V16: =(+'Company Scorecard'!AD3+'Company Scorecard'!Y3+'Company Scorecard'!S3)/91 -> 0 | W16: =(+'Company Scorecard'!AE3+'Company Scorecard'!Z3+'Company Scorecard'!T3)/91 -> 9801.3847 | X16: =(+'Company Scorecard'!AF3+'Company Scorecard'!AA3+'Company Scorecard'!V3)/91 -> 0 | Y16: =(+'Company Scorecard'!AG3+'Company Scorecard'!AB3+'Company Scorecard'!W3)/91 -> 0 | Z16: =(+'Company Scorecard'!AH3+'Company Scorecard'!AC3+'Company Scorecard'!X3)/91 -> 0 | AA16: =(+'Company Scorecard'!AI3+'Company Scorecard'!AD3+'Company Scorecard'!Y3)/91 -> 0 | AB16: =(+'Company Scorecard'!AJ3+'Company Scorecard'!AE3+'Company Scorecard'!Z3)/91 -> 7199.2464 | AC16: =(+'Company Scorecard'!AE3+'Company Scorecard'!AJ3+'Company Scorecard'!AP3)/92 -> 5317.8436 | AD16: =(+'Company Scorecard'!AJ3+'Company Scorecard'!AP3+'Company Scorecard'!AU3)/92 -> 3291.5473 | AE16: =(+'Company Scorecard'!AP3+'Company Scorecard'!AU3+'Company Scorecard'!AZ3)/92 -> 2559.2728 | AF16: =(+'Company Scorecard'!AU3+'Company Scorecard'!AZ3+'Company Scorecard'!BF3)/92 -> 3659.3973 | AG16: =('Company Scorecard'!$AZ3+'Company Scorecard'!$BF3+'Company Scorecard'!$BK3)/91 -> 7440.8911 | AH16: =('Company Scorecard'!$BF3+'Company Scorecard'!$BK3+'Company Scorecard'!$BQ3)/92 -> 10642.61 | AI16: =('Company Scorecard'!$BK3+'Company Scorecard'!$BQ3+'Company Scorecard'!$BV3)/92 -> 12088.266 | AJ16: =('Company Scorecard'!$CA3+'Company Scorecard'!$BQ3+'Company Scorecard'!$BV3)/90 -> 11538.636 | AK16: =('Company Scorecard'!$BV3+'Company Scorecard'!$CA3+'Company Scorecard'!$CF3)/90 -> 9436.7133
B17: (does not include WellSky) | D17: PAL | L17: =(+'Company Scorecard'!T4+'Company Scorecard'!O4+'Company Scorecard'!J4)/91 -> 9098.6574 | M17: =(+'Company Scorecard'!U4+'Company Scorecard'!O4+'Company Scorecard'!J4)/91 -> 5880.4045 | N17: =(+'Company Scorecard'!V4+'Company Scorecard'!P4+'Company Scorecard'!K4)/91 -> 0 | O17: =(+'Company Scorecard'!W4+'Company Scorecard'!Q4+'Company Scorecard'!L4)/91 -> 0 | P17: =(+'Company Scorecard'!X4+'Company Scorecard'!R4+'Company Scorecard'!M4)/91 -> 0 | Q17: =(+'Company Scorecard'!Y4+'Company Scorecard'!S4+'Company Scorecard'!N4)/91 -> 0 | R17: =(+'Company Scorecard'!Z4+'Company Scorecard'!T4+'Company Scorecard'!O4)/91 -> 10164.902 | S17: =(+'Company Scorecard'!AA4+'Company Scorecard'!V4+'Company Scorecard'!P4)/91 -> 0 | T17: =(+'Company Scorecard'!AB4+'Company Scorecard'!W4+'Company Scorecard'!Q4)/91 -> 0 | U17: =(+'Company Scorecard'!AC4+'Company Scorecard'!X4+'Company Scorecard'!R4)/91 -> 0 | V17: =(+'Company Scorecard'!AD4+'Company Scorecard'!Y4+'Company Scorecard'!S4)/91 -> 0 | W17: =(+'Company Scorecard'!AE4+'Company Scorecard'!Z4+'Company Scorecard'!T4)/91 -> 13065.673 | AB17: =(+'Company Scorecard'!AJ4+'Company Scorecard'!AE4+'Company Scorecard'!Z4)/91 -> 15273.042 | AC17: =(+'Company Scorecard'!AE4+'Company Scorecard'!AJ4+'Company Scorecard'!AP4)/92 -> 16620.088 | AD17: =(+'Company Scorecard'!AJ4+'Company Scorecard'!AP4+'Company Scorecard'!AU4)/92 -> 15983.732 | AE17: =(+'Company Scorecard'!AP4+'Company Scorecard'!AU4+'Company Scorecard'!AZ4)/92 -> 15763.812 | AF17: =(+'Company Scorecard'!AU4+'Company Scorecard'!AZ4+'Company Scorecard'!BF4)/92 -> 14115.922 | AG17: =('Company Scorecard'!$AZ4+'Company Scorecard'!$BF4+'Company Scorecard'!$BK4)/91 -> 12322.037 | AH17: =('Company Scorecard'!$BF4+'Company Scorecard'!$BK4+'Company Scorecard'!$BQ4)/92 -> 9745.0587 | AI17: =('Company Scorecard'!$BK4+'Company Scorecard'!$BQ4+'Company Scorecard'!$BV4)/92 -> 7992.6542 | AJ17: =('Company Scorecard'!$CA4+'Company Scorecard'!$BQ4+'Company Scorecard'!$BV4)/90 -> 8125.8959 | AK17: =('Company Scorecard'!$BV4+'Company Scorecard'!$CA4+'Company Scorecard'!$CF4)/90 -> 9924.8403
D18: HOSP | L18: =(+'Company Scorecard'!T5+'Company Scorecard'!O5+'Company Scorecard'!J5)/91 -> 46850.313 | M18: =(+'Company Scorecard'!U5+'Company Scorecard'!O5+'Company Scorecard'!J5)/91 -> 29521.232 | N18: =(+'Company Scorecard'!V5+'Company Scorecard'!P5+'Company Scorecard'!K5)/91 -> 0 | O18: =(+'Company Scorecard'!W5+'Company Scorecard'!Q5+'Company Scorecard'!L5)/91 -> 0 | P18: =(+'Company Scorecard'!X5+'Company Scorecard'!R5+'Company Scorecard'!M5)/91 -> 0 | Q18: =(+'Company Scorecard'!Y5+'Company Scorecard'!S5+'Company Scorecard'!N5)/91 -> 0 | R18: =(+'Company Scorecard'!Z5+'Company Scorecard'!T5+'Company Scorecard'!O5)/91 -> 48482.406 | S18: =(+'Company Scorecard'!AA5+'Company Scorecard'!V5+'Company Scorecard'!P5)/91 -> 0 | T18: =(+'Company Scorecard'!AB5+'Company Scorecard'!W5+'Company Scorecard'!Q5)/91 -> 0 | U18: =(+'Company Scorecard'!AC5+'Company Scorecard'!X5+'Company Scorecard'!R5)/91 -> 0 | V18: =(+'Company Scorecard'!AD5+'Company Scorecard'!Y5+'Company Scorecard'!S5)/91 -> 0 | W18: =(+'Company Scorecard'!AE5+'Company Scorecard'!Z5+'Company Scorecard'!T5)/91 -> 52406.442 | AB18: =(+'Company Scorecard'!AJ5+'Company Scorecard'!AE5+'Company Scorecard'!Z5)/91 -> 53930.257 | AC18: =(+'Company Scorecard'!AE5+'Company Scorecard'!AJ5+'Company Scorecard'!AP5)/92 -> 56053.951 | AD18: =(+'Company Scorecard'!AJ5+'Company Scorecard'!AP5+'Company Scorecard'!AU5)/92 -> 58442.6 | AE18: =(+'Company Scorecard'!AP5+'Company Scorecard'!AU5+'Company Scorecard'!AZ5)/92 -> 58693.283 | AF18: =(+'Company Scorecard'!AU5+'Company Scorecard'!AZ5+'Company Scorecard'!BF5)/92 -> 58413.346 | AG18: =('Company Scorecard'!$AZ5+'Company Scorecard'!$BF5+'Company Scorecard'!$BK5)/91 -> 57032.555 | AH18: =('Company Scorecard'!$BF5+'Company Scorecard'!$BK5+'Company Scorecard'!$BQ5)/92 -> 57104.478 | AI18: =('Company Scorecard'!$BK5+'Company Scorecard'!$BQ5+'Company Scorecard'!$BV5)/92 -> 57452.757 | AJ18: =('Company Scorecard'!$CA5+'Company Scorecard'!$BQ5+'Company Scorecard'!$BV5)/90 -> 58081.151 | AK18: =('Company Scorecard'!$BV5+'Company Scorecard'!$CA5+'Company Scorecard'!$CF5)/90 -> 58118.918
B19: Total average Revnue per day | L19: =(+'Company Scorecard'!T6+'Company Scorecard'!O6+'Company Scorecard'!J6)/91 -> 67412.054 | M19: =(+'Company Scorecard'!U6+'Company Scorecard'!O6+'Company Scorecard'!J6)/91 -> 42507.315 | N19: =(+'Company Scorecard'!V6+'Company Scorecard'!P6+'Company Scorecard'!K6)/91 -> 0 | O19: =(+'Company Scorecard'!W6+'Company Scorecard'!Q6+'Company Scorecard'!L6)/91 -> 0 | P19: =(+'Company Scorecard'!X6+'Company Scorecard'!R6+'Company Scorecard'!M6)/91 -> 0 | Q19: =(+'Company Scorecard'!Y6+'Company Scorecard'!S6+'Company Scorecard'!N6)/91 -> 0 | R19: =(+'Company Scorecard'!Z6+'Company Scorecard'!T6+'Company Scorecard'!O6)/91 -> 69449.658 | S19: =(+'Company Scorecard'!AA6+'Company Scorecard'!V6+'Company Scorecard'!P6)/91 -> 0 | T19: =(+'Company Scorecard'!AB6+'Company Scorecard'!W6+'Company Scorecard'!Q6)/91 -> 0 | U19: =(+'Company Scorecard'!AC6+'Company Scorecard'!X6+'Company Scorecard'!R6)/91 -> 0 | V19: =(+'Company Scorecard'!AD6+'Company Scorecard'!Y6+'Company Scorecard'!S6)/91 -> 0 | W19: =(+'Company Scorecard'!AE6+'Company Scorecard'!Z6+'Company Scorecard'!T6)/91 -> 75273.499 | AB19: =(+'Company Scorecard'!AJ6+'Company Scorecard'!AE6+'Company Scorecard'!Z6)/91 -> 76402.546 | AC19: =(+'Company Scorecard'!AE6+'Company Scorecard'!AJ6+'Company Scorecard'!AP6)/92 -> 77991.883 | AD19: =(+'Company Scorecard'!AJ6+'Company Scorecard'!AP6+'Company Scorecard'!AU6)/92 -> 77717.879 | AE19: =+AE18+AE17+AE16 -> 77016.368 | AF19: =+AF18+AF17+AF16 -> 76188.665 | AG19: =+AG18+AG17+AG16 -> 76795.483 | AH19: =+AH18+AH17+AH16 -> 77492.146 | AI19: =+AI18+AI17+AI16 -> 77533.677 | AJ19: =('Company Scorecard'!$CA6+'Company Scorecard'!$BQ6+'Company Scorecard'!$BV6)/90 -> 77745.682 | AK19: =('Company Scorecard'!$BV6+'Company Scorecard'!$CA6+'Company Scorecard'!$CF6)/90 -> 77480.471
A20: DSO by Service Line
D21: HH | L21: =+L11/L16 -> 55.526853 | M21: =+M11/M16 -> 0 | N21: =+N11/N16 -> #DIV/0! | O21: =+O11/O16 -> #DIV/0! | P21: =+P11/P16 -> #DIV/0! | Q21: =+Q11/Q16 -> #DIV/0! | R21: =+R11/R16 -> 54.728047 | S21: =+S11/S16 -> #DIV/0! | ... AK21: =+AK11/AK16 -> 0
D22: PAL | L22: =+L12/L17 -> 60.94077 | M22: =+M12/M17 -> 0 | N22: =+N12/N17 -> #DIV/0! | O22: =+O12/O17 -> #DIV/0! | P22: =+P12/P17 -> #DIV/0! | Q22: =+Q12/Q17 -> #DIV/0! | R22: =+R12/R17 -> 65.756211 | S22: =+S12/S17 -> #DIV/0! | ... W22: =+W12/W17 -> 78.629159 | AB22: =+AB12/AB17 -> 69.628295 | AC22: =+AC12/AC17 -> 76.049605 | AD22: =+AD12/AD17 -> 66.351949 | AE22: =+AE12/AE17 -> 60.275997 | AF22: =+AF12/AF17 -> 58.291926 | AG22: =+AG12/AG17 -> 45.749231 | AH22: =+AH12/AH17 -> 54.2509 | AI22: =+AI12/AI17 -> 56.844525 | ... AK22: =+AK12/AK17 -> 0
D23: HOSP | L23: =+L13/L18 -> 62.544748 | M23: =+M13/M18 -> 0 | N23: =+N13/N18 -> #DIV/0! | O23: =+O13/O18 -> #DIV/0! | P23: =+P13/P18 -> #DIV/0! | Q23: =+Q13/Q18 -> #DIV/0! | R23: =+R13/R18 -> 58.186417 | S23: =+S13/S18 -> #DIV/0! | ... W23: =+W13/W18 -> 54.864899 | AB23: =+AB13/AB18 -> 53.446503 | AC23: =+AC13/AC18 -> 55.254827 | AD23: =+AD13/AD18 -> 50.597307 | AE23: =+AE13/AE18 -> 53.635216 | AF23: =+AF13/AF18 -> 49.637908 | AG23: =+AG13/AG18 -> 54.101283 | AH23: =+AH13/AH18 -> 47.458573 | AI23: =+AI13/AI18 -> 53.63303 | ... AK23: =+AK13/AK18 -> 0
B24: Total DSO | L24: =+L14/L19 -> 61.1349 | M24: =+M14/M19 -> 0 | N24: =+N14/N19 -> #DIV/0! | O24: =+O14/O19 -> #DIV/0! | P24: =+P14/P19 -> #DIV/0! | Q24: =+Q14/Q19 -> #DIV/0! | R24: =+R14/R19 -> 58.756437 | S24: =+S14/S19 -> #DIV/0! | ... W24: =+W14/W19 -> 58.95231 | AB24: =+AB14/AB19 -> 56.979809 | AC24: =+AC14/AC19 -> 60.433208 | AD24: =+AD14/AD19 -> 54.513569 | AE24: =+AE14/AE19 -> 55.735443 | AF24: =+AF14/AF19 -> 53.10192 | AG24: =+AG14/AG19 -> 54.371868 | AH24: =+AH14/AH19 -> 50.540648 | AI24: =+AI14/AI19 -> 54.316299 | ... AK24: =+AK14/AK19 -> 0
A25: AP Aging
A26: Total AP Aging | O26: =SUM(#REF!) -> #REF! | R26: 1291733.4 | W26: 762873.47 | AB26: 492383.47 | AC26: 670034.84 | AD26: 815587.18 | AE26: 712256.58 | AF26: 593993.9 | AG26: 572966.32 | AH26: 487109.78 | AI26: 362561.16
A27: Contributiion Margin Per FTE
D28: HH/PAL | AC28: =234725/('Company Scorecard'!AV83+'Company Scorecard'!AV84) -> 11071.934 | AD28: =92360/('Company Scorecard'!AV83+AV90) -> 11430.693 | AE28: =92360/('Company Scorecard'!AW83+AW90) -> #DIV/0! | AF28: =92360/('Company Scorecard'!AX83+AX90) -> 11388.409 | AG28: =92360/('Company Scorecard'!AY83+AY90) -> #DIV/0! | AH28: =92360/('Company Scorecard'!AZ83+AZ90) -> #DIV/0! | AI28: =92360/('Company Scorecard'!BA83+BA90) -> 10853.114 | AJ28: =92360/('Company Scorecard'!BB83+BB90) -> #DIV/0! | AK28: =92360/('Company Scorecard'!BC83+BC90) -> 12216.931
D29: HOSP | AC29: =799543/'Company Scorecard'!AV85 -> 14156.215 | AD29: =733800/'Company Scorecard'!AV85 -> 12992.21 | AE29: =733800/'Company Scorecard'!AW85 -> #DIV/0! | AF29: =733800/'Company Scorecard'!AX85 -> 13136.412 | AG29: =733800/'Company Scorecard'!AY85 -> #DIV/0! | AH29: =733800/'Company Scorecard'!AZ85 -> #DIV/0! | AI29: =733800/'Company Scorecard'!BA85 -> 13889.835 | AJ29: =733800/'Company Scorecard'!BB85 -> #DIV/0! | AK29: =733800/'Company Scorecard'!BC85 -> 14171.495
A30: Billing System Adjustment % | E30: Billing System Adjustment % | I30: Billing System Adjustment % | M30: Billing System Adjustment % | Q30: Billing System Adjustment % | U30: Billing System Adjustment % | Y30: Billing System Adjustment %
C31: Home Health | D31: HL1 | J31: =-12476.4/405942.08 -> -0.030734434 | K31: =-7430.66/333582.79 -> -0.02227531 | L31: =12802.58/395983.97 -> 0.032331056 | R31: =-3775.24/293987.28 -> -0.012841508 | W31: =1745.86/218766.01 -> 0.0079804902 | AB31: =7162.87/167815.72 -> 0.04268295 | AC31: =538.99/146193.91 -> 0.0036868157 | AD31: =-2666.26/122385.41 -> -0.021785767 | AE31: =-133.72/111138.58 -> -0.0012031825 | AF31: =-1008.78/244155.56 -> -0.0041317101 | AG31: =3491.53/381600.66 -> 0.0091496959 | AH31: =2657.99/417354.81 -> 0.0063686579 | AI31: =-1901.95/370141.67 -> -0.0051384379 | AJ31: =-4764.45/314543.91 -> -0.01514717 | AK31: =2688.93/213295.97 -> 0.012606567
C32: Palliative | D32: PO1 | J32: =-859.24/302225.63 -> -0.0028430415 | K32: =-199.97/286076.41 -> -0.00069900905 | L32: =4720.8/297197.58 -> 0.015884382 | R32: =-2823.85/393502.24 -> -0.007176198 | W32: =3391.25/529760.55 -> 0.006401477 | AB32: =12063/496938.66 -> 0.024274626 | AC32: =1733.64/555221.24 -> 0.003122431 | AD32: =16581.44/566861.85 -> 0.029251289 | AE32: =8104.51/511348.77 -> 0.01584928 | AF32: =4567.51/409327.98 -> 0.011158558 | AG32: =6868.75/298765.44 -> 0.022990444 | AH32: =2250/264090.17 -> 0.0085198173 | AI32: =7869.8/208269.32 -> 0.03778665 | AJ32: =15366.58/276485.49 -> 0.055578251 | AK32: =4211.92/428044.52 -> 0.009839911
B33: Month End Close Revenue Report | C33: Livingstones Orange | D33: LO1 | J33: 0 | K33: 0 | L33: 0 | R33: 0 | W33: 0 | AB33: 0 | AC33: =-33332.07/56407.51 -> -0.59091546 | AD33: =0 -> 0 | AE33: 0 | AF33: 0 | AG33: 0 | AH33: 0 | AI33: 0 | AJ33: 0 | AK33: 0
C34: Acacia Orange | D34: XO1 | J34: =-8859.75/602413.3 -> -0.014707096 | K34: =-13417.98/520083.2 -> -0.02579968 | L34: =-164430.57/836083.1 -> -0.19666774 | R34: =-107562.17/759153.93 -> -0.1416869 | W34: =-272142.85/955324.77 -> -0.28486946 | AB34: =-221984.98/913265.74 -> -0.24306724 | AC34: =-150454.67/810366.03 -> -0.18566261 | AD34: =-25373.16/743879.56 -> -0.034109231 | AE34: =-49174.5/801428.56 -> -0.061358557 | AF34: =-19880.55/851478.27 -> -0.023348276 | AG34: =-26876.32/819948.82 -> -0.032778046 | AH34: =13036.04/857965.92 -> 0.015194123 | AI34: =-3653.53/835360.06 -> -0.0043735991 | AJ34: =-4081.5/789379.59 -> -0.0051705163 | AK34: =-3387.49/910848.77 -> -0.0037190477
C35: Livingstone IE | D35: LI1 | J35: 0 | K35: 0 | L35: 0 | R35: 0 | W35: =-17819.7/39742 -> -0.44838458 | AB35: =-16085.16/31270.41 -> -0.51438916 | AC35: =-1214/15368.83 -> -0.078991049 | AD35: =-1359.2/17403.47 -> -0.078099368 | AE35: =-1214/14734.46 -> -0.082391889 | AF35: =-1214/15115.29 -> -0.080316024 | AG35: =-1335.8/14627.7 -> -0.091319893 | AH35: =-1214/15115.29 -> -0.080316024 | AI35: =-1214/15115.29 -> -0.080316024 | AJ35: =-1214/13652.52 -> -0.088921313 | AK35: =0 -> 0
C36: Acacia IE | D36: ZI1 | J36: =156.16/278807.03 -> 0.00056010065 | K36: 0 | L36: =-14815.52/276671.44 -> -0.053549148 | R36: =-17540.26/228845.01 -> -0.076646897 | W36: =-40897.5/291537 -> -0.14028237 | AB36: =-120894.98/387394.9 -> -0.31207169 | AC36: =-23125.34/326074.19 -> -0.070920486 | AD36: =-1035.18/341431.26 -> -0.0030318841 | AE36: =-8211.5/344966.6 -> -0.023803754 | AF36: =-2168/325184.72 -> -0.0066669799 | AG36: =-2246.88/304421.44 -> -0.0073808205 | AH36: =-2168/314846.36 -> -0.0068858983 | AI36: =-2278.64/283582.69 -> -0.0080351872 | AJ36: =-712/256516.24 -> -0.0027756527 | AK36: =-2319/343434.33 -> -0.0067523826
C37: Livingstones SGV | D37: LS1 | J37: 0 | K37: 0 | L37: 0 | R37: 0 | W37: 0 | AB37: 0 | AC37: 0 | AD37: =0 -> 0 | AE37: 0 | AF37: 0 | AG37: 0 | AH37: 0 | AI37: 0 | AJ37: 0 | AK37: 0
C38: Acacia SGV | D38: ZS1 | J38: 0 | K38: =-14737.06/181983.09 -> -0.080980381 | L38: =-4747.84/193156.74 -> -0.024580245 | R38: =-26854.22/237249.37 -> -0.11318985 | W38: =-9507.67/228611.03 -> -0.041588851 | AB38: =-53348.29/299826.63 -> -0.17793046 | AC38: =-123474.47/411557.2 -> -0.30001776 | AD38: =-2687.1/271066.63 -> -0.0099130609 | AE38: =-2060/216138.11 -> -0.009530943 | AF38: =-9020.08/193425.01 -> -0.046633473 | AG38: =-2060/181453.67 -> -0.01135276 | AH38: =-2353.36/191175.48 -> -0.012309947 | AI38: =-2060/187290.36 -> -0.010998964 | AJ38: =-21779.9/140561.31 -> -0.15494947 | AK38: =-253.44/131006.1 -> -0.0019345664
C39: Livingstones Desert | D39: XD1 | J39: =-1304.08/313799.55 -> -0.004155774 | K39: =-1226/322543.8 -> -0.0038010342 | L39: =-128846.44/534396.81 -> -0.2411063 | R39: =-27209.02/446138.92 -> -0.060987775 | W39: =-162040.26/633816.27 -> -0.25565809 | AB39: =-30056.95/518108.14 -> -0.058012889 | AC39: 0 | AD39: =-12062.45/561979.05 -> -0.021464234 | AE39: =-3843.38/470419.03 -> -0.0081701202 | AF39: =-5814.33/421613.62 -> -0.01379066 | AG39: =-13482.86/371679.87 -> -0.036275465 | AH39: =-2525.28/432716.36 -> -0.0058358783 | AI39: =-1690.36/508924 -> -0.003321439 | AJ39: =-12775.39/505246.82 -> -0.025285444 | AK39: =-1817.74/522984.35 -> -0.0034757063
C40: Acacia Desert | D40: ZD1 | J40: =-136.64/250460.33 -> -0.00054555546 | K40: =-767.31/177119.44 -> -0.0043321614 | L40: =-6905.79/222814.65 -> -0.030993429 | R40: =-663.68/193268.46 -> -0.0034339799 | W40: =-54040.91/260970.73 -> -0.20707652 | AB40: 0 | AC40: 0 | AD40: =-20994.73/201386.34 -> -0.10425101 | AE40: =-1675/163970.66 -> -0.010215242 | AF40: =-20169.72/244597.08 -> -0.082461001 | AG40: =-10430.07/264197.45 -> -0.039478314 | AH40: =-2316.06/227289.78 -> -0.010189899 | AI40: =-177.98/174788.1 -> -0.0010182615 | AJ40: =-15790/219211.49 -> -0.072030896 | AK40: =-4400/137098.68 -> -0.032093672
A41: Billing Manual Adjustment %
D42: HL1 | J42: =-41267.31/(405942.08-12476.4) -> -0.1048816 | K42: =-34496.11/(333582.79-7430.66) -> -0.10576693 | L42: =-58139.14/(395983.97+12802.58) -> -0.14222371 | R42: =-42396.04/(293987.28-3775.24) -> -0.14608643 | W42: =-76919.83/(218766.01+1745.86) -> -0.34882399 | AB42: =-16575.27/(167815.72+7162.87) -> -0.094727418 | AC42: =-31117.03/(146193.91+538.99) -> -0.2120658 | AD42: =-92241.9/(122385.41-2666.26) -> -0.77048576 | AE42: =-18644.89/(111138.58-133.72) -> -0.16796463 | AF42: =-16529.73/(244155.56-1008.78) -> -0.067982517 | AG42: =-17158.4/(381600.66+3491.53) -> -0.044556603 | AH42: =-25653.41/(417354.81+2657.99) -> -0.061077686 | AI42: =-9271.94/(370141.67-1901.95) -> -0.025179087 | AJ42: =-23293.15/(314543.91-4764.45) -> -0.075192687 | AK42: =-13234.18/(213295.97+2688.93) -> -0.061273635
D43: PO1 | J43: =-10717.24/(302225.63-859.24) -> -0.035562161 | K43: =-41967.87/(286076.41-199.97) -> -0.14680423 | L43: =-18899.89/(297197.58+4720.8) -> -0.062599336 | R43: =-23768.58/(393502.24-2823.85) -> -0.060839249 | W43: =-12024.14/(529760.55+3391.25) -> -0.022552939 | AB43: =-39009.93/(496938.66+12063) -> -0.076640084 | AC43: =-38795.63/(555221.24+1733.64) -> -0.069656684 | AD43: =-124830.79/(566861.85+16581.44) -> -0.21395531 | AE43: =-45954.31/(511348.77+8104.51) -> -0.088466686 | AF43: =-47342.12/(409327.98+4567.51) -> -0.11438182 | AG43: =-24381.16/(298765.44+6868.75) -> -0.079772358 | AH43: =-17601.15/(264090.17+2250) -> -0.066085225 | AI43: =-14178.07/(208269.32+7869.8) -> -0.065596964 | AJ43: =-12747.83/(276485.49+15366.58) -> -0.04367908 | AK43: =4198.11/(428044.52+4211.92) -> 0.009712082
B44: Month End Close Revenue Report | C44: Livingstones Orange | D44: LO1 | J44: 0 | K44: 0 | L44: 0 | R44: 0 | W44: 0 | AB44: =-145.88/7299.32 -> -0.019985423 | AC44: =-1705.46/(56407.51-33332.07) -> -0.073908016 | AD44: =-691.21/11180.63 -> -0.061822098 | AE44: 0 | AF44: 0 | AG44: 0 | AH44: 0 | AI44: 0 | AJ44: 0 | AK44: 0
C45: Acacia Orange | D45: XO1 | J45: =-10930.48/(602413.3-8859.75) -> -0.018415322 | K45: =-9438.51/(520083.2-13417.98) -> -0.018628691 | L45: =-10244.16/(836083.1-164430.57) -> -0.015252172 | R45: =-111792.89/(759153.93-107562.17) -> -0.17156891 | W45: =-12694.26/(955324.77-272142.85) -> -0.018581083 | AB45: =-20687.57/(913265.74-221984.98) -> -0.029926437 | AC45: =-16982.52/(810366.03-150454.67) -> -0.025734547 | AD45: =-9514/(743879.56-25373.16) -> -0.013241357 | AE45: =-6518.19/(801428.56-49174.5) -> -0.0086648785 | AF45: =-43880.9/(851478.27-19880.55) -> -0.05276698 | AG45: =-22344.52/(819948.82-26876.32) -> -0.028174625 | AH45: =-102085.29/(857965.92+13036.04) -> -0.11720443 | AI45: =93497.18/(835360.06-3653.53) -> 0.11241607 | AJ45: =-20518.29/(789379.59-4081.5) -> -0.026128027 | AK45: =-20999.5/(910848.77-3387.49) -> -0.023140932
C46: Livingstone IE | D46: LI1 | J46: 0 | K46: 0 | L46: =-76.17/8933.39 -> -0.0085264385 | R46: =-120.9/14586.3 -> -0.0082885996 | W46: =-537.55/(39742-17819.7) -> -0.024520694 | AB46: =-1768.18/(31270.41-16085.16) -> -0.11644062 | AC46: =-1861.09/(15368.83-1214) -> -0.13148091 | AD46: =-171.58/(17403.47-1359.2) -> -0.010694161 | AE46: =-682.17/(14734.46-1214) -> -0.050454644 | AF46: =-355.75/(15115.29-1214) -> -0.02559115 | AG46: =-121.8/(14627.7-1214) -> -0.0090802687 | AH46: =164.68/(15115.29-1214) -> 0.011846383 | AI46: =-125.64/(15115.29-1214) -> -0.0090380101 | AJ46: =-113.46/(13652.52-1214) -> -0.009121664 | AK46: =-125.66/14960.29 -> -0.0083995698
C47: Acacia IE | D47: ZI1 | J47: =-3926.83/(278807.03-156.16) -> -0.014092294 | K47: =-4877.86/264640.39 -> -0.018432031 | L47: =-4231.95/(276671.44-14815.52) -> -0.016161368 | R47: =-12747.54/(228845.01-17540.26) -> -0.060327749 | W47: =-3011.1/(291537-40897.5) -> -0.012013669 | AB47: =-4828.21/(387394.9-120894.98) -> -0.018117116 | AC47: =-10206.17/(326074.19-23125.34) -> -0.033689417 | AD47: =-8347.83/(341431.26-1035.18) -> -0.024523872 | AE47: =-4322.41/(344966.6-8211.5) -> -0.01283547 | AF47: =-6963.19/(325184.72-2168) -> -0.021556748 | AG47: =-9519.26/(304421.44-2246.88) -> -0.03150252 | AH47: =-22912.18/(314846.36-2168) -> -0.073277153 | AI47: =-4673.94/(283582.69-2278.64) -> -0.01661526 | AJ47: =6200.98/(256516.24-712) -> 0.024241115 | AK47: =-2319/(343434.33-5621.74) -> -0.006864753
C48: Livingstones SGV | D48: LS1 | J48: 0 | K48: 0 | L48: 0 | R48: 0 | W48: =-80.37/4020.21 -> -0.019991493 | AB48: =-245.34/12272.22 -> -0.019991493 | AC48: =-640.1/12272.22 -> -0.052158452 | AD48: =-337.21/5583.82 -> -0.060390557 | AE48: 0 | AF48: 0 | AG48: 0 | AH48: 0 | AI48: 0 | AJ48: 0 | AK48: 0
C49: Acacia SGV | D49: ZS1 | J49: =-2708.82/200721.68 -> -0.013495403 | K49: =-3853.5/(181983.09-14737.06) -> -0.023040906 | L49: =-3387.81/(193156.74-4747.84) -> -0.017981157 | R49: =-8233.86/(237249.37-26854.22) -> -0.039135218 | W49: =-3521.77/(228611.03-9507.67) -> -0.016073555 | AB49: =-5399.78/(299826.63-53348.29) -> -0.021907726 | AC49: =-5082.69/(411557.2-123474.47) -> -0.017643161 | AD49: =-3749.9/(271066.63-2687.1) -> -0.013972377 | AE49: =-4941.85/(216138.11-2060) -> -0.023084331 | AF49: =-3375.15/(193425.01-9020.08) -> -0.018302927 | AG49: =-48591.99/(181453.67-2060) -> -0.27086792 | AH49: =-61130.61/(191175.48-2353.36) -> -0.32374708 | AI49: =-2472.22/(187290.36-2060) -> -0.013346732 | AJ49: =-15211.86/(140561.31-21779.9) -> -0.128066 | AK49: =3178.48/(131006.1-253.44) -> 0.024309104
C50: Livingstones Desert | D50: XD1 | J50: =-27258.94/(313799.55-1304.08) -> -0.087229872 | K50: =-20890.51/(322543.8-1226) -> -0.065015103 | L50: =-19450.28/(534396.81-128846.44) -> -0.047960208 | R50: =-24361.43/(446138.92-27209.02) -> -0.058151567 | W50: =-22338.83/(633816.27-162040.26) -> -0.0473505 | AB50: =-15028.89/(518108.14-30056.95) -> -0.030793676 | AC50: =-42041.09/522771.51 -> -0.080419627 | AD50: =-28887.39/(561979.05-12062.45) -> -0.052530493 | AE50: =-30232.14/(470419.03-3843.38) -> -0.064795795 | AF50: =-23806.44/(421613.62-5814.33) -> -0.057254643 | AG50: =-6476.33/(371679.87-13482.86) -> -0.018080358 | AH50: =-8100.77/(432716.36-2525.28) -> -0.018830632 | AI50: =-9925.06/(508924-1690.36) -> -0.019567038 | AJ50: =-9605.63/(505246.82-12775.39) -> -0.019504949 | AK50: =-29266.29/(522984.35-1817.74) -> -0.056155343
C51: Acacia Desert | D51: ZD1 | J51: =-3824.92/(250460.33-136.64) -> -0.015279896 | K51: =-2676.14/(177119.44-767.31) -> -0.01517498 | L51: =-3391.31/(222814.65-6905.79) -> -0.015707137 | R51: =-7927.12/(193268.46-663.68) -> -0.041157442 | W51: =-10726.37/(260970.73-54040.91) -> -0.051835787 | AB51: =-16602.39/202425.08 -> -0.082017456 | AC51: =-10665.49/185330.13 -> -0.057548603 | AD51: =-3341.24/(201386.34-20994.73) -> -0.018522147 | AE51: =-2677.93/(163970.66-1675) -> -0.016500318 | AF51: =-4394.87/(244597.08-20169.72) -> -0.019582595 | AG51: =-11396.29/(264197.45-10430.07) -> -0.044908412 | AH51: =-14005.29/(227289.78-2316.06) -> -0.062253004 | AI51: =-3081.55/(174788.1-177.98) -> -0.017648175 | AJ51: =-1081.59/(219211.49-15790) -> -0.0053169899 | AK51: =-2315.24/(137098.68-4400) -> -0.017447348
A53: Billing Manual Adjustment Breakdown %
A54: Month End Close Adjustment Detail Report | B54: CMS HIPPS ADJUSTMENT | D54: HL1 | J54: =-3336.71/393465.68 -> -0.0084803076 | K54: =-5225.2/326152.13 -> -0.016020745 | L54: =-2635.97/408786.55 -> -0.0064482797 | R54: =346.93/290212.04 -> 0.0011954363 | W54: =928.67/220511.87 -> 0.0042114286 | AB54: =-6848.09/174978.59 -> -0.039136731 | AC54: -0.027 | AD54: -0.0389 | AE54: -0.02 | AF54: -0.007 | AG54: 0.005 | AH54: -0.02 | AI54: 0.1 | AJ54: -0.036
B55: CONTRACTUAL ADJUSTMENT | D55: HL1 | J55: =-12825/393465.68 -> -0.032594965 | K55: =-11610/326152.13 -> -0.035596885 | L55: =-22045/408786.55 -> -0.0539279 | R55: =-16405/290212.04 -> -0.056527634 | W55: =-13131.4/220511.87 -> -0.059549629 | AB55: =-17372.76/174978.59 -> -0.099285061 | AC55: -0.096 | AD55: -0.0211 | AE55: -0.011 | AF55: -0.01 | AG55: -0.003 | AH55: -0.003 | AI55: -0.01 | AJ55: -0.009 | AK55: -0.012
B56: CONTRACTUAL MANUAL | D56: HL1 | AC56: -0.076 | AD56: -0.0988 | AE56: -0.12 | AF56: -0.032 | AG56: -0.024 | AH56: -0.02 | AI56: -0.001 | AJ56: -0.013 | AK56: -0.032
B57: MSP ADJUSTMENT | D57: HL1 | J57: =-490.01/393465.68 -> -0.0012453691
B58: PDGM PEP | D58: HL1 | AG58: -0.003 | AI58: 0.001
B59: SEQUESTRATION | D59: HL1 | J59: =-7020.69/393465.08 -> -0.017843235 | K59: =-5741.33/326152.13 -> -0.017603227 | L59: =-7016.23/408786.55 -> -0.017163554 | R59: =-4940.31/290212.04 -> -0.017023105 | W59: =-3570.7/220511.87 -> -0.016192779 | AB59: =-2612.6/174978.59 -> -0.01493097 | AC59: -0.014 | AD59: -0.0173 | AE59: -0.017 | AF59: -0.019 | AG59: -0.019 | AH59: -0.019 | AI59: -0.019 | AJ59: -0.019 | AK59: -0.018
B60: SMALL BALANCE ADJUSTMENT | D60: HL1 | K60: =-6429.36/326152.13 -> -0.019712764 | L60: =-23615.36/408786.55 -> -0.057769415 | R60: =-15778.9/290212.04 -> -0.054370246 | W60: =-8100.08/220511.87 -> -0.036733079 | AB60: =346.16/174978.59 -> 0.0019782992 | AC60: 0.002 | AH60: 0.001 | AI60: 0.003 | AJ60: 0.002 | AK60: 0.001
B61: TIMELY FILING | D61: HL1 | R61: =-5590.84/290212.04 -> -0.019264673 | W61: =-3844.73/220511.87 -> -0.017435479 | AD61: -0.5404
B62: UNCOLLECTABLE/BAD DEBT | D62: HL1 | J62: =-17464.4/393465.68 -> -0.044386082 | K62: =-5483.31/326152.13 -> -0.016812124 | L62: =-2807.8/408786.55 -> -0.0068686213 | W62: =-49195.09/220511.87 -> -0.22309497 | AB62: =9912.02/174978.59 -> 0.056647045 | AC62: -0.055 | AD62: -0.0538
B64: CMS HIPPS ADJUSTMENT | D64: PO1 | J64: =-4910.21/301366.4 -> -0.016293157 | K64: =-21243.17/285876.44 -> -0.074308922 | L64: =-12954.47/301918.38 -> -0.042907192 | R64: =-13621.79/390678.39 -> -0.034867017 | W64: =-9604.16/533151.8 -> -0.018013931 | AB64: =-27766.74/509001.66 -> -0.054551374 | AC64: -0.042 | AD64: -0.0661 | AE64: -0.086 | AF64: -0.111 | AG64: -0.063 | AH64: -0.064 | AI64: -0.059 | AJ64: -0.04 | AK64: 0.003
B65: CONTRACTUAL ADJUSTMENT | D65: PO1 | AB65: =-2614.94/509001.66 -> -0.0051373899 | AC65: 0.004
B66: CONTRACTUAL MANUAL | D66: PO1 | AD66: -0.0123 | AF66: -0.001 | AG66: -0.001 | AI66: -0.002 | AJ66: -0.002
B67: MSP ADJUSTMENT | D67: PO1 | K67: =-3061.66/285876.44 -> -0.010709732 | L67: =-41.07/301918.38 -> -0.00013603014
B68: PAYER INITIATED ADJUSTMENT | D68: PO1 | AG68: -0.003 | AI68: -0.003 | AK68: 0.012
B69: PDGM PEP | D69: PO1 | AG69: -0.011 | AK69: -0.002
B70: SEQUESTRATION | D70: PO1 | J70: =-5807.03/301366.4 -> -0.019269003 | K70: =-5607.48/285876.44 -> -0.019615048 | L70: =-5904.35/301918.38 -> -0.019556113 | R70: =-4260.36/390678.39 -> -0.010905031 | W70: =-2803.76/533151.8 -> -0.00525884 | AB70: =(-2043.39-64.26)/509001.66 -> -0.0041407527 | AC70: -0.003 | AD70: -0.0025 | AE70: -0.002 | AF70: -0.002 | AG70: -0.002 | AH70: -0.002 | AI70: -0.002 | AJ70: -0.001
B71: SMALL BALANCE ADJUSTMENT | D71: PO1 | W71: =383.78/533151.8 -> 0.00071983251 | AE71: 0.008 | AK71: -0.003
B72: TIMELY FILING | D72: PO1 | AB72: =-4664.89/509001.66 -> -0.0091647835 | AC72: -0.01 | AD72: -0.0853 | AE72: -0.008
B73: UNCOLLECTABLE/BAD DEBT | D73: PO1 | K73: =-12055.56/285876.44 -> -0.042170527 | R73: =-5843.94/390678.39 -> -0.014958442 | AB73: =-1855.7/509001.66 -> -0.0036457641 | AC73: -0.018 | AD73: -0.0477
B75: CONTRACTUAL ADJUSTMENT | D75: LO1 | AC75: -0.067 | AD75: -0.0523
B76: SEQUESTRATION | D76: LO1 | AC76: -0.007 | AD76: -0.0096
B78: CONTRACTUAL ADJUSTMENT | D78: XO1 | W78: =-356.58/683181.92 -> -0.00052194004 | AB78: =-5003.19/691280.76 -> -0.0072375658 | AC78: -0.006 | AG78: -0.001 | AH78: -0.001 | AI78: -0.001 | AJ78: -0.001 | AK78: -0.001
B79: CONTRACTUAL MANUAL | D79: XO1 | AD79: 0.0057 | AE79: 0.027 | AF79: -0.004 | AG79: -0.003 | AH79: -0.001 | AI79: 0.028 | AJ79: -0.007 | AK79: -0.002
B80: NON-CONTRACT PROVIDER | D80: XO1 | AF80: -0.022 | AH80: -0.06 | AK80: -0.008
B81: NO AUTHORIZATION | D81: XO1 | AG81: -0.006 | AH81: -0.02 | AK81: 0.008
B82: PAYER INITIATED ADJUSTMENT | D82: XO1 | AK82: -0.002
B83: SEQUESTRATION | D83: XO1 | J83: =-10944.29/593553.6 -> -0.018438588 | K83: =-9438.19/506665.22 -> -0.01862806 | L83: =-10245.23/671652.53 -> -0.015253765 | R83: =(-10239.02-171.83)/651591.76 -> -0.015977565 | W83: =(-12183.94-36.38)/683181.92 -> -0.017887359 | AB83: =(-12028.6-177.56)/691280.76 -> -0.017657312 | AC83: -0.0195 | AD83: -0.0188 | AE83: -0.018 | AF83: -0.018 | AG83: -0.018 | AH83: -0.018 | AI83: -0.019 | AJ83: -0.018 | AK83: -0.019
B84: SMALL BALANCE ADJUSTMENT | D84: XO1 | J84: =13.81/593553.6 -> 2.3266643e-05 | K84: =-0.32/506665.22 -> -6.3158075e-07 | L84: =1.07/671652.53 -> 1.5930856e-06 | R84: =-27.75/651591.76 -> -4.2588016e-05 | W84: =-117.36/683181.92 -> -0.00017178441 | AB84: =7.36/691280.76 -> 1.0646904e-05
B85: TIMELY FILING | D85: XO1 | R85: =-78995.24/651591.76 -> -0.12123425 | AB85: =-3485.58/691280.76 -> -0.005042206 | AF85: -0.009 | AH85: -0.018 | AI85: 0.103
B86: UNCOLLECTABLE/BAD DEBT | D86: XO1 | R86: =-22359.05/651591.76 -> -0.034314507 | AD86: -0.0001
B88: CONTRACTUAL ADJUSTMENT | D88: LI1 | AB88: =-1840.9/15185.25 -> -0.12122948
B89: PAYER INITIATED ADJUSTMENT | D89: LI1 | AH89: 0.021
B90: SEQUESTRATION | D90: LI1 | L90: =-76.17/8933.19 -> -0.0085266293 | R90: =-120.9/14586.3 -> -0.0082885996 | W90: =-537.55/21922.3 -> -0.024520694 | AB90: =(-157.17+229.89)/15185.25 -> 0.0047888576 | AC90: -0.0736 | AD90: -0.0107 | AE90: -0.05 | AG90: -0.009 | AH90: -0.009 | AI90: -0.009 | AJ90: -0.009 | AK90: -0.008
B91: UNCOLLECTABLE/BAD DEBT | D91: LI1 | AC91: -0.0578
B93: CONTRACTUAL ADJUSTMENT | D93: ZI1 | W93: =836.81/250639.5 -> 0.0033386996 | AB93: =-607.71/266519.92 -> -0.0022801673 | AC93: 0.0029
B94: CONTRACTUAL MANUAL | D94: ZI1 | AC94: 0.0043 | AD94: -0.0075 | AE94: -0.004 | AF94: -0.003 | AG94: -0.003 | AJ94: 0.053
B95: INTEREST RECEIVED FROM PAYER | D95: ZI1 | AF95: 0.001
B96: NO AUTHORIZATION | D96: ZI1 | AG96: -0.009
B97: NO COVERAGE | D97: ZI1 | AH97: -0.042
B98: NON-CONTRACT PROVIDER | D98: ZI1 | AH98: -0.01
B99: SEQUESTRATION | D99: ZI1 | J99: =-3926.93/278650.9 -> -0.014092651 | K99: =-4880.07/264640.39 -> -0.018440382 | L99: =-4230.56/261855.92 -> -0.01615606 | R99: =(-3651.85-3686.6)/211304.75 -> -0.034729224 | W99: =-3852.39/250639.5 -> -0.015370243 | AB99: =-4242.45/266519.92 -> -0.015917947 | AC99: -0.0161 | AD99: -0.0164 | AE99: -0.016 | AF99: -0.017 | AG99: -0.017 | AH99: -0.017 | AI99: -0.017 | AJ99: -0.017 | AK99: -0.016
B100: SMALL BALANCE ADJUSTMENT | D100: ZI1 | J100: =0.1/278650.9 -> 3.5887198e-07 | K100: =2.21/264640.39 -> 8.350955e-06 | L100: =-1.39/261855.92 -> -5.3082627e-06 | R100: =46.66/211304.75 -> 0.00022081851 | W100: =4.48/250639.5 -> 1.7874278e-05 | AB100: =21.95/266519.92 -> 8.2357822e-05
B101: TIMELY FILING | D101: ZI1 | AB101: =-1579.78/246478.34 -> -0.006409407 | AD101: -0.0007 | AG101: -0.002 | AH101: -0.005
B102: UNCOLLECTABLE/BAD DEBT | D102: ZI1 | R102: =-5455.75/211304.75 -> -0.025819344 | AC102: -0.0248 | AF102: -0.002 | AJ102: -0.012
B104: SEQUESTRATION | D104: LS1 | W104: =-80.37/4020.21 -> -0.019991493 | AB104: =-245.34/12272.22 -> -0.019991493 | AC104: -0.0522 | AD104: -0.0604
D105: LS1
B107: CONTRACTUAL ADJUSTMENT | D107: ZS1 | W107: =608.46/219103.36 -> 0.0027770455 | AB107: =299.61/246478.34 -> 0.0012155632 | AC107: -0.0011 | AD107: -0.0024 | AJ107: 0.015
B108: CONTRACTUAL MANUAL | D108: ZS1 | AD108: 0.0059 | AE108: -0.006 | AF108: -0.001 | AG108: 0.012 | AI108: 0.004
...

Sheet HR
A1: KPI | B1: Definition | C1: Benchmark | D1: Service Line | E1: 45931 | F1: 45962 | G1: 45992 | H1: 46023 | I1: 46054 | J1: 46082
A2: HR/ RECRUITMENT
A3: Open Jobs
D4: Home Health | G4: 1 | J4: 2
D5: Hospice OC | I5: 1 | J5: 4
D6: Hospice IE/SGV
D7: Hospice Desert | I7: 1 | J7: 3
D8: Midco OC | G8: 1 | J8: 1
D9: Midco IE/SGV | I9: 1
D10: Midco Desert | J10: 2
A11: Time to Hire
B12: From Recquisition to Offer Acceptance | C12: 14 days | D12: ALL ( Acacia)
B13: Cost per hire
B14: Month end report
A15: Cost per hire
A17: Retention Rate | C17: 0.9
A19: HR Files (complete) | C19: 1
A21: Employee Satisfaction | C21: 0.9
A24: COMPLIANCE/ QA
A25: FALLS
C26: 14 days | D26: ALL ( Acacia)
A27: COMPLAINTS | B27: Complaints Resolved | C27: 1
A29: INFECTIONS
A31: LIVE DC'S | C31: 0.9
A32: Revocations & transfers
A33: TERMINATIONS | C33: 1
A35: Employee Satisfaction | C35: 0.9
A37: ADRs | C37: 0.9
A39: ACTIVE LAWSUITS
A41: GRIEVANCE
A42: iNCIDENT REPORTS
A43: WORKER INJURIES
A44: EMERGENCY PREP

Sheet Avg Salary by Position
A3: Company | B3: Location | C3: Position | D3: Total Pay 05/09/25 | E3: FTE Count | F3: Average Annual Pay | G3: Notes
A4: Palliative | C4: CHHA | D4: 334.8 | E4: 0.158125 | F4: =(D4/E4)*26 -> 55050.119
C5: LVN | D5: 7044.5 | E5: 2.41375 | F5: =(D5/E5)*26 -> 75880.684 | G5: Lets have this updated for Q4 2025 | J5: =+F5/2080 -> 36.481098
C6: RN | D6: 8175.44 | E6: 1.877375 | F6: =(D6/E6)*26 -> 113222.69 | J6: =+F6/2080 -> 54.433984
C7: Counseling | D7: 380 | E7: 0.14 | F7: =(D7/E7)*26 -> 70571.429 | J7: =+F7/2080 -> 33.928571
C8: MSW | D8: 3076.92 | E8: 1 | F8: =(D8/E8)*26 -> 79999.92 | G8: Sow trend and do by QUarter | J8: =+F8/2080 -> 38.4615
C9: PT | D9: 23181.23 | E9: 4.73875 | F9: =(D9/E9)*26 -> 127187.97 | J9: =+F9/2080 -> 61.148061
A10: Home Health | C10: CHHA | D10: 120 | E10: 0.06 | F10: =(D10/E10)*26 -> 52000 | G10: Keep ny location | J10: =+F10/2080 -> 25
C11: LVN | D11: 7712.14 | E11: 2.41375 | F11: =(D11/E11)*26 -> 83072.249 | J11: =+F11/2080 -> 39.938581
C12: RN | D12: 20673.84 | E12: 4.95875 | F12: =(D12/E12)*26 -> 108398.25 | J12: =+F12/2080 -> 52.114545
C13: Counseling | D13: 0 | E13: 0 | F13: 0 | J13: =+F13/2080 -> 0
C14: MSW | D14: 0 | E14: 0 | F14: 0 | J14: =+F14/2080 -> 0
C15: PT | D15: 4775.6 | E15: 1.51 | F15: =(D15/E15)*26 -> 82228.874 | J15: =+F15/2080 -> 39.533113
A16: Hospice includ. Living Stones | B16: Desert | C16: CHHA | D16: 10044.73 | E16: 5.15775 | F16: =(D16/E16)*26 -> 50635.06 | J16: =+F16/2080 -> 24.343779
B17: Desert | C17: LVN | D17: 14024.02 | E17: 4.129 | F17: =(D17/E17)*26 -> 88308.191 | J17: =+F17/2080 -> 42.455861
B18: Desert | C18: RN | D18: 25234.97 | E18: 5.68275 | F18: =(D18/E18)*26 -> 115456.29 | J18: =+F18/2080 -> 55.507831
B19: Desert | C19: NP | D19: 0 | E19: 0 | F19: 0 | J19: =+F19/2080 -> 0
B20: Desert | C20: Counseling | D20: 0 | E20: 0 | F20: 0 | J20: =+F20/2080 -> 0
B21: Desert | C21: MSW | D21: 9689.44 | E21: 3.01925 | F21: =(D21/E21)*26 -> 83439.742 | J21: =+F21/2080 -> 40.11526
B22: IE | C22: CHHA | D22: 8512.85 | E22: 4.16575 | F22: =(D22/E22)*26 -> 53131.873 | J22: =+F22/2080 -> 25.54417
B23: IE | C23: LVN | D23: 3950.19 | E23: 1.12275 | F23: =(D23/E23)*26 -> 91476.232 | J23: =+F23/2080 -> 43.978958
B24: IE | C24: RN | D24: 19183.63 | E24: 4.190625 | F24: =(D24/E24)*26 -> 119021.48 | J24: =+F24/2080 -> 57.221864
B25: IE | C25: NP | D25: 1050 | E25: 0.11 | F25: =(D25/E25)*26 -> 248181.82 | J25: =+F25/2080 -> 119.31818
B26: IE | C26: Counseling | D26: 3122.13 | E26: 1.003375 | F26: =(D26/E26)*26 -> 80902.335 | J26: =+F26/2080 -> 38.895353
B27: IE | C27: MSW | D27: 3893.48 | E27: 1.0135 | F27: =(D27/E27)*26 -> 99882.072 | J27: =+F27/2080 -> 48.020227
B28: OC | C28: CHHA | D28: 10967.42 | E28: 6.151375 | F28: =(D28/E28)*26 -> 46355.964 | J28: =+F28/2080 -> 22.286521
B29: OC | C29: LVN | D29: 4029 | E29: 1.38 | F29: =(D29/E29)*26 -> 75908.696 | J29: =+F29/2080 -> 36.494565
B30: OC | C30: RN | D30: 27083.22 | E30: 5.8015 | F30: =(D30/E30)*26 -> 121376.15 | J30: =+F30/2080 -> 58.353917
B31: OC | C31: NP | D31: 0 | E31: 0 | F31: 0 | J31: =+F31/2080 -> 0
B32: OC | C32: Counseling | D32: 5950.77 | E32: 2 | F32: =(D32/E32)*26 -> 77360.01 | J32: =+F32/2080 -> 37.192313
B33: OC | C33: MSW | D33: 2961.54 | E33: 1 | F33: =(D33/E33)*26 -> 77000.04 | J33: =+F33/2080 -> 37.01925
B34: OC | C34: Clinical Liaison | D34: 5015.85 | E34: 1 | F34: =(D34/E34)*26 -> 130412.1 | G34: Nina also does LVN visits, but couldn't split it | J34: =+F34/2080 -> 62.698125
B35: SGV | C35: CHHA | D35: 4117.2 | E35: 1.99525 | F35: =(D35/E35)*26 -> 53651.021 | J35: =+F35/2080 -> 25.79376
B36: SGV | C36: LVN | D36: 7852.49 | E36: 1.83 | F36: =(D36/E36)*26 -> 111565.43 | G36: Naomi is in this group, but also does OC visits, couldn't split it | J36: =+F36/2080 -> 53.637227
B37: SGV | C37: RN | D37: 4862.38 | E37: 1.129125 | F37: =(D37/E37)*26 -> 111964.47 | J37: =+F37/2080 -> 53.829071
B38: SGV | C38: NP | D38: 0 | E38: 0 | F38: 0 | J38: =+F38/2080 -> 0
B39: SGV | C39: Counseling | D39: 2916 | E39: 1.000625 | F39: =(D39/E39)*26 -> 75768.645 | G39: FT FTE's only no per diem | J39: =+F39/2080 -> 36.427233
B40: SGV | C40: MSW | D40: 0 | E40: 0 | F40: 0

Sheet Hospice Administrator Scorecard
A1: ACACIA HEALTH HOSPICE SCORECARD
A2: KPI | B2: Benchmark | C2: Service Line | D2: 45690 | E2: =D2+7 -> 45697 | F2: =E2+7 -> 45704 | G2: =F2+7 -> 45711 | H2: 45689 | I2: =G2+7 -> 45718 | J2: =I2+7 -> 45725 | K2: =J2+7 -> 45732 | L2: =K2+7 -> 45739 | M2: 45717 | N2: 3/30-4/5 | O2: 4/6-4/12 | P2: 4/13-4/19 | Q2: 4/20-4/26 | R2: 4/27-5/3 | S2: 45748 | T2: 5/4-5/10 | U2: 5/11-5/17 | V2: 5/18-5/24 | W2: 5/25-5/31 | X2: 45778 | Y2: 6/1-6/7 | Z2: 6/8-6/14 | AA2: 6/15-6/21 | AB2: 6/22-6/28 | AC2: 45809 | AD2: 6/29-7/5 | AE2: 7/6-7/12 | AF2: 7/13-7/19 | AG2: 7/20-7/26 | AH2: 7/27-8/2 | AI2: 45839 | AJ2: 8/3-8/9 | AK2: 8/10-8/16 | AL2: 8/17-8/23 | AM2: 8/24-8/30 | AN2: 45870 | AO2: 8/31-9/6 | AP2: 9/7-9/13 | AQ2: 9/14-9/20 | AR2: 9/21-9/27 | AS2: 45901 | AT2: 9/28-10/4 | AU2: 10/5-10/11 | AV2: 10/12-10/18 | AW2: 10/19-10/25 | AX2: 10/26-11/1 | AY2: 45931 | AZ2: ='Company Scorecard'!BG1 -> 11/2-11/8 | BA2: ='Company Scorecard'!BH1 -> 11/9-11/15 | BB2: ='Company Scorecard'!BI1 -> 11/16-11/22 | BC2: ='Company Scorecard'!BJ1 -> 11/23-11/29 | BD2: 45962 | BE2: ='Company Scorecard'!BL1 -> 11/30-12/6 | BF2: ='Company Scorecard'!BM1 -> 12/7-12/13 | BG2: ='Company Scorecard'!BN1 -> 12/14-12/20 | BH2: ='Company Scorecard'!BO1 -> 12/21-12/27 | BI2: ='Company Scorecard'!BP1 -> 12/28-1/3 | BJ2: ='Company Scorecard'!BQ1 -> 45992 | BK2: ='Company Scorecard'!BR1 -> 1/4-1/10 | BL2: ='Company Scorecard'!BS1 -> 1/11-1/17 | ... CE2: ='Company Scorecard'!CL1 -> 46113
A3: Current Census | B3: Benchmark
B4: increase 15% per quarter | C4: Hospice OC | D4: ='Company Scorecard'!K10 -> 78 | E4: ='Company Scorecard'!L10 -> 80 | F4: ='Company Scorecard'!M10 -> 81 | G4: ='Company Scorecard'!N10 -> 82 | H4: ='Company Scorecard'!O10 -> 79.1 | I4: ='Company Scorecard'!P10 -> 82 | J4: ='Company Scorecard'!Q10 -> 86 | K4: ='Company Scorecard'!R10 -> 88 | ... CE4: ='Company Scorecard'!CL10 -> 123
B5: increase 15% per quarter | C5: Hospice IE | D5: ='Company Scorecard'!K11 -> 36 | E5: ='Company Scorecard'!L11 -> 36 | F5: ='Company Scorecard'!M11 -> 38 | G5: ='Company Scorecard'!N11 -> 36.6 | H5: ='Company Scorecard'!O11 -> 36.6 | I5: ='Company Scorecard'!P11 -> 36.2 | J5: ='Company Scorecard'!Q11 -> 34 | K5: ='Company Scorecard'!R11 -> 34 | ... O5: ='Company Scorecard'!V11 -> 32 | P5: 33 | Q5: ='Company Scorecard'!X11 -> 33 | R5: ='Company Scorecard'!Y11 -> 33 | S5: ='Company Scorecard'!Z11 -> 33.3 | T5: ='Company Scorecard'!AA11 -> 31 | U5: ='Company Scorecard'!AB11 -> 31 | V5: ='Company Scorecard'!AC11 -> 33 | W5: ='Company Scorecard'!AD11 -> 35 | X5: ='Company Scorecard'!AE11 -> 33.8 | ... CE5: ='Company Scorecard'!CL11 -> 48
B6: increase 15% per quarter | C6: Hospice SGV | D6: ='Company Scorecard'!K12 -> 24.5 | E6: ='Company Scorecard'!L12 -> 25 | F6: ='Company Scorecard'!M12 -> 24 | G6: ='Company Scorecard'!N12 -> 26 | H6: ='Company Scorecard'!O12 -> 24.5 | I6: ='Company Scorecard'!P12 -> 23.8 | J6: ='Company Scorecard'!Q12 -> 25 | K6: ='Company Scorecard'!R12 -> 26 | ... N6: ='Company Scorecard'!U12 -> 29 | O6: 28 | P6: ='Company Scorecard'!W12 -> 28 | Q6: 27 | R6: 27 | S6: ='Company Scorecard'!Z12 -> 28 | T6: 27 | U6: 27 | V6: 27 | W6: 27 | X6: ='Company Scorecard'!AE12 -> 30.9 | Y6: ='Company Scorecard'!AF12 -> 31 | Z6: ='Company Scorecard'!AG12 -> 32 | AA6: ='Company Scorecard'!AH12 -> 35 | AB6: ='Company Scorecard'!AI12 -> 34 | AC6: ='Company Scorecard'!AJ12 -> 35.9 | AD6: ='Company Scorecard'!AK12 -> 34 | AE6: ='Company Scorecard'!AL12 -> 33 | ... CE6: ='Company Scorecard'!CL12 -> 19
B7: increase 15% per quarter | C7: Hospice Desert | D7: ='Company Scorecard'!K13 -> 75 | E7: ='Company Scorecard'!L13 -> 74 | F7: ='Company Scorecard'!M13 -> 74 | G7: ='Company Scorecard'!N13 -> 74 | H7: ='Company Scorecard'!O13 -> 71.1 | I7: ='Company Scorecard'!P13 -> 81 | J7: ='Company Scorecard'!Q13 -> 86 | K7: ='Company Scorecard'!R13 -> 84 | ... M7: ='Company Scorecard'!T13 -> 83 | N7: 85 | O7: 88 | P7: 89 | Q7: 92 | R7: 92 | S7: ='Company Scorecard'!Z13 -> 86.3 | T7: 92 | U7: 92 | V7: 92 | W7: 92 | X7: ='Company Scorecard'!AE13 -> 92.6 | Y7: ='Company Scorecard'!AF13 -> 100 | Z7: ='Company Scorecard'!AG13 -> 100 | AA7: ='Company Scorecard'!AH13 -> 98 | AB7: ='Company Scorecard'!AI13 -> 97 | AC7: ='Company Scorecard'!AJ13 -> 98.3 | AD7: ='Company Scorecard'!AK13 -> 95 | AE7: ='Company Scorecard'!AL13 -> 96 | ... CE7: ='Company Scorecard'!CL13 -> 85.4
B8: increase 15% per quarter | C8: Total Hospice | D8: =SUM(D4:D7) -> 213.5 | E8: =SUM(E4:E7) -> 215 | F8: =SUM(F4:F7) -> 217 | G8: =SUM(G4:G7) -> 218.6 | H8: =SUM(H4:H7) -> 211.3 | I8: =SUM(I4:I7) -> 223 | J8: =SUM(J4:J7) -> 231 | K8: =SUM(K4:K7) -> 232 | ... CE8: =SUM(CE4:CE7) -> 275.4
A9: Admissions | B9: Benchmark
B10: 35 | C10: Hospice OC | D10: ='Company Scorecard'!K23 -> 0 | E10: ='Company Scorecard'!L23 -> 8 | F10: ='Company Scorecard'!M23 -> 7 | G10: ='Company Scorecard'!N23 -> 3 | H10: ='Company Scorecard'!O23 -> 18 | I10: ='Company Scorecard'!P23 -> 7 | J10: ='Company Scorecard'!Q23 -> 7 | K10: ='Company Scorecard'!R23 -> 4 | ... CE10: ='Company Scorecard'!CL23 -> 21
B11: 20 | C11: Hospice IE | D11: ='Company Scorecard'!K24 -> 2 | E11: ='Company Scorecard'!L24 -> 1 | F11: ='Company Scorecard'!M24 -> 1 | G11: ='Company Scorecard'!N24 -> 0 | H11: ='Company Scorecard'!O24 -> 4 | I11: ='Company Scorecard'!P24 -> 0 | J11: ='Company Scorecard'!Q24 -> 2 | K11: ='Company Scorecard'!R24 -> 0 | ... CE11: ='Company Scorecard'!CL24 -> 11
B12: 15 | C12: Hospice SGV | D12: ='Company Scorecard'!K25 -> 3 | E12: ='Company Scorecard'!L25 -> 2 | F12: ='Company Scorecard'!M25 -> 0 | G12: ='Company Scorecard'!N25 -> 3 | H12: ='Company Scorecard'!O25 -> 8 | I12: ='Company Scorecard'!P25 -> 0 | J12: ='Company Scorecard'!Q25 -> 3 | K12: ='Company Scorecard'!R25 -> 1 | ... CE12: ='Company Scorecard'!CL25 -> 5
B13: 35 | C13: Hospice Desert | D13: ='Company Scorecard'!K26 -> 8 | E13: ='Company Scorecard'!L26 -> 10 | F13: ='Company Scorecard'!M26 -> 7 | G13: ='Company Scorecard'!N26 -> 6 | H13: ='Company Scorecard'!O26 -> 33 | I13: ='Company Scorecard'!P26 -> 12 | J13: ='Company Scorecard'!Q26 -> 10 | K13: ='Company Scorecard'!R26 -> 5 | ... CE13: ='Company Scorecard'!CL26 -> 21
A14: Weekly Referral | B14: Benchmark
B15: 8 | C15: Hospice OC | D15: 5 | E15: 5 | F15: 5 | G15: 9 | H15: =SUM(D15:G15) -> 24 | I15: 5 | J15: 8 | K15: 8 | L15: 11 | M15: 40 | N15: 5 | O15: 10 | P15: 9 | Q15: 13 | R15: 6 | S15: 37 | T15: 12 | U15: 13 | V15: 13 | W15: 10 | X15: 46 | Y15: 7 | Z15: 7 | AA15: 8 | AB15: 9 | AC15: 34 | AD15: 8 | AE15: 4 | AF15: 12 | AG15: 7 | AH15: 6 | AI15: 31 | AJ15: 9 | AK15: 9 | AL15: 8 | AM15: 10 | AN15: 36 | AO15: 10 | AP15: 8 | AQ15: 7 | AR15: 5 | AS15: 35 | AT15: 10 | AU15: 9 | AV15: 10 | AW15: 11 | AX15: 7 | AY15: 41 | AZ15: 11 | BA15: 15 | BB15: 6 | BC15: 5 | BD15: 37 | BE15: 12 | BF15: 14 | BG15: 9 | BH15: 5 | BI15: 6 | BJ15: 43 | BK15: 6 | BL15: 5 | BM15: 7 | BN15: 0 | BO15: 31 | BP15: 11 | BQ15: 15 | BR15: 7 | BS15: 15 | BT15: 48 | BU15: 14 | BV15: 5 | BW15: 14 | BX15: 6 | BY15: 42 | BZ15: 6 | CA15: 10 | CB15: 11 | CC15: 9 | CD15: 9 | CE15: 37
B16: 4 | C16: Hospice IE | D16: 2 | E16: 2 | F16: 2 | G16: 1 | H16: =SUM(D16:G16) -> 7 | I16: 0 | J16: 2 | K16: 2 | L16: 1 | M16: 6 | N16: 0 | O16: 2 | P16: 3 | Q16: 1 | R16: 1 | S16: 7 | T16: 2 | U16: 1 | V16: 1 | W16: 2 | X16: 10 | Y16: 5 | Z16: 2 | AA16: 5 | AB16: 3 | AC16: 15 | AD16: 4 | AE16: 2 | AF16: 2 | AG16: 4 | AH16: 6 | AI16: 18 | AJ16: 6 | AK16: 3 | AL16: 6 | AM16: 1 | AN16: 17 | AO16: 2 | AP16: 3 | AQ16: 1 | AR16: 3 | AS16: 9 | AT16: 2 | AU16: 2 | AV16: 5 | AW16: 11 | AX16: 6 | AY16: 27 | AZ16: 1 | BA16: 5 | BB16: 1 | BC16: 2 | BD16: 10 | BE16: 4 | BF16: 8 | BG16: 1 | BH16: 3 | BI16: 2 | BJ16: 18 | BK16: 2 | BL16: 3 | BM16: 4 | BN16: 0 | BO16: 18 | BP16: 10 | BQ16: 6 | BR16: 4 | BS16: 5 | BT16: 24 | BU16: 1 | BV16: 2 | BW16: 3 | BX16: 3 | BY16: 9 | BZ16: 2 | CA16: 7 | CB16: 6 | CC16: 10 | CD16: 5 | CE16: 28
B17: 4 | C17: Hospice SGV | D17: 2 | E17: 4 | F17: 4 | G17: 4 | H17: =SUM(D17:G17) -> 14 | I17: 3 | J17: 3 | K17: 7 | L17: 1 | M17: 16 | N17: 6 | O17: 2 | P17: 3 | Q17: 1 | R17: 0 | S17: 11 | T17: 2 | U17: 2 | V17: 2 | W17: 2 | X17: 9 | Y17: 2 | Z17: 6 | AA17: 4 | AB17: 5 | AC17: 17 | AD17: 2 | AE17: 6 | AF17: 3 | AG17: 5 | AH17: 1 | AI17: 18 | AJ17: 0 | AK17: 6 | AL17: 1 | AM17: 3 | AN17: 12 | AO17: 3 | AP17: 0 | AQ17: 0 | AR17: 1 | AS17: 5 | AT17: 2 | AU17: 3 | AV17: 2 | AW17: 0 | AX17: 2 | AY17: 7 | AZ17: 0 | BA17: 3 | BB17: 5 | BC17: 7 | BD17: 16 | BE17: 2 | BF17: 0 | BG17: 2 | BH17: 0 | BI17: 3 | BJ17: 6 | BK17: 3 | BL17: 0 | BM17: 2 | BN17: 0 | BO17: 2 | BP17: 1 | BQ17: 1 | BR17: 1 | BS17: 2 | BT17: 5 | BU17: 2 | BV17: 1 | BW17: 3 | BX17: 5 | BY17: 12 | BZ17: 6 | CA17: 2 | CB17: 0 | CC17: 2 | CD17: 1 | CE17: 10
B18: 9 | C18: Hospice Desert | D18: 10 | E18: 7 | F18: 7 | G18: 7 | H18: =SUM(D18:G18) -> 31 | I18: 8 | J18: 10 | K18: 6 | L18: 10 | M18: 42 | N18: 5 | O18: 7 | P18: 11 | Q18: 6 | R18: 10 | S18: 37 | T18: 6 | U18: 6 | V18: 6 | W18: 6 | X18: 36 | Y18: 6 | Z18: 5 | AA18: 9 | AB18: 3 | AC18: 23 | AD18: 4 | AE18: 11 | AF18: 5 | AG18: 12 | AH18: 13 | AI18: 41 | AJ18: 8 | AK18: 8 | AL18: 8 | AM18: 5 | AN18: 33 | AO18: 6 | AP18: 3 | AQ18: 8 | AR18: 6 | AS18: 29 | AT18: 12 | AU18: 5 | AV18: 7 | AW18: 12 | AX18: 10 | AY18: 38 | AZ18: 10 | BA18: 8 | BB18: 7 | BC18: 4 | BD18: 30 | BE18: 11 | BF18: 12 | BG18: 14 | BH18: 7 | BI18: 12 | BJ18: =14+38 -> 52 | BK18: 12 | BL18: 9 | BM18: 12 | BN18: 2 | BO18: 48 | BP18: 6 | BQ18: 8 | BR18: 3 | BS18: 14 | BT18: 35 | BU18: 6 | BV18: 10 | BW18: =1+6 -> 7 | BX18: 7 | BY18: 37 | BZ18: 14 | CA18: 6 | CB18: 7 | CC18: 11 | CD18: 8 | CE18: 40
A19: NTUC Rate (Admission / Referral) | B19: Benchmark
B20: <20% | C20: Hospice OC | D20: =IF(IFERROR(1-D10/D15,0)<0,0,IFERROR(1-D10/D15,0)) -> 1 | E20: =IF(IFERROR(1-E10/E15,0)<0,0,IFERROR(1-E10/E15,0)) -> 0 | F20: =IF(IFERROR(1-F10/F15,0)<0,0,IFERROR(1-F10/F15,0)) -> 0 | G20: =IF(IFERROR(1-G10/G15,0)<0,0,IFERROR(1-G10/G15,0)) -> 0.66666667 | H20: =IF(IFERROR(1-H10/H15,0)<0,0,IFERROR(1-H10/H15,0)) -> 0.25 | I20: =IF(IFERROR(1-I10/I15,0)<0,0,IFERROR(1-I10/I15,0)) -> 0 | J20: =IF(IFERROR(1-J10/J15,0)<0,0,IFERROR(1-J10/J15,0)) -> 0.125 | K20: =IF(IFERROR(1-K10/K15,0)<0,0,IFERROR(1-K10/K15,0)) -> 0.5 | ... CE20: =IF(IFERROR(1-CE10/CE15,0)<0,0,IFERROR(1-CE10/CE15,0)) -> 0.43243243
B21: <20% | C21: Hospice IE | D21: =IF(IFERROR(1-D11/D16,0)<0,0,IFERROR(1-D11/D16,0)) -> 0 | E21: =IF(IFERROR(1-E11/E16,0)<0,0,IFERROR(1-E11/E16,0)) -> 0.5 | F21: =IF(IFERROR(1-F11/F16,0)<0,0,IFERROR(1-F11/F16,0)) -> 0.5 | G21: =IF(IFERROR(1-G11/G16,0)<0,0,IFERROR(1-G11/G16,0)) -> 1 | H21: =IF(IFERROR(1-H11/H16,0)<0,0,IFERROR(1-H11/H16,0)) -> 0.42857143 | I21: =IF(IFERROR(1-I11/I16,0)<0,0,IFERROR(1-I11/I16,0)) -> 0 | J21: =IF(IFERROR(1-J11/J16,0)<0,0,IFERROR(1-J11/J16,0)) -> 0 | K21: =IF(IFERROR(1-K11/K16,0)<0,0,IFERROR(1-K11/K16,0)) -> 1 | ... CE21: =IF(IFERROR(1-CE11/CE16,0)<0,0,IFERROR(1-CE11/CE16,0)) -> 0.60714286
B22: <20% | C22: Hospice SGV | D22: =IF(IFERROR(1-D12/D17,0)<0,0,IFERROR(1-D12/D17,0)) -> 0 | E22: =IF(IFERROR(1-E12/E17,0)<0,0,IFERROR(1-E12/E17,0)) -> 0.5 | F22: =IF(IFERROR(1-F12/F17,0)<0,0,IFERROR(1-F12/F17,0)) -> 1 | G22: =IF(IFERROR(1-G12/G17,0)<0,0,IFERROR(1-G12/G17,0)) -> 0.25 | H22: =IF(IFERROR(1-H12/H17,0)<0,0,IFERROR(1-H12/H17,0)) -> 0.42857143 | I22: =IF(IFERROR(1-I12/I17,0)<0,0,IFERROR(1-I12/I17,0)) -> 1 | J22: =IF(IFERROR(1-J12/J17,0)<0,0,IFERROR(1-J12/J17,0)) -> 0 | K22: =IF(IFERROR(1-K12/K17,0)<0,0,IFERROR(1-K12/K17,0)) -> 0.85714286 | ... CE22: =IF(IFERROR(1-CE12/CE17,0)<0,0,IFERROR(1-CE12/CE17,0)) -> 0.5
B23: <20% | C23: Hospice Desert | D23: =IF(IFERROR(1-D13/D18,0)<0,0,IFERROR(1-D13/D18,0)) -> 0.2 | E23: =IF(IFERROR(1-E13/E18,0)<0,0,IFERROR(1-E13/E18,0)) -> 0 | F23: =IF(IFERROR(1-F13/F18,0)<0,0,IFERROR(1-F13/F18,0)) -> 0 | G23: =IF(IFERROR(1-G13/G18,0)<0,0,IFERROR(1-G13/G18,0)) -> 0.14285714 | H23: =IF(IFERROR(1-H13/H18,0)<0,0,IFERROR(1-H13/H18,0)) -> 0 | I23: =IF(IFERROR(1-I13/I18,0)<0,0,IFERROR(1-I13/I18,0)) -> 0 | J23: =IF(IFERROR(1-J13/J18,0)<0,0,IFERROR(1-J13/J18,0)) -> 0 | K23: =IF(IFERROR(1-K13/K18,0)<0,0,IFERROR(1-K13/K18,0)) -> 0.16666667 | ... CE23: =IF(IFERROR(1-CE13/CE18,0)<0,0,IFERROR(1-CE13/CE18,0)) -> 0.475
A24: Live Discharge | B24: Benchmark
C25: Hospice OC | D25: =D30+D35 -> 0 | E25: =E30+E35 -> 1 | F25: =F30+F35 -> 2 | G25: =G30+G35 -> 0 | H25: =SUM(D25:G25) -> 3 | I25: =I30+I35 -> 1 | J25: =J30+J35 -> 0 | K25: =K30+K35 -> 2 | L25: =L30+L35 -> 2 | M25: =SUM(I25:L25) -> 5 | N25: ='Company Scorecard'!U45 -> 0 | O25: ='Company Scorecard'!V45 -> 0 | P25: ='Company Scorecard'!W45 -> 1 | Q25: ='Company Scorecard'!X45 -> 2 | R25: ='Company Scorecard'!Y45 -> 1 | S25: =SUM(N25:R25) -> 4 | T25: =T30+T35 -> 0 | U25: =U30+U35 -> 5 | V25: =V30+V35 -> 1 | W25: =W30+W35 -> 1 | X25: =SUM(T25:W25) -> 7 | Y25: =Y30+Y35 -> 2 | Z25: =Z30+Z35 -> 0 | AA25: =AA30+AA35 -> 4 | AB25: =AB30+AB35 -> 2 | AC25: =SUM(Y25:AB25) -> 8 | AD25: =AD30+AD35 -> 2 | AE25: =AE30+AE35 -> 1 | AF25: =AF30+AF35 -> 1 | AG25: =AG30+AG35 -> 2 | AH25: =AH30+AH35 -> 1 | AI25: =SUM(AE25:AH25) -> 5 | AJ25: =AJ30+AJ35 -> 0 | AK25: =AK30+AK35 -> 2 | AL25: =AL30+AL35 -> 1 | AM25: =AM30+AM35 -> 0 | AN25: =SUM(AJ25:AM25) -> 3 | AO25: =AO30+AO35 -> 2 | AP25: =AP30+AP35 -> 2 | AQ25: =AQ30+AQ35 -> 2 | AR25: =AR30+AR35 -> 1 | AS25: 9 | AT25: =AT30+AT35 -> 2 | AU25: =AU30+AU35 -> 1 | AV25: =AV30+AV35 -> 1 | AW25: =AW30+AW35 -> 1 | AX25: =AX30+AX35 -> 2 | AY25: =AY30+AY35 -> 6 | AZ25: =AZ30+AZ35 -> 1 | BA25: =BA30+BA35 -> 0 | ... CE25: =CE30+CE35 -> 10
C26: Hospice IE | D26: =D31+D36 -> 0 | E26: =E31+E36 -> 0 | F26: =F31+F36 -> 0 | G26: =G31+G36 -> 0 | H26: =SUM(D26:G26) -> 0 | I26: =I31+I36 -> 0 | J26: =J31+J36 -> 1 | K26: =K31+K36 -> 0 | L26: =L31+L36 -> 0 | M26: =SUM(I26:L26) -> 1 | N26: ='Company Scorecard'!U46 -> 0 | O26: ='Company Scorecard'!V46 -> 1 | P26: ='Company Scorecard'!W46 -> 0 | Q26: ='Company Scorecard'!X46 -> 0 | R26: ='Company Scorecard'!Y46 -> 1 | S26: =SUM(N26:R26) -> 2 | T26: =T31+T36 -> 1 | U26: =U31+U36 -> 0 | V26: =V31+V36 -> 0 | W26: =W31+W36 -> 0 | X26: =SUM(T26:W26) -> 1 | Y26: =Y31+Y36 -> 0 | Z26: =Z31+Z36 -> 1 | AA26: =AA31+AA36 -> 0 | AB26: =AB31+AB36 -> 0 | AC26: =SUM(Y26:AB26) -> 1 | AD26: =AD31+AD36 -> 0 | AE26: =AE31+AE36 -> 0 | AF26: =AF31+AF36 -> 1 | AG26: =AG31+AG36 -> 1 | AH26: =AH31+AH36 -> 1 | AI26: =SUM(AE26:AH26) -> 3 | AJ26: =AJ31+AJ36 -> 0 | AK26: =AK31+AK36 -> 0 | AL26: =AL31+AL36 -> 1 | AM26: =AM31+AM36 -> 1 | AN26: =SUM(AJ26:AM26) -> 2 | AO26: =AO31+AO36 -> 0 | AP26: =AP31+AP36 -> 2 | AQ26: =AQ31+AQ36 -> 0 | AR26: =AR31+AR36 -> 0 | AS26: 2 | AT26: =AT31+AT36 -> 0 | AU26: =AU31+AU36 -> 0 | AV26: =AV31+AV36 -> 1 | AW26: =AW31+AW36 -> 1 | AX26: =AX31+AX36 -> 0 | AY26: =AY31+AY36 -> 2 | AZ26: =AZ31+AZ36 -> 1 | BA26: =BA31+BA36 -> 1 | ... CE26: =CE31+CE36 -> 2
C27: Hospice SGV | D27: =D32+D37 -> 1 | E27: =E32+E37 -> 0 | F27: =F32+F37 -> 0 | G27: =G32+G37 -> 0 | H27: =SUM(D27:G27) -> 1 | I27: =I32+I37 -> 0 | J27: =J32+J37 -> 1 | K27: =K32+K37 -> 1 | L27: =L32+L37 -> 0 | M27: =SUM(I27:L27) -> 2 | N27: ='Company Scorecard'!U47 -> 0 | O27: ='Company Scorecard'!V47 -> 0 | P27: ='Company Scorecard'!W47 -> 0 | Q27: ='Company Scorecard'!X47 -> 0 | R27: ='Company Scorecard'!Y47 -> 0 | S27: =SUM(N27:R27) -> 0 | T27: =T32+T37 -> 0 | U27: =U32+U37 -> 0 | V27: =V32+V37 -> 0 | W27: =W32+W37 -> 0 | X27: =SUM(T27:W27) -> 0 | Y27: =Y32+Y37 -> 0 | Z27: =Z32+Z37 -> 0 | AA27: =AA32+AA37 -> 0 | AB27: =AB32+AB37 -> 1 | AC27: =SUM(Y27:AB27) -> 1 | AD27: =AD32+AD37 -> 0 | AE27: =AE32+AE37 -> 0 | AF27: =AF32+AF37 -> 0 | AG27: =AG32+AG37 -> 0 | AH27: =AH32+AH37 -> 0 | AI27: =SUM(AE27:AH27) -> 0 | AJ27: =AJ32+AJ37 -> 0 | AK27: =AK32+AK37 -> 1 | AL27: =AL32+AL37 -> 2 | AM27: =AM32+AM37 -> 0 | AN27: =SUM(AJ27:AM27) -> 3 | AO27: =AO32+AO37 -> 0 | AP27: =AP32+AP37 -> 0 | AQ27: =AQ32+AQ37 -> 1 | AR27: =AR32+AR37 -> 0 | AS27: 2 | AT27: =AT32+AT37 -> 2 | AU27: =AU32+AU37 -> 2 | AV27: =AV32+AV37 -> 0 | AW27: =AW32+AW37 -> 0 | AX27: =AX32+AX37 -> 1 | AY27: =AY32+AY37 -> 4 | AZ27: =AZ32+AZ37 -> 0 | BA27: =BA32+BA37 -> 0 | ... CE27: =CE32+CE37 -> 0
C28: Hospice Desert | D28: =D33+D38 -> 0 | E28: =E33+E38 -> 1 | F28: =F33+F38 -> 3 | G28: =G33+G38 -> 0 | H28: =SUM(D28:G28) -> 4 | I28: =I33+I38 -> 0 | J28: =J33+J38 -> 1 | K28: =K33+K38 -> 0 | L28: =L33+L38 -> 2 | M28: =SUM(I28:L28) -> 3 | N28: ='Company Scorecard'!U48 -> 2 | O28: ='Company Scorecard'!V48 -> 0 | P28: ='Company Scorecard'!W48 -> 3 | Q28: ='Company Scorecard'!X48 -> 0 | R28: ='Company Scorecard'!Y48 -> 3 | S28: =SUM(N28:R28) -> 8 | T28: =T33+T38 -> 0 | U28: =U33+U38 -> 0 | V28: =V33+V38 -> 1 | W28: =W33+W38 -> 1 | X28: =SUM(T28:W28) -> 2 | Y28: =Y33+Y38 -> 1 | Z28: =Z33+Z38 -> 0 | AA28: =AA33+AA38 -> 2 | AB28: =AB33+AB38 -> 0 | AC28: =SUM(Y28:AB28) -> 3 | AD28: =AD33+AD38 -> 2 | AE28: =AE33+AE38 -> 1 | AF28: =AF33+AF38 -> 0 | AG28: =AG33+AG38 -> 0 | AH28: =AH33+AH38 -> 1 | AI28: =SUM(AE28:AH28) -> 2 | AJ28: =AJ33+AJ38 -> 2 | AK28: =AK33+AK38 -> 0 | AL28: =AL33+AL38 -> 3 | AM28: =AM33+AM38 -> 3 | AN28: =SUM(AJ28:AM28) -> 8 | AO28: =AO33+AO38 -> 5 | AP28: =AP33+AP38 -> 1 | AQ28: =AQ33+AQ38 -> 3 | AR28: =AR33+AR38 -> 2 | AS28: 9 | AT28: =AT33+AT38 -> 1 | AU28: =AU33+AU38 -> 0 | AV28: =AV33+AV38 -> 0 | AW28: =AW33+AW38 -> 0 | AX28: =AX33+AX38 -> 2 | AY28: =AY33+AY38 -> 2 | AZ28: =AZ33+AZ38 -> 1 | BA28: =BA33+BA38 -> 5 | ... CE28: =CE33+CE38 -> 7
A29: Live Discharge - Patient Initiated (Revocation/Tsf to Other Hospice) | B29: Benchmark
C30: Hospice OC | D30: 0 | E30: 1 | F30: 0 | G30: 0 | H30: =SUM(D30:G30) -> 1 | I30: 0 | J30: 0 | K30: 2 | L30: 0 | M30: =SUM(I30:L30) -> 2 | N30: 0 | O30: 0 | P30: 0 | Q30: 0 | R30: 0 | S30: =SUM(N30:R30) -> 0 | T30: 0 | U30: 2 | V30: 1 | W30: 0 | X30: =SUM(T30:W30) -> 3 | Y30: 0 | Z30: 0 | AA30: 1 | AB30: 1 | AC30: =SUM(Y30:AB30) -> 2 | AD30: 1 | AE30: 0 | AF30: 0 | AG30: 0 | AH30: 0 | AI30: =SUM(AD30:AH30) -> 1 | AJ30: 0 | AK30: 1 | AL30: 0 | AM30: 0 | AN30: =SUM(AI30:AM30) -> 2 | AO30: 0 | AP30: 2 | AQ30: 0 | AR30: 1 | AS30: 5 | AT30: 1 | AU30: 0 | AV30: 0 | AW30: 1 | AX30: 1 | AY30: 2 | AZ30: 0 | BA30: 0 | BB30: 0 | BC30: 0 | BD30: 3 | BE30: 1 | BF30: 0 | BG30: 0 | BH30: 0 | BI30: 0 | BJ30: 2 | BK30: 0 | BL30: 1 | BM30: 0 | BN30: 0 | BO30: 2 | BP30: 0 | BQ30: 0 | BR30: 0 | BS30: 2 | BT30: 4 | BU30: 1 | BV30: 1 | BW30: 0 | BX30: 1 | BY30: 5 | BZ30: 0 | CA30: 0 | CB30: 0 | CC30: 0 | CD30: 1 | CE30: 5
C31: Hospice IE | D31: 0 | E31: 0 | F31: 0 | G31: 0 | H31: =SUM(D31:G31) -> 0 | I31: 0 | J31: 0 | K31: 0 | L31: 0 | M31: =SUM(I31:L31) -> 0 | N31: 0 | O31: 1 | P31: 0 | Q31: 0 | R31: 0 | S31: =SUM(N31:R31) -> 1 | T31: 1 | U31: 0 | V31: 0 | W31: 0 | X31: =SUM(T31:W31) -> 1 | Y31: 0 | Z31: 1 | AA31: 0 | AB31: 0 | AC31: =SUM(Y31:AB31) -> 1 | AD31: 0 | AE31: 0 | AF31: 0 | AG31: 0 | AH31: 0 | AI31: =SUM(AD31:AH31) -> 0 | AJ31: 0 | AK31: 0 | AL31: 0 | AM31: 0 | AN31: =SUM(AI31:AM31) -> 0 | AO31: 0 | AP31: 1 | AQ31: 0 | AR31: 0 | AS31: 0 | AT31: 0 | AU31: 0 | AV31: 1 | AW31: 1 | AX31: 0 | AY31: 2 | AZ31: 0 | BA31: 0 | BB31: 0 | BC31: 0 | BD31: 0 | BE31: 0 | BF31: 0 | BG31: 0 | BH31: 0 | BI31: 0 | BJ31: 0 | BK31: 0 | BL31: 0 | BM31: 1 | BN31: 0 | BO31: 1 | BP31: 0 | BQ31: 0 | BR31: 0 | BS31: 0 | BT31: 0 | BU31: 0 | BV31: 0 | BW31: 0 | BX31: 0 | BY31: 0 | BZ31: 0 | CA31: 0 | CB31: 0 | CC31: 0 | CD31: 0 | CE31: 0
C32: Hospice SGV | D32: 1 | E32: 0 | F32: 0 | G32: 0 | H32: =SUM(D32:G32) -> 1 | I32: 0 | J32: 1 | K32: 1 | L32: 0 | M32: =SUM(I32:L32) -> 2 | N32: 0 | O32: 0 | P32: 0 | Q32: 0 | R32: 0 | S32: =SUM(N32:R32) -> 0 | T32: 0 | U32: 0 | V32: 0 | W32: 0 | X32: =SUM(T32:W32) -> 0 | Y32: 0 | Z32: 0 | AA32: 0 | AB32: 0 | AC32: =SUM(Y32:AB32) -> 0 | AD32: 0 | AE32: 0 | AF32: 0 | AG32: 0 | AH32: 0 | AI32: =SUM(AD32:AH32) -> 0 | AJ32: 0 | AK32: 0 | AL32: 0 | AM32: 0 | AN32: =SUM(AI32:AM32) -> 0 | AO32: 0 | AP32: 0 | AQ32: 0 | AR32: 0 | AS32: 1 | AT32: 1 | AU32: 0 | AV32: 0 | AW32: 0 | AX32: 0 | AY32: 0 | AZ32: 0 | BA32: 0 | BB32: 0 | BC32: 0 | BD32: 0 | BE32: 0 | BF32: 0 | BG32: 0 | BH32: 0 | BI32: 0 | BJ32: 0 | BK32: 0 | BL32: 0 | BM32: 0 | BN32: 0 | BO32: 0 | BP32: 0 | BQ32: 0 | BR32: 0 | BS32: 0 | BT32: 0 | BU32: 0 | BV32: 0 | BW32: 0 | BX32: 0 | BY32: 0 | BZ32: 0 | CA32: 0 | CB32: 0 | CC32: 0 | CD32: 0 | CE32: 0
C33: Hospice Desert | D33: 0 | E33: 1 | F33: 3 | G33: 0 | H33: =SUM(D33:G33) -> 4 | I33: 0 | J33: 0 | K33: 0 | L33: 2 | M33: =SUM(I33:L33) -> 2 | N33: 0 | O33: 0 | P33: 2 | Q33: 0 | R33: 0 | S33: =SUM(N33:R33) -> 2 | T33: 0 | U33: 0 | V33: 0 | W33: 0 | X33: =SUM(T33:W33) -> 0 | Y33: 0 | Z33: 0 | AA33: 0 | AB33: 0 | AC33: =SUM(Y33:AB33) -> 0 | AD33: 1 | AE33: 1 | AF33: 0 | AG33: 0 | AH33: 1 | AI33: =SUM(AD33:AH33) -> 3 | AJ33: 1 | AK33: 0 | AL33: 2 | AM33: 0 | AN33: =SUM(AI33:AM33) -> 6 | AO33: 1 | AP33: 0 | AQ33: 2 | AR33: 2 | AS33: 5 | AT33: 1 | AU33: 0 | AV33: 0 | AW33: 0 | AX33: 0 | AY33: 0 | AZ33: 0 | BA33: 1 | BB33: 0 | BC33: 1 | BD33: 3 | BE33: 0 | BF33: 0 | BG33: 0 | BH33: 0 | BI33: 0 | BJ33: 1 | BK33: 0 | BL33: 0 | BM33: 0 | BN33: 0 | BO33: 0 | BP33: 0 | BQ33: 0 | BR33: 0 | BS33: 0 | BT33: 0 | BU33: 0 | BV33: 2 | BW33: 1 | BX33: 0 | BY33: 3 | BZ33: 0 | CA33: 3 | CB33: 1 | CC33: 1 | CD33: 0 | CE33: 3
A34: Live Discharge - Hospice Initiated (Prognosis/DC for cause/Out of Area) | B34: Benchmark
B35: 4% or < per month | C35: Hospice OC | D35: 0 | E35: 0 | F35: 2 | G35: 0 | H35: =SUM(D35:G35) -> 2 | I35: 1 | J35: 0 | K35: 0 | L35: 2 | M35: =SUM(I35:L35) -> 3 | N35: 0 | O35: 0 | P35: 1 | Q35: 1 | R35: 1 | S35: =SUM(N35:R35) -> 3 | T35: 0 | U35: 3 | V35: 0 | W35: 1 | X35: =SUM(T35:W35) -> 4 | Y35: 2 | Z35: 0 | AA35: 3 | AB35: 1 | AC35: =SUM(Y35:AB35) -> 6 | AD35: 1 | AE35: 1 | AF35: 1 | AG35: 2 | AH35: 1 | AI35: =SUM(AD35:AH35) -> 6 | AJ35: 0 | AK35: 1 | AL35: 1 | AM35: 0 | AN35: =SUM(AI35:AM35) -> 8 | AO35: 2 | AP35: 0 | AQ35: 2 | AR35: 0 | AS35: 4 | AT35: 1 | AU35: 1 | AV35: 1 | AW35: 0 | AX35: 1 | AY35: 4 | AZ35: 1 | BA35: 0 | BB35: 3 | BC35: 0 | BD35: 2 | BE35: 0 | BF35: 2 | BG35: 1 | BH35: 1 | BI35: 1 | BJ35: 5 | BK35: 0 | BL35: 0 | BM35: 0 | BN35: 0 | BO35: 1 | BP35: 3 | BQ35: 2 | BR35: 1 | BS35: 2 | BT35: 7 | BU35: 1 | BV35: 2 | BW35: 0 | BX35: 0 | BY35: 5 | BZ35: 0 | CA35: 0 | CB35: 0 | CC35: 0 | CD35: 0 | CE35: 5
B36: 4% or < per month | C36: Hospice IE | D36: 0 | E36: 0 | F36: 0 | G36: 0 | H36: =SUM(D36:G36) -> 0 | I36: 0 | J36: 1 | K36: 0 | L36: 0 | M36: =SUM(I36:L36) -> 1 | N36: 0 | O36: 0 | P36: 0 | Q36: 0 | R36: 0 | S36: =SUM(N36:R36) -> 0 | T36: 0 | U36: 0 | V36: 0 | W36: 0 | X36: =SUM(T36:W36) -> 0 | Y36: 0 | Z36: 0 | AA36: 0 | AB36: 0 | AC36: =SUM(Y36:AB36) -> 0 | AD36: 0 | AE36: 0 | AF36: 1 | AG36: 1 | AH36: 1 | AI36: =SUM(AD36:AH36) -> 3 | AJ36: 0 | AK36: 0 | AL36: 1 | AM36: 1 | AN36: =SUM(AI36:AM36) -> 5 | AO36: 0 | AP36: 1 | AQ36: 0 | AR36: 0 | AS36: 2 | AT36: 0 | AU36: 0 | AV36: 0 | AW36: 0 | AX36: 0 | AY36: 0 | AZ36: 1 | BA36: 1 | BB36: 0 | BC36: 0 | BD36: 2 | BE36: 0 | BF36: 0 | BG36: 1 | BH36: 0 | BI36: 1 | BJ36: 1 | BK36: 0 | BL36: 1 | BM36: 0 | BN36: 0 | BO36: 2 | BP36: 0 | BQ36: 1 | BR36: 0 | BS36: 0 | BT36: 1 | BU36: 1 | BV36: 0 | BW36: 0 | BX36: 0 | BY36: 2 | BZ36: 0 | CA36: 0 | CB36: 0 | CC36: 1 | CD36: 3 | CE36: 2
B37: 4% or < per month | C37: Hospice SGV | D37: 0 | E37: 0 | F37: 0 | G37: 0 | H37: =SUM(D37:G37) -> 0 | I37: 0 | J37: 0 | K37: 0 | L37: 0 | M37: =SUM(I37:L37) -> 0 | N37: 0 | O37: 0 | P37: 0 | Q37: 0 | R37: 0 | S37: =SUM(N37:R37) -> 0 | T37: 0 | U37: 0 | V37: 0 | W37: 0 | X37: =SUM(T37:W37) -> 0 | Y37: 0 | Z37: 0 | AA37: 0 | AB37: 1 | AC37: =SUM(Y37:AB37) -> 1 | AD37: 0 | AE37: 0 | AF37: 0 | AG37: 0 | AH37: 0 | AI37: =SUM(AD37:AH37) -> 0 | AJ37: 0 | AK37: 1 | AL37: 2 | AM37: 0 | AN37: =SUM(AI37:AM37) -> 3 | AO37: 0 | AP37: 0 | AQ37: 1 | AR37: 0 | AS37: 1 | AT37: 1 | AU37: 2 | AV37: 0 | AW37: 0 | AX37: 1 | AY37: 4 | AZ37: 0 | BA37: 0 | BB37: 0 | BC37: 0 | BD37: 0 | BE37: 0 | BF37: 0 | BG37: 0 | BH37: 0 | BI37: 0 | BJ37: 0 | BK37: 0 | BL37: 0 | BM37: 0 | BN37: 0 | BO37: 0 | BP37: 3 | BQ37: 0 | BR37: 0 | BS37: 0 | BT37: 3 | BU37: 0 | BV37: 0 | BW37: 0 | BX37: 0 | BY37: 0 | BZ37: 0 | CA37: 1 | CB37: 0 | CC37: 0 | CD37: 0 | CE37: 0
B38: 4% or < per month | C38: Hospice Desert | D38: 0 | E38: 0 | F38: 0 | G38: 0 | H38: =SUM(D38:G38) -> 0 | I38: 0 | J38: 1 | K38: 0 | L38: 0 | M38: =SUM(I38:L38) -> 1 | N38: 2 | O38: 0 | P38: 1 | Q38: 0 | R38: 0 | S38: =SUM(N38:R38) -> 3 | T38: 0 | U38: 0 | V38: 1 | W38: 1 | X38: =SUM(T38:W38) -> 2 | Y38: 1 | Z38: 0 | AA38: 2 | AB38: 0 | AC38: =SUM(Y38:AB38) -> 3 | AD38: 1 | AE38: 0 | AF38: 0 | AG38: 0 | AH38: 0 | AI38: =SUM(AD38:AH38) -> 1 | AJ38: 1 | AK38: 0 | AL38: 1 | AM38: 3 | AN38: =SUM(AI38:AM38) -> 6 | AO38: 4 | AP38: 1 | AQ38: 1 | AR38: 0 | AS38: 4 | AT38: 0 | AU38: 0 | AV38: 0 | AW38: 0 | AX38: 2 | AY38: 2 | AZ38: 1 | BA38: 4 | BB38: 0 | BC38: 1 | BD38: 5 | BE38: 2 | BF38: 1 | BG38: 1 | BH38: 1 | BI38: 0 | BJ38: 4 | BK38: 2 | BL38: 1 | BM38: 2 | BN38: 2 | BO38: 7 | BP38: 1 | BQ38: 0 | BR38: 3 | BS38: 0 | BT38: 4 | BU38: 2 | BV38: 0 | BW38: 1 | BX38: 0 | BY38: 4 | BZ38: 0 | CA38: 0 | CB38: 0 | CC38: 1 | CD38: 1 | CE38: 4
A39: Total Patient Days | B39: Benchmark
C40: Hospice OC | D40: ='Company Scorecard'!K50 -> 546 | E40: ='Company Scorecard'!L50 -> 560 | F40: ='Company Scorecard'!M50 -> 567 | G40: ='Company Scorecard'!N50 -> 574 | H40: ='Company Scorecard'!O50 -> 2214 | I40: ='Company Scorecard'!P50 -> 574 | J40: ='Company Scorecard'!Q50 -> 602 | K40: ='Company Scorecard'!R50 -> 616 | ... AE40: ='Company Scorecard'!AL50 -> 658 | AI40: ='Company Scorecard'!AP50 -> 3077 | AN40: ='Company Scorecard'!AU50 -> 3164 | AS40: ='Company Scorecard'!AZ50 -> 3260 | AY40: ='Company Scorecard'!BF50 -> 3414 | BD40: ='Company Scorecard'!BK50 -> 3295 | BJ40: ='Company Scorecard'!BQ50 -> 3555 | BO40: ='Company Scorecard'!BV50 -> 3578 | BT40: ='Company Scorecard'!CA50 -> 3359 | BY40: ='Company Scorecard'!CF50 -> 3881 | CE40: ='Company Scorecard'!CL50 -> 3697
C41: Hospice IE | D41: ='Company Scorecard'!K51 -> 252 | E41: ='Company Scorecard'!L51 -> 252 | F41: ='Company Scorecard'!M51 -> 266 | G41: ='Company Scorecard'!N51 -> 256.2 | H41: ='Company Scorecard'!O51 -> 1054 | I41: ='Company Scorecard'!P51 -> 253.4 | J41: ='Company Scorecard'!Q51 -> 238 | K41: ='Company Scorecard'!R51 -> 238 | ... AE41: ='Company Scorecard'!AL51 -> 273 | AI41: ='Company Scorecard'!AP51 -> 1236 | AN41: ='Company Scorecard'!AU51 -> 1395 | AS41: ='Company Scorecard'!AZ51 -> 1399 | AY41: ='Company Scorecard'!BF51 -> 1387 | BD41: ='Company Scorecard'!BK51 -> 1312 | BJ41: ='Company Scorecard'!BQ51 -> 1340 | BO41: ='Company Scorecard'!BV51 -> 1240 | BT41: ='Company Scorecard'!CA51 -> 1157 | BY41: ='Company Scorecard'!CF51 -> 1393 | CE41: ='Company Scorecard'!CL51 -> 1443
C42: Hospice SGV | D42: ='Company Scorecard'!K52 -> 171.5 | E42: ='Company Scorecard'!L52 -> 175 | F42: ='Company Scorecard'!M52 -> 168 | G42: ='Company Scorecard'!N52 -> 182 | H42: ='Company Scorecard'!O52 -> 680 | I42: ='Company Scorecard'!P52 -> 166.6 | J42: ='Company Scorecard'!Q52 -> 175 | K42: ='Company Scorecard'!R52 -> 182 | ... AE42: ='Company Scorecard'!AL52 -> 231 | AI42: ='Company Scorecard'!AP52 -> 1162 | AN42: ='Company Scorecard'!AU52 -> 1149 | AS42: ='Company Scorecard'!AZ52 -> 927 | AY42: ='Company Scorecard'!BF52 -> 773 | BD42: ='Company Scorecard'!BK52 -> 707 | BJ42: ='Company Scorecard'!BQ52 -> 741 | BO42: ='Company Scorecard'!BV52 -> 756 | BT42: ='Company Scorecard'!CA52 -> 549 | BY42: ='Company Scorecard'!CF52 -> 561 | CE42: ='Company Scorecard'!CL52 -> 566
C43: Hospice Desert | D43: ='Company Scorecard'!K53 -> 525 | E43: ='Company Scorecard'!L53 -> 518 | F43: ='Company Scorecard'!M53 -> 518 | G43: ='Company Scorecard'!N53 -> 518 | H43: ='Company Scorecard'!O53 -> 1990.8 | I43: ='Company Scorecard'!P53 -> 567 | J43: ='Company Scorecard'!Q53 -> 602 | K43: ='Company Scorecard'!R53 -> 588 | ... AE43: ='Company Scorecard'!AL53 -> 672 | AI43: ='Company Scorecard'!AP53 -> 3013 | AN43: ='Company Scorecard'!AU53 -> 3054 | AS43: ='Company Scorecard'!AZ53 -> 2690 | AY43: ='Company Scorecard'!BF53 -> 2834 | BD43: ='Company Scorecard'!BK53 -> 2756 | BJ43: ='Company Scorecard'!BQ53 -> 2915 | BO43: ='Company Scorecard'!BV53 -> 3019 | BT43: ='Company Scorecard'!CA53 -> 2756 | BY43: ='Company Scorecard'!CF53 -> 2873 | CE43: ='Company Scorecard'!CL53 -> 2561
C44: TOTAL | M44: =SUM(M40:M43) -> 7073 | N44: =SUM(N40:N43) -> 1624 | O44: =SUM(O40:O43) -> 1652 | P44: =SUM(P40:P43) -> 1673 | Q44: =SUM(Q40:Q43) -> 1694 | R44: =SUM(R40:R43) -> 1680 | S44: =SUM(S40:S43) -> 7126 | T44: =SUM(T40:T43) -> 1645 | ... BT44: =SUM(BT40:BT43) -> 7821 | BY44: =SUM(BY40:BY43) -> 8708 | CE44: =SUM(CE40:CE43) -> 8267
A45: MEDIAN LOS | B45: Benchmark
A46: Hospice Median LOS Report | B46: 100 days or less | C46: Hospice OC | D46: ='Company Scorecard'!K60 -> 291.62 | E46: ='Company Scorecard'!L60 -> 277.32 | F46: ='Company Scorecard'!M60 -> 265.03 | G46: ='Company Scorecard'!N60 -> 270.69 | I46: ='Company Scorecard'!P60 -> 272.45 | J46: ='Company Scorecard'!Q60 -> 262.95 | K46: ='Company Scorecard'!R60 -> 260.29 | L46: ='Company Scorecard'!S60 -> 247.36 | N46: ='Company Scorecard'!U60 -> 245.25 | O46: ='Company Scorecard'!V60 -> 247.39 | P46: ='Company Scorecard'!W60 -> 242.62 | Q46: ='Company Scorecard'!X60 -> 251.91 | R46: ='Company Scorecard'!Y60 -> 262.32 | T46: ='Company Scorecard'!AA60 -> 248.15 | U46: ='Company Scorecard'!AB60 -> 231.11 | V46: ='Company Scorecard'!AC60 -> 235.23 | W46: ='Company Scorecard'!AD60 -> 238.79 | AY46: 38 | BD46: 20 | BJ46: 17 | BO46: 50 | BT46: 23.5 | BU46: 50.5 | BV46: 12 | BW46: 37 | BX46: 85 | BY46: 37 | BZ46: 0 | CA46: 9 | CB46: 17.5 | CC46: 48 | CD46: 82.5 | CE46: 31
B47: 100 days or less | C47: Hospice IE | D47: ='Company Scorecard'!K61 -> 264.14 | E47: ='Company Scorecard'!L61 -> 270.89 | F47: ='Company Scorecard'!M61 -> 270.68 | G47: ='Company Scorecard'!N61 -> 284.54 | I47: ='Company Scorecard'!P61 -> 298.36 | J47: ='Company Scorecard'!Q61 -> 295.84 | K47: ='Company Scorecard'!R61 -> 305.71 | L47: ='Company Scorecard'!S61 -> 295.14 | N47: ='Company Scorecard'!U61 -> 318.27 | O47: ='Company Scorecard'!V61 -> 311.18 | P47: ='Company Scorecard'!W61 -> 322.24 | Q47: ='Company Scorecard'!X61 -> 329 | R47: ='Company Scorecard'!Y61 -> 326.09 | T47: ='Company Scorecard'!AA61 -> 351.75 | U47: ='Company Scorecard'!AB61 -> 344.52 | V47: ='Company Scorecard'!AC61 -> 329.71 | W47: ='Company Scorecard'!AD61 -> 336.71 | AY47: 10 | BD47: 35 | BJ47: 12.5 | BO47: 43 | BT47: 105 | BU47: 6 | BV47: 0 | BW47: 22 | BX47: 4 | BY47: 5.5 | BZ47: 0 | CA47: 59 | CB47: 62 | CC47: 470.5 | CD47: 64 | CE47: 64
B48: 100 days or less | C48: Hospice SGV | D48: ='Company Scorecard'!K62 -> 174.74 | E48: ='Company Scorecard'!L62 -> 184.52 | F48: ='Company Scorecard'!M62 -> 180.24 | G48: ='Company Scorecard'!N62 -> 179.27 | I48: ='Company Scorecard'!P62 -> 200.04 | J48: ='Company Scorecard'!Q62 -> 182.65 | K48: ='Company Scorecard'!R62 -> 188.85 | L48: ='Company Scorecard'!S62 -> 181.75 | N48: ='Company Scorecard'!U62 -> 175.73 | O48: ='Company Scorecard'!V62 -> 174.35 | P48: ='Company Scorecard'!W62 -> 191.48 | Q48: ='Company Scorecard'!X62 -> 200.61 | R48: ='Company Scorecard'!Y62 -> 214.37 | T48: ='Company Scorecard'!AA62 -> 221.37 | U48: ='Company Scorecard'!AB62 -> 205.9 | V48: ='Company Scorecard'!AC62 -> 199.72 | W48: ='Company Scorecard'!AD62 -> 213.1 | AY48: 26 | BD48: 51 | BJ48: 203.5 | BO48: 164.5 | BT48: 77 | BU48: 0 | BV48: 0 | BW48: 0 | BX48: 9 | BY48: 135.5 | BZ48: 262 | CA48: 6 | CB48: 0 | CC48: 0 | CD48: 31 | CE48: 18.5
B49: 100 days or less | C49: Hospice Desert | D49: ='Company Scorecard'!K63 -> 73.01 | E49: ='Company Scorecard'!L63 -> 75.76 | F49: ='Company Scorecard'!M63 -> 76.84 | G49: ='Company Scorecard'!N63 -> 84.5 | I49: ='Company Scorecard'!P63 -> 83.22 | J49: ='Company Scorecard'!Q63 -> 81.1 | K49: ='Company Scorecard'!R63 -> 89.18 | L49: ='Company Scorecard'!S63 -> 92.43 | N49: ='Company Scorecard'!U63 -> 86.58 | O49: ='Company Scorecard'!V63 -> 90.64 | P49: ='Company Scorecard'!W63 -> 88.77 | Q49: ='Company Scorecard'!X63 -> 95.2 | R49: ='Company Scorecard'!Y63 -> 95.71 | T49: ='Company Scorecard'!AA63 -> 101.97 | U49: ='Company Scorecard'!AB63 -> 106.2 | V49: ='Company Scorecard'!AC63 -> 103.51 | W49: ='Company Scorecard'!AD63 -> 107.44 | AY49: 11 | BD49: 16.5 | BJ49: 31 | BO49: 22 | BT49: 17 | BU49: 37 | BV49: 69.5 | BW49: 37 | BX49: 4 | BY49: 34 | BZ49: 129 | CA49: 14 | CB49: 27 | CC49: 30.5 | CD49: 22.5 | CE49: 30.5
A50: % of Workers Achieving expected Points | B50: Benchmark
C51: Hospice OC | D51: ='Company Scorecard'!K69 -> 1 | E51: ='Company Scorecard'!L69 -> 0.91666667 | F51: ='Company Scorecard'!M69 -> 0.91666667 | G51: ='Company Scorecard'!N69 -> 0.91666667 | I51: ='Company Scorecard'!P69 -> 0 | J51: ='Company Scorecard'!Q69 -> 0 | K51: ='Company Scorecard'!R69 -> 0 | L51: ='Company Scorecard'!S69 -> 0 | N51: ='Company Scorecard'!U69 -> 0 | O51: ='Company Scorecard'!V69 -> 0 | P51: ='Company Scorecard'!W69 -> 0 | Q51: ='Company Scorecard'!X69 -> 0 | R51: ='Company Scorecard'!Y69 -> 0 | T51: ='Company Scorecard'!AA69 -> 0 | U51: ='Company Scorecard'!AB69 -> 0 | V51: ='Company Scorecard'!AC69 -> 0 | W51: ='Company Scorecard'!AD69 -> 0 | Y51: ='Company Scorecard'!AF69 -> 0 | Z51: ='Company Scorecard'!AG69 -> 0 | AA51: ='Company Scorecard'!AH69 -> 0 | AD51: ='Company Scorecard'!AK69 -> 0 | AE51: ='Company Scorecard'!AL69 -> 0
C52: Hospice IE | D52: ='Company Scorecard'!K70 -> 1 | E52: ='Company Scorecard'!L70 -> 1 | F52: ='Company Scorecard'!M70 -> 1 | G52: ='Company Scorecard'!N70 -> 1 | I52: ='Company Scorecard'!P70 -> 0 | J52: ='Company Scorecard'!Q70 -> 0 | K52: ='Company Scorecard'!R70 -> 0 | L52: ='Company Scorecard'!S70 -> 0 | N52: ='Company Scorecard'!U70 -> 0 | O52: ='Company Scorecard'!V70 -> 0 | P52: ='Company Scorecard'!W70 -> 0 | Q52: ='Company Scorecard'!X70 -> 0 | R52: ='Company Scorecard'!Y70 -> 0 | T52: ='Company Scorecard'!AA70 -> 0 | U52: ='Company Scorecard'!AB70 -> 0 | V52: ='Company Scorecard'!AC70 -> 0 | W52: ='Company Scorecard'!AD70 -> 0 | Y52: ='Company Scorecard'!AF70 -> 0 | Z52: ='Company Scorecard'!AG70 -> 0 | AA52: ='Company Scorecard'!AH70 -> 0 | AD52: ='Company Scorecard'!AK70 -> 0 | AE52: ='Company Scorecard'!AL70 -> 0
C53: Hospice SGV | D53: ='Company Scorecard'!K71 -> 1 | E53: ='Company Scorecard'!L71 -> 0.83333333 | F53: ='Company Scorecard'!M71 -> 1 | G53: ='Company Scorecard'!N71 -> 1 | I53: ='Company Scorecard'!P71 -> 0 | J53: ='Company Scorecard'!Q71 -> 0 | K53: ='Company Scorecard'!R71 -> 0 | L53: ='Company Scorecard'!S71 -> 0 | N53: ='Company Scorecard'!U71 -> 0 | O53: ='Company Scorecard'!V71 -> 0 | P53: ='Company Scorecard'!W71 -> 0 | Q53: ='Company Scorecard'!X71 -> 0 | R53: ='Company Scorecard'!Y71 -> 0 | T53: ='Company Scorecard'!AA71 -> 0 | U53: ='Company Scorecard'!AB71 -> 0 | V53: ='Company Scorecard'!AC71 -> 0 | W53: ='Company Scorecard'!AD71 -> 0 | Y53: ='Company Scorecard'!AF71 -> 0 | Z53: ='Company Scorecard'!AG71 -> 0 | AA53: ='Company Scorecard'!AH71 -> 0 | AD53: ='Company Scorecard'!AK71 -> 0 | AE53: ='Company Scorecard'!AL71 -> 0
C54: Hospice Desert | D54: ='Company Scorecard'!K72 -> 1 | E54: ='Company Scorecard'!L72 -> 1 | F54: ='Company Scorecard'!M72 -> 1 | G54: ='Company Scorecard'!N72 -> 1 | I54: ='Company Scorecard'!P72 -> 0 | J54: ='Company Scorecard'!Q72 -> 0 | K54: ='Company Scorecard'!R72 -> 0 | L54: ='Company Scorecard'!S72 -> 0 | N54: ='Company Scorecard'!U72 -> 0 | O54: ='Company Scorecard'!V72 -> 0 | P54: ='Company Scorecard'!W72 -> 0 | Q54: ='Company Scorecard'!X72 -> 0 | R54: ='Company Scorecard'!Y72 -> 0 | T54: ='Company Scorecard'!AA72 -> 0 | U54: ='Company Scorecard'!AB72 -> 0 | V54: ='Company Scorecard'!AC72 -> 0 | W54: ='Company Scorecard'!AD72 -> 0 | Y54: ='Company Scorecard'!AF72 -> 0 | Z54: ='Company Scorecard'!AG72 -> 0 | AA54: ='Company Scorecard'!AH72 -> 0 | AD54: ='Company Scorecard'!AK72 -> 0 | AE54: ='Company Scorecard'!AL72 -> 0
A55: OT (< 3% Total payroll) | B55: Benchmark
C56: Hospice OC | D56: 4.83 | E56: 3.64 | F56: 1.43 | G56: 4.12 | I56: 0.015 | J56: 0.01 | K56: 0.014 | L56: 0.026 | N56: 0.006 | O56: 0.049 | P56: 0.037 | Q56: 0.003 | R56: 0.011 | T56: 0.014 | U56: 0.025 | V56: 0.017 | W56: 0.025 | Y56: 0.004 | Z56: 0.019 | AA56: 0.037 | AB56: 0.035 | AD56: 0.042 | AE56: 0.014 | AF56: 0.006 | AG56: 0.021 | AH56: 0.024 | AJ56: 0.026 | AK56: 0.072 | AL56: 0.037 | AM56: 0.03 | AO56: 0.024 | AP56: 0.034 | AQ56: 0.026 | AR56: 0.023 | AT56: 0.013 | AU56: 0.024 | AV56: 0.034 | AW56: 0.01 | AX56: 0.018 | AZ56: 0.025 | BA56: 0.024 | BB56: 0.022 | BC56: 0.067 | BE56: 0.036 | BF56: 0.018 | BG56: 0.038 | BH56: 0.04 | BI56: 0.073 | BO56: 0.049 | BT56: 0.032 | BY56: 0.036
C57: Hospice IE | D57: 17.22 | E57: 9.69 | F57: 22.05 | G57: 16.82 | I57: 0.057 | J57: 0.033 | K57: 0.044 | L57: 0.017 | N57: 0.035 | O57: 0.034 | P57: 0.051 | Q57: 0.045 | R57: 0.066 | T57: 0.034 | U57: 0.042 | V57: 0.07 | W57: 0.107 | Y57: 0.042 | Z57: 0.068 | AA57: 0.067 | AB57: 0.095 | AD57: 0.085 | AE57: 0.077 | AF57: 0.064 | AG57: 0.083 | AH57: 0.053 | AJ57: 0.07 | AK57: 0.064 | AL57: 0.077 | AM57: 0.081 | AO57: 0.073 | AP57: 0.068 | AQ57: 0.054 | AR57: 0.067 | AT57: 0.052 | AU57: 0.056 | AV57: 0.064 | AW57: 0.067 | AX57: 0.065 | AZ57: 0.103 | BA57: 0.046 | BB57: 0.068 | BC57: 0.09 | BE57: 0.045 | BF57: 0.057 | BG57: 0.104 | BH57: 0.185 | BI57: 0.13 | BO57: 0.107 | BT57: 0.064 | BY57: 0.063
C58: Hospice SGV | D58: 20.92 | E58: 3.88 | F58: 6.45 | G58: 3.62 | I58: 0.014 | J58: 0.02 | K58: 0.027 | L58: 0.089 | N58: 0.039 | O58: 0.07 | P58: 0.038 | Q58: 0.023 | R58: 0.023 | T58: 0.093 | U58: 0.105 | V58: 0.047 | W58: 0.025 | Y58: 0.029 | Z58: 0.073 | AA58: 0.074 | AB58: 0.051 | AD58: 0.174 | AE58: 0.05 | AF58: 0.068 | AG58: 0.063 | AH58: 0.034 | AJ58: 0.023 | AK58: 0.071 | AL58: 0.039 | AM58: 0.043 | AO58: 0.103 | AP58: 0.023 | AQ58: 0.021 | AR58: 0.04 | AT58: 0.051 | AU58: 0.02 | AV58: 0.059 | AW58: 0.032 | AX58: 0.047 | AZ58: 0.034 | BA58: 0.022 | BB58: 0.106 | BC58: 0.173 | BE58: 0.071 | BF58: 0.024 | BG58: 0.025 | BH58: 0.102 | BI58: 0.17 | BO58: 0.077 | BT58: 0.039 | BY58: 0.023
C59: Hospice Desert/Living Stones | D59: 20.28 | E59: 46.13 | F59: =25.4+1.77 -> 27.17 | G59: 24.15 | I59: 0.099 | J59: 0.093 | K59: 0.068 | L59: 0.077 | N59: 0.058 | O59: 0.057 | P59: 0.057 | Q59: 0.084 | R59: 0.073 | T59: 0.067 | U59: 0.036 | V59: 0.076 | W59: 0.102 | Y59: 0.091 | Z59: 0.09 | AA59: 0.042 | AB59: 0.058 | AD59: 0.107 | AE59: 0.072 | AF59: 0.063 | AG59: 0.06 | AH59: 0.087 | AJ59: 0.093 | AK59: 0.066 | AL59: 0.04 | AM59: 0.048 | AO59: 0.076 | AP59: 0.041 | AQ59: 0.055 | AR59: 0.063 | AT59: 0.082 | AU59: 0.049 | AV59: 0.09 | AW59: 0.063 | AX59: 0.083 | AZ59: 0.053 | BA59: 0.045 | BB59: 0.038 | BC59: 0.106 | BE59: 0.056 | BF59: 0.073 | BG59: 0.06 | BH59: 0.152 | BI59: 0.195 | BO59: 0.095 | BT59: 0.056 | BY59: 0.068
A60: Average hours to admit from referral | B60: Benchmark
A61: HCHB Analytics - Population Report Card - Monthly | C61: Hospice OC | Y61: 0.4 | Z61: 0.3 | AA61: 0.25 | AB61: 0.33 | AD61: 0.375 | AE61: 0.25 | BO61: 4 Hrs | BT61: 5 Hrs | BY61: 7 Hrs | CE61: 6 Hrs
C62: Hospice IE | Y62: 0.75 | Z62: 2.3 | AA62: 2 | AB62: 0 | AD62: 0.5 | AE62: 1.5 | BO62: 10 Hrs | BT62: 22 Hrs | BY62: 5 Hrs | CE62: 21 Hrs
C63: Hospice SGV | Y63: 1 | Z63: 2 | AA63: 2 | AB63: 1 | AD63: N/A | AE63: 2.3 | BO63: 20 Hrs | BT63: 15 Hrs | BY63: 8 Hrs | CE63: 10 Hrs
C64: Hospice Desert | Y64: 1 | Z64: 1.5 | AA64: 2.25 | AB64: 1.33 | AD64: 4.25 | AE64: 1 | BO64: 8 Hrs | BT64: 14 Hrs | BY64: 19 Hrs | CE64: 56 Hrs
A65: Contribution Margin | B65: Benchmark
B66: Enter in target | C66: Hospice OC | AS66: 0.52 | AY66: 0.5 | BD66: 0.51 | BJ66: 0.47 | BO66: 0.47 | BT66: 0.47
C67: Hospice IE | AS67: 0.39 | AY67: 0.41 | BD67: 0.36 | BJ67: 0.17 | BO67: 0.27 | BT67: 0.25
C68: Hospice SGV | AS68: 0.39 | AY68: 0.17 | BD68: -0.04 | BJ68: 0.01 | BO68: 0.44 | BT68: 0.47
C69: Hospice Desert | AS69: 0.46 | AY69: 0.43 | BD69: 0.42 | BJ69: 0.45 | BO69: 0.42 | BT69: 0.54
A70: DME PPD | B70: Benchmark
B71: 7 | C71: Hospice OC | D71: 7.7 | H71: 7.41 | M71: =22223.98/'Company Scorecard'!T$50 -> 8.43735 | S71: 7.02 | X71: 7.41 | AC71: 7.2 | AI71: 8.21 | AN71: 6.84 | AS71: 7.21 | AY71: =25426.93/'Company Scorecard'!BF50 -> 7.4478412 | BD71: 7.08 | BJ71: 7.48 | BO71: =22622.8/'Company Scorecard'!BV50 -> 6.3227501 | BP71: =22622.8/'Company Scorecard'!BW50 -> 27.860591 | BQ71: =22622.8/'Company Scorecard'!BX50 -> 26.709327 | BR71: =22622.8/'Company Scorecard'!BY50 -> 26.490398 | BS71: =22622.8/'Company Scorecard'!BZ50 -> 26.275029 | BT71: =21462.57/'Company Scorecard'!CA50 -> 6.3895713 | BY71: 6
B72: 7 | C72: Hospice IE | D72: 8.61 | H72: 6.56 | M72: 13.23 | S72: 8.47 | X72: 8.04 | AC72: 7.78 | AI72: 8.47 | AN72: 7.69 | AS72: 7.5 | AY72: =10098.96/'Company Scorecard'!BF51 -> 7.2811536 | BD72: 7.54 | BJ72: 7.78 | BO72: =8522.37/'Company Scorecard'!BV51 -> 6.872879 | BP72: =8522.37/'Company Scorecard'!BW51 -> 31.217473 | BQ72: =8522.37/'Company Scorecard'!BX51 -> 28.987653 | BR72: =8522.37/'Company Scorecard'!BY51 -> 28.987653 | BS72: =8522.37/'Company Scorecard'!BZ51 -> 28.313522 | BT72: =7295.51/'Company Scorecard'!CA51 -> 6.3055402 | BY72: =8115.48/'Company Scorecard'!CF51 -> 5.8259009
B73: 7 | C73: Hospice SGV | D73: 10.7 | H73: =7472.19/'Company Scorecard'!O52 -> 10.988515 | M73: =7273.5/'Company Scorecard'!T$52 -> 9.4461039 | S73: 6.56 | X73: 5.84 | AC73: 5.58 | AI73: 7.96 | AN73: 7.61 | AS73: 8.1 | AY73: =6335.69/'Company Scorecard'!BF52 -> 8.1962354 | BD73: 8.03 | BJ73: 6.98 | BO73: =4645.94/'Company Scorecard'!BV52 -> 6.1454233 | BP73: =4645.94/'Company Scorecard'!BW52 -> 30.168442 | BQ73: =4645.94/'Company Scorecard'!BX52 -> 33.185286 | BR73: =4645.94/'Company Scorecard'!BY52 -> 36.87254 | BS73: =4645.94/'Company Scorecard'!BZ52 -> 36.87254 | BT73: =4320.93/'Company Scorecard'!CA52 -> 7.8705464 | BY73: =3915.35/'Company Scorecard'!CF52 -> 6.9792335
B74: 7 | C74: Hospice Desert | D74: 7.7 | H74: =14346/'Company Scorecard'!O53 -> 7.2061483 | M74: =17163/'Company Scorecard'!T$53 -> 6.6704236 | S74: 6.52 | X74: 6.37 | AC74: 6.41 | AI74: 6.25 | AN74: 6.36 | AS74: 6.35 | AY74: =17826.5/'Company Scorecard'!BF53 -> 6.2902258 | BD74: 6.68 | BJ74: 6.56 | BO74: =19520.5/'Company Scorecard'!BV53 -> 6.4658827 | BP74: =19520.5/'Company Scorecard'!BW53 -> 27.886429 | BQ74: =19520.5/'Company Scorecard'!BX53 -> 28.16811 | BR74: =19520.5/'Company Scorecard'!BY53 -> 28.455539 | BS74: =19520.5/'Company Scorecard'!BZ53 -> 28.748895 | BT74: =19174/'Company Scorecard'!CA53 -> 6.9571843 | BY74: =18696.5/'Company Scorecard'!CF53 -> 6.5076575
A75: Pharmacy PPD | B75: Benchmark
B76: 6 | C76: Hospice OC | D76: 6.71 | H76: 5.69 | M76: =15332/'Company Scorecard'!T$50 -> 5.8208049 | S76: 5.84 | X76: 5.97 | AC76: 5.8 | AI76: 5.51 | AN76: 5.79 | AS76: 5.72 | AY76: =19082.46/'Company Scorecard'!BF50 -> 5.5894728 | BD76: 5.49 | BJ76: 5.48 | BO76: 5.56 | BP76: =19686.43/'Company Scorecard'!BW50 -> 24.244372 | BQ76: =19686.43/'Company Scorecard'!BX50 -> 23.242538 | BR76: =19686.43/'Company Scorecard'!BY50 -> 23.052026 | BS76: =19686.43/'Company Scorecard'!BZ50 -> 22.864611 | BT76: 5.69 | BY76: =20779.45/'Company Scorecard'!CF50 -> 5.3541484
B77: 6 | C77: Hospice IE | D77: 8.16 | H77: 5.09 | M77: 6.39 | S77: 8.32 | X77: 6.39 | AC77: 5.92 | AI77: 7.37 | AN77: 6.59 | AS77: 6.04 | AY77: =8082.22/'Company Scorecard'!BF51 -> 5.8271233 | BD77: 6.47 | BJ77: 6.64 | BO77: =8050.02/'Company Scorecard'!BV51 -> 6.4919516 | BP77: =8050.02/'Company Scorecard'!BW51 -> 29.487253 | BQ77: =8050.02/'Company Scorecard'!BX51 -> 27.38102 | BR77: =8050.02/'Company Scorecard'!BY51 -> 27.38102 | BS77: =8050.02/'Company Scorecard'!BZ51 -> 26.744252 | BT77: =7306.81/'Company Scorecard'!CA51 -> 6.3153068 | BY77: =8095.89/'Company Scorecard'!CF51 -> 5.8118378
B78: 6 | C78: Hospice SGV | D78: 9.5 | H78: =6649.32/'Company Scorecard'!O52 -> 9.7784118 | M78: =6497.53/'Company Scorecard'!T$52 -> 8.4383506 | S78: 5.38 | X78: 5.49 | AC78: 5.02 | AI78: 6.75 | AN78: 5.9 | AS78: 6.79 | AY78: =4927.27/'Company Scorecard'!BF52 -> 6.3742173 | BD78: 6.3 | BJ78: 5.24 | BO78: =4870.78/'Company Scorecard'!BV52 -> 6.4428307 | BP78: =4870.78/'Company Scorecard'!BW52 -> 31.628442 | BQ78: =4870.78/'Company Scorecard'!BX52 -> 34.791286 | BR78: =4870.78/'Company Scorecard'!BY52 -> 38.656984 | BS78: =4870.78/'Company Scorecard'!BZ52 -> 38.656984 | BT78: =3396.8/'Company Scorecard'!CA52 -> 6.1872495 | BY78: =2861.48/'Company Scorecard'!CF52 -> 5.1006774
B79: 6 | C79: Hospice Desert | D79: 8.36 | H79: =19045.34/'Company Scorecard'!O53 -> 9.5666767 | M79: =23339.5/'Company Scorecard'!T$53 -> 9.0709289 | S79: 8.96 | X79: 7.67 | AC79: 9.16 | AI79: 6.63 | AN79: 6.3 | AS79: =18574.31/2706 -> 6.8641205 | AY79: =24211.59/'Company Scorecard'!BF53 -> 8.5432569 | BD79: 6.35 | BJ79: 7 | BO79: =20998.64/'Company Scorecard'!BV53 -> 6.9554952 | BP79: =20998.64/'Company Scorecard'!BW53 -> 29.998057 | BQ79: =20998.64/'Company Scorecard'!BX53 -> 30.301068 | BR79: =20998.64/'Company Scorecard'!BY53 -> 30.610262 | BS79: =20998.64/'Company Scorecard'!BZ53 -> 30.925832 | BT79: =20998.64/'Company Scorecard'!CA53 -> 7.6192453 | BY79: =18505.53/'Company Scorecard'!CF53 -> 6.4411869
A80: Supplies PPD | B80: Benchmark
B81: 5.5 | C81: Hospice OC | D81: 5.53 | H81: 5.88 | M81: =15619.47/'Company Scorecard'!T$50 -> 5.9299431 | S81: 5.67 | X81: 5.67 | AC81: 6.12 | AI81: 5.35 | AN81: 5.92 | AS81: 5.48 | AY81: =18423.3/'Company Scorecard'!BF50 -> 5.3963972 | BD81: 5.13 | BJ81: 5.02 | BO81: 6.39 | BP81: 6.39 | BQ81: 6.39 | BR81: 6.39 | BS81: 6.39 | BT81: =22265.63/'Company Scorecard'!CA50 -> 6.6286484 | BY81: =25596.26/'Company Scorecard'!CF50 -> 6.5952744
B82: 5.5 | C82: Hospice IE | D82: 6.03 | H82: 4.46 | M82: 6.12 | S82: 7.87 | X82: 6.15 | AC82: 5.49 | AI82: 6.72 | AN82: 6.06 | AS82: 5.69 | AY82: =7708.14/'Company Scorecard'!BF51 -> 5.5574189 | BD82: 4.15 | BJ82: 4.52 | BO82: 4.56 | BP82: 4.56 | BQ82: 4.56 | BR82: 4.56 | BS82: 4.56 | BT82: =5525.1/'Company Scorecard'!CA51 -> 4.7753673 | BY82: =7858.1/'Company Scorecard'!CF51 -> 5.6411342
B83: 5.5 | C83: Hospice SGV | D83: 8.15 | H83: =6146.22/'Company Scorecard'!O52 -> 9.0385588 | M83: =5671.68/'Company Scorecard'!T$52 -> 7.3658182 | S83: 4.56 | X83: 5.29 | AC83: 4.98 | AI83: 6.3 | AN83: 5.55 | AS83: 6.22 | AY83: =4586.52/'Company Scorecard'!BF52 -> 5.9334023 | BD83: 5.72 | BJ83: 5.79 | BO83: 5.29 | BP83: 5.29 | BQ83: 5.29 | BR83: 5.29 | BS83: 5.29 | BT83: =2856.223/'Company Scorecard'!CA52 -> 5.202592 | BY83: =3891.41/'Company Scorecard'!CF52 -> 6.9365597
B84: 5.5 | C84: Hospice Desert | D84: 5.43 | H84: =8901.8/'Company Scorecard'!O53 -> 4.4714688 | M84: =12205.08/'Company Scorecard'!T$53 -> 4.7435212 | S84: 5.43 | X84: 5.01 | AC84: 4.38 | AI84: 4.45 | AN84: 4.81 | AS84: =11260.27/2706 -> 4.1612232 | AY84: =12572.58/'Company Scorecard'!BF53 -> 4.4363373 | BD84: 4.71 | BJ84: 4.06 | BO84: 4.86 | BP84: 4.86 | BQ84: 4.86 | BR84: 4.86 | BS84: 4.86 | BT84: =12831.12/'Company Scorecard'!CA53 -> 4.6557039 | BY84: =13281.39/'Company Scorecard'!CF53 -> 4.6228298
A85: HIS - Timely Submission | B85: Benchmark
A86: HCHB App - HIS Timely Submission Tracing Report | B86: 0.97 | C86: Hospice OC | AG86: 12 | AH86: 9 | AJ86: 14 | AK86: 15 | AL86: 10 | AM86: 10 | AO86: 14 | AP86: 13 | AQ86: 10 | AR86: 13 | AT86: 10 | AU86: 10 | AV86: 14 | AW86: 10 | AX86: 18 | AZ86: 22 | BA86: 20 | BB86: 16 | BC86: 13 | BE86: 16
B87: 0.97 | C87: Hospice IE | AG87: 5 | AH87: 10 | AJ87: 2 | AK87: 5 | AL87: 5 | AM87: 3 | AO87: 3 | AP87: 6 | AQ87: 2 | AR87: 4 | AT87: 4 | AU87: 3 | AV87: 7 | AW87: 6 | AX87: 7 | AZ87: 7 | BA87: 11 | BB87: 8 | BC87: 8 | BE87: 7
B88: 0.97 | C88: Hospice SGV | AG88: 2 | AH88: 6 | AJ88: 2 | AK88: 4 | AL88: 4 | AM88: 7 | AO88: 1 | AP88: 2 | AQ88: 1 | AR88: 5 | AT88: 4 | AU88: 4 | AV88: 3 | AW88: 3 | AX88: 2 | AZ88: 3 | BA88: 1 | BB88: 3 | BC88: 7 | BE88: 3
B89: 0.97 | C89: Hospice Desert | AG89: 11 | AH89: 15 | AJ89: 14 | AK89: 9 | AL89: 15 | AM89: 11 | AO89: 10 | AP89: 5 | AQ89: 14 | AR89: 10 | AT89: 5 | AU89: =11+4 -> 15 | AV89: 20 | AW89: 13 | AX89: 21 | AZ89: 19 | BA89: 20 | BB89: 15 | BC89: 10 | BE89: =11+9 -> 20
A90: NOE - Timely Submission | B90: Benchmark
A91: HCHB App - Hospice NOE Status Report | B91: 1 | C91: Hospice OC | AG91: 5 | AH91: 5 | AJ91: 7 | AK91: 10 | AL91: 6 | AM91: 5 | AO91: 7 | AP91: 7 | AQ91: 5 | AR91: 3 | AT91: 5 | AU91: 5 | AV91: 5 | AW91: 5 | AX91: 7 | AZ91: 8 | BA91: 8 | BB91: 3 | BC91: 2 | BE91: 8
B92: 1 | C92: Hospice IE | AG92: 2 | AH92: 6 | AJ92: 2 | AK92: 4 | AL92: 2 | AM92: 1 | AO92: 1 | AP92: 3 | AQ92: 1 | AR92: 2 | AT92: 1 | AU92: 1 | AV92: 4 | AW92: 1 | AX92: 5 | AZ92: 2 | BA92: 3 | BB92: 1 | BC92: 1 | BE92: 4
B93: 1 | C93: Hospice SGV | AG93: 1 | AH93: 2 | AJ93: 0 | AK93: 3 | AL93: 1 | AM93: 3 | AO93: 0 | AP93: 0 | AQ93: 0 | AR93: 1 | AT93: 1 | AU93: 2 | AV93: 1 | AW93: 1 | AX93: 1 | AZ93: 0 | BA93: 0 | BB93: 2 | BC93: 3 | BE93: 0
B94: 1 | C94: Hospice Desert | AG94: 7 | AH94: 8 | AJ94: 2 | AK94: 3 | AL94: 4 | AM94: 4 | AO94: 4 | AP94: 2 | AQ94: 7 | AR94: 1 | AT94: 3 | AU94: 8 | AV94: 6 | AW94: 10 | AX94: 5 | AZ94: 6 | BA94: 5 | BB94: 6 | BC94: 3 | BE94: 1

Sheet HH Admin Scorecard
A1: ACACIA HEALTH HH & PAL SCORECARD (Draft)
E2: (Start of Week) Weekly
A3: KPI | C3: Benchmark | D3: Service Line | E3: 45690 | F3: =E3+7 -> 45697 | G3: =F3+7 -> 45704 | H3: =G3+7 -> 45711 | I3: 45689 | J3: =H3+7 -> 45718 | K3: =J3+7 -> 45725 | L3: =K3+7 -> 45732 | M3: =L3+7 -> 45739 | N3: 45717 | O3: 3/30-4/5 | P3: 4/6-4/12 | Q3: 4/13-4/19 | R3: 4/20-4/26 | S3: 4/27-5/3 | T3: 45748 | U3: 5/4-5/10 | V3: 5/11-5/17 | W3: 5/18-5/24 | X3: 5/25-5/31 | Y3: 45778 | Z3: 6/1-6/7 | AA3: 6/8-6/14 | AB3: 6/15-6/21 | AC3: 6/22-6/28 | AD3: 45809 | AE3: 6/29-7/5 | AF3: 7/6-7/12 | AG3: 7/13-7/19 | AH3: 7/20-7/26 | AI3: 7/27-8/2 | AJ3: 45839 | AK3: 8/3-8/9 | AL3: 8/10-8/16 | AM3: 8/17-8/23 | AN3: 8/24-8/30 | AO3: 45870 | AP3: 8/31-9/6 | AQ3: 9/7-9/13 | AR3: 9/14-9/20 | AS3: 9/21-9/27 | AT3: 45901 | AU3: 9/28-10/4 | AV3: 10/5-10/11 | AW3: 10/12-10/18 | AX3: 10/19-10/25 | AY3: 10/26-11/1 | AZ3: 45931 | BA3: ='Company Scorecard'!BG1 -> 11/2-11/8 | BB3: ='Company Scorecard'!BH1 -> 11/9-11/15 | BC3: ='Company Scorecard'!BI1 -> 11/16-11/22 | BD3: ='Company Scorecard'!BJ1 -> 11/23-11/29 | BE3: 45962 | BF3: ='Company Scorecard'!BL1 -> 11/30-12/6 | BG3: ='Company Scorecard'!BM1 -> 12/7-12/13 | BH3: ='Company Scorecard'!BN1 -> 12/14-12/20 | BI3: ='Company Scorecard'!BO1 -> 12/21-12/27 | BJ3: ='Company Scorecard'!BP1 -> 12/28-1/3 | BK3: ='Company Scorecard'!BQ1 -> 45992 | BL3: ='Company Scorecard'!BR1 -> 1/4-1/10 | BM3: ='Company Scorecard'!BS1 -> 1/11-1/17 | ... CF3: ='Company Scorecard'!CL1 -> 46113
A4: Current Census | C4: Benchmark
D5: HH | E5: ='Company Scorecard'!K$7 -> 153 | F5: ='Company Scorecard'!L$7 -> 152 | G5: ='Company Scorecard'!M$7 -> 149 | H5: ='Company Scorecard'!N$7 -> 150 | I5: ='Company Scorecard'!O$7 -> 148 | J5: ='Company Scorecard'!P$7 -> 150 | K5: ='Company Scorecard'!Q$7 -> 153 | L5: ='Company Scorecard'!R$7 -> 156 | M5: ='Company Scorecard'!S$7 -> 162 | N5: ='Company Scorecard'!T7 -> 154 | O5: ='Company Scorecard'!U$7 -> 156 | P5: ='Company Scorecard'!V$7 -> 145 | Q5: ='Company Scorecard'!W$7 -> 137 | R5: ='Company Scorecard'!X$7 -> 130 | S5: ='Company Scorecard'!Y$7 -> 122 | T5: ='Company Scorecard'!Z$7 -> 135 | U5: ='Company Scorecard'!AA$7 -> 110 | V5: ='Company Scorecard'!AB$7 -> 102 | ... CF5: ='Company Scorecard'!CL$7 -> 55
D6: Palliative | E6: ='Company Scorecard'!K$8 -> 113 | F6: ='Company Scorecard'!L$8 -> 112 | G6: ='Company Scorecard'!M$8 -> 113 | H6: ='Company Scorecard'!N$8 -> 115 | I6: ='Company Scorecard'!O$8 -> 113 | J6: ='Company Scorecard'!P$8 -> 112 | K6: ='Company Scorecard'!Q$8 -> 115 | L6: ='Company Scorecard'!R$8 -> 118 | M6: ='Company Scorecard'!S$8 -> 115 | N6: ='Company Scorecard'!T8 -> 114 | O6: ='Company Scorecard'!U$8 -> 122 | P6: ='Company Scorecard'!V$8 -> 133 | Q6: ='Company Scorecard'!W$8 -> 146 | R6: ='Company Scorecard'!X$8 -> 157 | S6: ='Company Scorecard'!Y$8 -> 176 | T6: ='Company Scorecard'!Z$8 -> 144 | U6: ='Company Scorecard'!AA$8 -> 182 | V6: ='Company Scorecard'!AB$8 -> 190 | ... CF6: ='Company Scorecard'!CL$8 -> 185
D7: Total HH & PAL | E7: =E5+E6 -> 266 | F7: =F5+F6 -> 264 | G7: =G5+G6 -> 262 | H7: =H5+H6 -> 265 | I7: =I5+I6 -> 261 | J7: =J5+J6 -> 262 | K7: =K5+K6 -> 268 | L7: =L5+L6 -> 274 | ... CF7: =CF5+CF6 -> 240
A8: Hospice Census Equivalent (HCE) | C8: Benchmark
D9: HH+Palliative | E9: =E7/2.5 -> 106.4 | F9: =F7/2.5 -> 105.6 | G9: =G7/2.5 -> 104.8 | H9: =H7/2.5 -> 106 | I9: =I7/2.5 -> 104.4 | J9: =J7/2.5 -> 104.8 | K9: =K7/2.5 -> 107.2 | L9: =L7/2.5 -> 109.6 | ... CF9: =CF7/2.5 -> 96
A10: Weekly Admission | C10: Benchmark
D11: HH | E11: ='Company Scorecard'!K20 -> 9 | F11: ='Company Scorecard'!L20 -> 9 | G11: ='Company Scorecard'!M20 -> 9 | H11: 9 | I11: 10 | J11: ='Company Scorecard'!P20 -> 12 | K11: ='Company Scorecard'!Q20 -> 13 | L11: ='Company Scorecard'!R20 -> 13 | M11: ='Company Scorecard'!S20 -> 10 | N11: ='Company Scorecard'!$T$20 -> 50 | O11: ='Company Scorecard'!U20 -> 0 | P11: ='Company Scorecard'!V20 -> 0 | Q11: ='Company Scorecard'!W20 -> 0 | R11: ='Company Scorecard'!X20 -> 1 | S11: ='Company Scorecard'!Y20 -> 0 | T11: ='Company Scorecard'!Z$20 -> 1 | U11: ='Company Scorecard'!AA20 -> 0 | V11: ='Company Scorecard'!AB20 -> 0 | W11: ='Company Scorecard'!AC20 -> 0 | X11: ='Company Scorecard'!AD20 -> 0 | Y11: ='Company Scorecard'!AE$20 -> 0 | Z11: ='Company Scorecard'!AF20 -> 0 | AA11: ='Company Scorecard'!AG20 -> 0 | AB11: ='Company Scorecard'!AH20 -> 0 | AC11: ='Company Scorecard'!AI20 -> 0 | AD11: ='Company Scorecard'!AJ$20 -> 0 | AE11: ='Company Scorecard'!AK20 -> 1 | AF11: ='Company Scorecard'!AL20 -> 0 | AG11: ='Company Scorecard'!AM20 -> 0 | AH11: ='Company Scorecard'!AN20 -> 1 | AI11: ='Company Scorecard'!AO20 -> 0 | AJ11: ='Company Scorecard'!AP$20 -> 2 | AK11: ='Company Scorecard'!AQ20 -> 0 | AL11: ='Company Scorecard'!AR20 -> 1 | AM11: ='Company Scorecard'!AS20 -> 1 | AN11: ='Company Scorecard'!AT20 -> 1 | AO11: ='Company Scorecard'!AU$20 -> 3 | AP11: ='Company Scorecard'!AV20 -> 3 | AQ11: ='Company Scorecard'!AW20 -> 0 | AR11: ='Company Scorecard'!AX20 -> 1 | AS11: ='Company Scorecard'!AY20 -> 6 | AT11: ='Company Scorecard'!AZ$20 -> 16 | AU11: ='Company Scorecard'!BA20 -> 17 | AV11: ='Company Scorecard'!BB20 -> 17 | AW11: ='Company Scorecard'!BC20 -> 9 | AX11: ='Company Scorecard'!BD20 -> 19 | AY11: ='Company Scorecard'!BE20 -> 22 | AZ11: ='Company Scorecard'!BF$20 -> 74 | BA11: ='Company Scorecard'!BG20 -> 21 | BB11: ='Company Scorecard'!BH20 -> 21 | BC11: ='Company Scorecard'!BI20 -> 22 | BD11: ='Company Scorecard'!BJ20 -> 13 | BE11: ='Company Scorecard'!BK$20 -> 83 | BF11: ='Company Scorecard'!BL20 -> 19 | BG11: ='Company Scorecard'!BM20 -> 14 | BH11: ='Company Scorecard'!BN20 -> 18 | BI11: ='Company Scorecard'!BO20 -> 6 | BJ11: ='Company Scorecard'!BP20 -> 8 | BK11: ='Company Scorecard'!BQ$20 -> 62 | BL11: ='Company Scorecard'!BR20 -> 17 | BM11: ='Company Scorecard'!BS20 -> 22 | BN11: ='Company Scorecard'!BT20 -> 10 | BO11: ='Company Scorecard'!BU20 -> 18 | BP11: ='Company Scorecard'!BV$20 -> 71 | BQ11: ='Company Scorecard'!BW$20 -> 11 | BR11: ='Company Scorecard'!BX$20 -> 0 | BS11: ='Company Scorecard'!BY$20 -> 1 | BT11: ='Company Scorecard'!BZ$20 -> 0 | BU11: ='Company Scorecard'!CA$20 -> 11 | BV11: ='Company Scorecard'!CB$20 -> 0 | BW11: ='Company Scorecard'!CC$20 -> 0 | ... CF11: ='Company Scorecard'!CL$20 -> 2
D12: Palliative | E12: ='Company Scorecard'!K21 -> 11 | F12: ='Company Scorecard'!L21 -> 10 | G12: ='Company Scorecard'!M21 -> 12 | H12: ='Company Scorecard'!N21 -> 10 | I12: ='Company Scorecard'!O21 -> 43 | J12: ='Company Scorecard'!P21 -> 9 | K12: ='Company Scorecard'!Q21 -> 7 | L12: ='Company Scorecard'!R21 -> 8 | M12: ='Company Scorecard'!S21 -> 5 | N12: ='Company Scorecard'!$T$21 -> 32 | O12: ='Company Scorecard'!U21 -> 28 | P12: ='Company Scorecard'!V21 -> 20 | Q12: ='Company Scorecard'!W21 -> 19 | R12: ='Company Scorecard'!X21 -> 23 | S12: ='Company Scorecard'!Y21 -> 25 | T12: ='Company Scorecard'!Z$21 -> 107 | U12: ='Company Scorecard'!AA21 -> 22 | V12: ='Company Scorecard'!AB21 -> 19 | W12: ='Company Scorecard'!AC21 -> 17 | X12: ='Company Scorecard'!AD21 -> 18 | Y12: ='Company Scorecard'!AE$21 -> 80 | Z12: ='Company Scorecard'!AF21 -> 10 | AA12: ='Company Scorecard'!AG21 -> 15 | AB12: ='Company Scorecard'!AH21 -> 21 | AC12: ='Company Scorecard'!AI21 -> 22 | AD12: ='Company Scorecard'!AJ$21 -> 72 | AE12: ='Company Scorecard'!AK21 -> 17 | AF12: ='Company Scorecard'!AL21 -> 11 | AG12: ='Company Scorecard'!AM21 -> 18 | AH12: ='Company Scorecard'!AN21 -> 14 | AI12: ='Company Scorecard'!AO21 -> 17 | AJ12: ='Company Scorecard'!AP$21 -> 65 | AK12: ='Company Scorecard'!AQ21 -> 14 | AL12: ='Company Scorecard'!AR21 -> 20 | AM12: ='Company Scorecard'!AS21 -> 8 | AN12: ='Company Scorecard'!AT21 -> 12 | AO12: ='Company Scorecard'!AU$21 -> 60 | AP12: ='Company Scorecard'!AV21 -> 15 | AQ12: ='Company Scorecard'!AW21 -> 18 | AR12: ='Company Scorecard'!AX21 -> 14 | AS12: ='Company Scorecard'!AY21 -> 4 | AT12: ='Company Scorecard'!AZ$21 -> 55 | AU12: ='Company Scorecard'!BA21 -> 6 | AV12: ='Company Scorecard'!BB21 -> 1 | AW12: ='Company Scorecard'!BC21 -> 6 | AX12: ='Company Scorecard'!BD21 -> 4 | AY12: ='Company Scorecard'!BE21 -> 3 | AZ12: ='Company Scorecard'!BF$21 -> 15 | BA12: ='Company Scorecard'!BG21 -> 2 | BB12: ='Company Scorecard'!BH21 -> 1 | BC12: ='Company Scorecard'!BI21 -> 0 | BD12: ='Company Scorecard'!BJ21 -> 0 | BE12: ='Company Scorecard'!BK$21 -> 4 | BF12: ='Company Scorecard'!BL21 -> 3 | BG12: ='Company Scorecard'!BM21 -> 8 | BH12: ='Company Scorecard'!BN21 -> 0 | BI12: ='Company Scorecard'!BO21 -> 5 | BJ12: ='Company Scorecard'!BP21 -> 0 | BK12: ='Company Scorecard'!BQ$21 -> 16 | BL12: ='Company Scorecard'!BR21 -> 7 | BM12: ='Company Scorecard'!BS21 -> 2 | BN12: ='Company Scorecard'!BT21 -> 8 | BO12: ='Company Scorecard'!BU21 -> 3 | BP12: ='Company Scorecard'!BV$21 -> 20 | BQ12: ='Company Scorecard'!BW$21 -> 15 | BR12: ='Company Scorecard'!BX$21 -> 20 | BS12: ='Company Scorecard'!BY$21 -> 22 | BT12: ='Company Scorecard'!BZ$21 -> 19 | BU12: ='Company Scorecard'!CA$21 -> 73 | BV12: ='Company Scorecard'!CB$21 -> 17 | BW12: ='Company Scorecard'!CC$21 -> 24 | ... CF12: ='Company Scorecard'!CL$21 -> 74
A13: Recert % | C13: Benchmark
C14: 45%-55% | D14: HH | E14: ='Company Scorecard'!K33 -> 0.08496732 | F14: ='Company Scorecard'!L33 -> 0.092105263 | G14: ='Company Scorecard'!M33 -> 0.067114094 | H14: ='Company Scorecard'!N33 -> 0.08 | J14: ='Company Scorecard'!P33 -> 0.086666667 | K14: ='Company Scorecard'!Q33 -> 0.071895425 | L14: ='Company Scorecard'!R33 -> 0.051282051 | M14: ='Company Scorecard'!S33 -> 0.080246914 | O14: ='Company Scorecard'!U33 -> 0.051282051 | P14: ='Company Scorecard'!V33 -> 0.11278195 | Q14: ='Company Scorecard'!W33 -> 0.082191781 | R14: ='Company Scorecard'!X33 -> 0.044585987 | S14: ='Company Scorecard'!Y33 -> 0.079545455 | T14: ='Company Scorecard'!Z33 -> 0.974 | U14: ='Company Scorecard'!AA33 -> 0.15454545 | V14: ='Company Scorecard'!AB33 -> 0.098039216 | ... CF14: ='Company Scorecard'!CL33 -> 0.447
C15: 45%-55% | D15: Palliative | E15: ='Company Scorecard'!K34 -> 0.03539823 | F15: ='Company Scorecard'!L34 -> 0.080357143 | G15: ='Company Scorecard'!M34 -> 0.07079646 | H15: ='Company Scorecard'!N34 -> 0.052173913 | J15: ='Company Scorecard'!P34 -> 0.0625 | K15: ='Company Scorecard'!Q34 -> 0.07826087 | L15: ='Company Scorecard'!R34 -> 0.050847458 | M15: ='Company Scorecard'!S34 -> 0.07826087 | O15: ='Company Scorecard'!U34 -> 0.057377049 | P15: ='Company Scorecard'!V34 -> 0.061151079 | Q15: ='Company Scorecard'!W34 -> 0.010600707 | R15: ='Company Scorecard'!X34 -> 0.034843206 | S15: ='Company Scorecard'!Y34 -> 0.013422819 | T15: ='Company Scorecard'!Z34 -> 0.241 | U15: ='Company Scorecard'!AA34 -> 0.027472527 | V15: ='Company Scorecard'!AB34 -> 0.047368421 | ... CF15: ='Company Scorecard'!CL34 -> 0
A16: Discharge | C16: Benchmark
D17: HH | E17: ='Company Scorecard'!K36 -> 10 | F17: ='Company Scorecard'!L36 -> 8 | G17: ='Company Scorecard'!M36 -> 9 | H17: ='Company Scorecard'!N36 -> 8 | J17: ='Company Scorecard'!P36 -> 8 | K17: ='Company Scorecard'!Q36 -> 9 | L17: ='Company Scorecard'!R36 -> 5 | M17: ='Company Scorecard'!S36 -> 9 | O17: ='Company Scorecard'!U36 -> 13 | P17: ='Company Scorecard'!V36 -> 8 | Q17: ='Company Scorecard'!W36 -> 8 | R17: ='Company Scorecard'!X36 -> 6 | S17: ='Company Scorecard'!Y36 -> 10 | T17: ='Company Scorecard'!Z36 -> 39 | U17: ='Company Scorecard'!AA36 -> 9 | V17: ='Company Scorecard'!AB36 -> 6 | ... CF17: ='Company Scorecard'!CL36 -> 18
D18: Palliative | E18: ='Company Scorecard'!K37 -> 14 | F18: ='Company Scorecard'!L37 -> 9 | G18: ='Company Scorecard'!M37 -> 12 | H18: ='Company Scorecard'!N37 -> 8 | J18: ='Company Scorecard'!P37 -> 8 | K18: ='Company Scorecard'!Q37 -> 4 | L18: ='Company Scorecard'!R37 -> 8 | M18: ='Company Scorecard'!S37 -> 9 | O18: ='Company Scorecard'!U37 -> 11 | P18: ='Company Scorecard'!V37 -> 10 | Q18: ='Company Scorecard'!W37 -> 8 | R18: ='Company Scorecard'!X37 -> 8 | S18: ='Company Scorecard'!Y37 -> 8 | T18: ='Company Scorecard'!Z37 -> 40 | U18: ='Company Scorecard'!AA37 -> 11 | V18: ='Company Scorecard'!AB37 -> 14 | ... CF18: ='Company Scorecard'!CL37 -> 54
A19: Lupa % | C19: Benchmark
C20: 7% or below | D20: HH | E20: ='Company Scorecard'!K65 -> 0.075 | F20: ='Company Scorecard'!L65 -> 0.0556 | G20: ='Company Scorecard'!M65 -> 0.1538 | H20: ='Company Scorecard'!N65 -> 0.0541 | I20: ='Company Scorecard'!O65 -> 0.052 | J20: ='Company Scorecard'!P65 -> 0 | K20: ='Company Scorecard'!Q65 -> 0.0714 | L20: ='Company Scorecard'!R65 -> 0.0385 | M20: ='Company Scorecard'!S65 -> 0.0345 | N20: ='Company Scorecard'!$T$65 -> 0.047 | O20: ='Company Scorecard'!U65 -> 0.0645 | P20: ='Company Scorecard'!V65 -> 0.068 | Q20: ='Company Scorecard'!W65 -> 0.055 | R20: ='Company Scorecard'!X65 -> 0.052 | S20: ='Company Scorecard'!Y65 -> 0.053 | T20: ='Company Scorecard'!Z65 -> 0.045 | U20: ='Company Scorecard'!AA65 -> 0.048 | V20: ='Company Scorecard'!AB65 -> 0.057 | ... BS20: ='Company Scorecard'!BY65 -> 0.036 | BT20: 0.032 | BU20: ='Company Scorecard'!CA65 -> 0.055 | BV20: ='Company Scorecard'!CB65 -> 0.032 | BW20: ='Company Scorecard'!CC65 -> 0.043 | BX20: ='Company Scorecard'!CD65 -> 0.035 | BY20: ='Company Scorecard'!CE65 -> 0.038 | BZ20: ='Company Scorecard'!CF65 -> 0.062 | CA20: ='Company Scorecard'!CG65 -> 0.021 | CB20: ='Company Scorecard'!CH65 -> 0.012 | ... CF20: ='Company Scorecard'!CL65 -> 0.076
C21: 7% or below | D21: Palliative | E21: ='Company Scorecard'!K66 -> 0 | F21: ='Company Scorecard'!L66 -> 0.0417 | G21: ='Company Scorecard'!M66 -> 0.0435 | H21: ='Company Scorecard'!N66 -> 0 | I21: ='Company Scorecard'!O66 -> 0.047 | J21: ='Company Scorecard'!P66 -> 0.0313 | K21: ='Company Scorecard'!Q66 -> 0.0385 | L21: ='Company Scorecard'!R66 -> 0.0357 | M21: ='Company Scorecard'!S66 -> 0.1071 | N21: ='Company Scorecard'!$T$66 -> 0.059 | O21: ='Company Scorecard'!U66 -> 0.0857 | P21: ='Company Scorecard'!V66 -> 0.081 | Q21: ='Company Scorecard'!W66 -> 0.055 | R21: ='Company Scorecard'!X66 -> 0.058 | S21: ='Company Scorecard'!Y66 -> 0.039 | T21: ='Company Scorecard'!Z66 -> 0.046 | U21: ='Company Scorecard'!AA66 -> 0.05 | V21: ='Company Scorecard'!AB66 -> 0.05 | ... BS21: ='Company Scorecard'!BY66 -> 0 | BT21: 0 | BU21: ='Company Scorecard'!CA66 -> 0.03 | BV21: ='Company Scorecard'!CB66 -> 0.014 | BW21: ='Company Scorecard'!CC66 -> 0.022 | BX21: ='Company Scorecard'!CD66 -> 0.011 | BY21: ='Company Scorecard'!CE66 -> 0.01 | BZ21: ='Company Scorecard'!CF66 -> 0.049 | CA21: ='Company Scorecard'!CG66 -> 0.019 | CB21: ='Company Scorecard'!CH66 -> 0.032 | ... CF21: ='Company Scorecard'!CL66 -> 0.045
A22: Transition to Hospice | C22: Benchmark
A23: Transitioned to Hospice | B23: Conversion # from Palliative Tracker | BP23: ='[1]2026 Analysis'!B$6 -> 4 | BQ23: ='[1]2026 Analysis'!C$6 -> 9 | BR23: ='[1]2026 Analysis'!D$6 -> 8 | BS23: ='[1]2026 Analysis'!E$6 -> 0 | BT23: ='[1]2026 Analysis'!F$6 -> 0 | BU23: ='[1]2026 Analysis'!C$6 -> 9 | BV23: ='[1]2026 Analysis'!H$6 -> 0 | BW23: ='[1]2026 Analysis'!I$6 -> 0 | BX23: ='[1]2026 Analysis'!J$6 -> 0 | BY23: ='[1]2026 Analysis'!K$6 -> 0 | BZ23: ='[1]2026 Analysis'!D$6 -> 8
A24: Total Care Type-Palliative | B24: HCHB App-Unduplicated Census Report at EOM | BP24: 75 | BU24: 78 | BZ24: 85
A25: From Care Type-Palliative only | C25: 0.4 | BP25: =BP23/BP24 -> 0.053333333 | BU25: =BU23/BU24 -> 0.11538462 | BZ25: =BZ23/BZ24 -> 0.094117647
A26: All HH minus Care Type-UCI | BP26: 225 | BU26: 239 | BZ26: 237
A27: From all HH minus Care Type Ortho | C27: 0.15 | BP27: =BP23/BP26 -> 0.017777778 | BU27: =BU23/BU26 -> 0.037656904 | BZ27: =BZ23/BZ26 -> 0.033755274
A28: Unbilled Claims | C28: Benchmark
D29: HH | O29: fill in | BX29: =(168.5-108.8)/168.5 -> 0.35430267 | BY29: =(168-107)/168 -> 0.36309524
D30: Palliative | BX30: =(256.1-184.1)/256.1 -> 0.28114018 | BY30: =(270.7-204.5)/270.7 -> 0.24455116
A31: Contribution Margin | C31: Benchmark
C32: Enter in target | D32: HH
D33: Palliative

Sheet Data
A2: Executive Scorecard
B3: KPI
A5: 1 | B5: Current Census by Location & Service Line
A6: 2 | B6: Hospice Census Equivalent (HCE)
A7: 3 | B7: Weekly Admissions by Location & Service Line (add house category)
A8: 4 | B8: Revenue per period | C8: Monthly
A9: 5 | B9: Total Patient Days (HH & HOS) | C9: Hospice - Length of Stay Report
A10: 6 | B10: AVG Total LOS and by HCHB Location (HOS)
A11: 7 | B11: Recert % (HH & HOS) | C11: # of recert / # of census
A12: 8 | B12: # of Live Discharges by location (HOS) | C12: Discharge Report
A13: 9 | B13: Conversion Ratio by location AVG MTD (HH & HOS) | C13: Monthly
A14: 10 | B14: Lupa % (HH) | C14: PDGM LUPA Analysis Report; Analytics only show 30 days, not by week
A15: 11 | B15: % Workers under 30 Points (FT employees only) (HH&HOS) | C15: Field Operations/Field Productivity/Worker Points
A16: 12 | B16: $ of Unbilled claims by Location and service line | C16: Custom/AR Aging by Patient
A17: 13 | B17: Census per employee (Census/Employee) by location and service line | C17: ??
A18: 14 | B18: Outstanding AR over 90 days | C18: Monthly
B22: Executive Meeting Weds @ 2pm
B23: Data needs to be updated by end of day Tuesday for prior week #'s
B25: Ask Bryan for HCHB access
B27: Christina Godbee - Liason admission report by Liason include house accounts
A31: Hospice Administrator Scorecard
B32: KPI
A33: 1 | B33: Current Census: Increase Net Census by 15% quarter over quarter | C33: ok
A34: 2 | B34: Weekly Admissions: Increase Admissions 5% month over month | C34: ok
A35: 3 | B35: NTUC Rate: Less than 20% (Admissions ÷ Referrals) | C35: ok
A36: 4 | B36: Average Length of Stay: 100 days or less | C36: ok
A37: 5 | B37: 80% of new admissions BP1 | C37: ?
A38: 6 | B38: DME PPD - OC/IE/SGV: $7 / Low Desert: $7.25 | C38: Monthly Financial
A39: 7 | B39: Pharmacy PPD: OC/SGV: $6 / IE: $6.50 / Low Desert: $7.50 | C39: Monthly Financial
A40: 8 | B40: Supplies PPD: All branches $5.50 | C40: Monthly Financial
A41: 9 | B41: All Live Discharges: 7% or less per month | C41: ok
A42: 10 | B42: Live DC's: Patient Initated: Revocations / Transfer to other hospice: 3% or less per month | C42: ok
A43: 11 | B43: Live DC's:Hospice Initated: 4 % or less per month (ext. prognosis/Out of Area/DC for cause) | C43: ok
A44: 12 | B44: 100% QA Compliance: NOE/Non-covered/Transfer/F2F/Cert/Recert | C44: ?
... A46: 14 | B46: % Workers under 30 Points (FT employees only) | C46: ok
A47: 15 | B47: OT: Needs to be less than 3% total payroll
A48: 16 | B48: Maintain Gross Margin xx% | C48: Monthly Financial
A49: 17 | B49: Average time to admit less than 2 days from referral | C49: ?
A50: 18 | B50: Recert % | C50: ok

Sheet Central Support HH&P
A1: ACACIA HEALTH HH & PAL SCORECARD (Draft) | C1: Green means Bryan L. has a Question in a comment
E2: (Start of Week) Weekly
A3: KPI | C3: Benchmark | D3: Service Line | E3: 45690 | F3: =E3+7 -> 45697 | G3: =F3+7 -> 45704 | H3: =G3+7 -> 45711 | I3: 45689 | J3: =H3+7 -> 45718 | K3: =J3+7 -> 45725 | L3: =K3+7 -> 45732 | M3: =L3+7 -> 45739 | N3: 45717 | O3: 3/30-4/5 | P3: 4/6-4/12 | Q3: 4/13-4/19 | R3: 4/20-4/26 | S3: 4/27-5/3 | T3: 45748 | U3: 5/4-5/10 | V3: 5/11-5/17 | W3: 5/18-5/24 | X3: 5/25-5/31 | Y3: 45778 | Z3: 6/1-6/7 | AA3: 6/8-6/14 | AB3: 6/15-6/21 | AC3: 6/22-6/28 | AD3: 45809 | AE3: 6/29-7/5 | AF3: 7/6-7/12 | AG3: 7/13-7/19 | AH3: 7/20-7/26 | AI3: 7/27-8/2 | AJ3: 45839 | AK3: 8/3-8/9 | AL3: 8/10-8/16 | AM3: 8/17-8/23 | AN3: 8/24-8/30 | AO3: 45870 | AP3: 8/31-9/6 | AQ3: 9/7-9/13 | AR3: 9/14-9/20 | AS3: 9/21-9/27 | AT3: 45901 | AU3: 9/28-10/4 | AV3: 10/5-10/11 | AW3: 10/12-10/18 | AX3: 10/19-10/25 | AY3: 10/26-11/1 | AZ3: 45931 | BA3: ='Company Scorecard'!BG1 -> 11/2-11/8 | BB3: ='Company Scorecard'!BH1 -> 11/9-11/15 | BC3: ='Company Scorecard'!BI1 -> 11/16-11/22 | BD3: ='Company Scorecard'!BJ1 -> 11/23-11/29 | BE3: 45962 | BF3: ='Company Scorecard'!BL1 -> 11/30-12/6 | BG3: ='Company Scorecard'!BM1 -> 12/7-12/13 | BH3: ='Company Scorecard'!BN1 -> 12/14-12/20 | BI3: ='Company Scorecard'!BO1 -> 12/21-12/27 | BJ3: ='Company Scorecard'!BP1 -> 12/28-1/3 | BK3: ='Company Scorecard'!BQ1 -> 45992 | BL3: ='Company Scorecard'!BR1 -> 1/4-1/10 | BM3: ='Company Scorecard'!BS1 -> 1/11-1/17 | ... BX3: ='Company Scorecard'!CD1 -> 3/15-3/21
A4: Current Census | C4: Benchmark
D5: HH | E5: ='Company Scorecard'!K$7 -> 153 | F5: ='Company Scorecard'!L$7 -> 152 | G5: ='Company Scorecard'!M$7 -> 149 | H5: ='Company Scorecard'!N$7 -> 150 | I5: ='Company Scorecard'!O$7 -> 148 | J5: ='Company Scorecard'!P$7 -> 150 | K5: ='Company Scorecard'!Q$7 -> 153 | L5: ='Company Scorecard'!R$7 -> 156 | M5: ='Company Scorecard'!S$7 -> 162 | N5: ='Company Scorecard'!T7 -> 154 | O5: ='Company Scorecard'!U$7 -> 156 | P5: ='Company Scorecard'!V$7 -> 145 | Q5: ='Company Scorecard'!W$7 -> 137 | R5: ='Company Scorecard'!X$7 -> 130 | S5: ='Company Scorecard'!Y$7 -> 122 | T5: ='Company Scorecard'!Z$7 -> 135 | U5: ='Company Scorecard'!AA$7 -> 110 | V5: ='Company Scorecard'!AB$7 -> 102 | ... BX5: ='Company Scorecard'!CD$7 -> 89
D6: Palliative | E6: ='Company Scorecard'!K$8 -> 113 | F6: ='Company Scorecard'!L$8 -> 112 | G6: ='Company Scorecard'!M$8 -> 113 | H6: ='Company Scorecard'!N$8 -> 115 | I6: ='Company Scorecard'!O$8 -> 113 | J6: ='Company Scorecard'!P$8 -> 112 | K6: ='Company Scorecard'!Q$8 -> 115 | L6: ='Company Scorecard'!R$8 -> 118 | M6: ='Company Scorecard'!S$8 -> 115 | N6: ='Company Scorecard'!T8 -> 114 | O6: ='Company Scorecard'!U$8 -> 122 | P6: ='Company Scorecard'!V$8 -> 133 | Q6: ='Company Scorecard'!W$8 -> 146 | R6: ='Company Scorecard'!X$8 -> 157 | S6: ='Company Scorecard'!Y$8 -> 176 | T6: ='Company Scorecard'!Z$8 -> 144 | U6: ='Company Scorecard'!AA$8 -> 182 | V6: ='Company Scorecard'!AB$8 -> 190 | ... BX6: ='Company Scorecard'!CD$8 -> 167
D7: Total HH & PAL | E7: =E5+E6 -> 266 | F7: =F5+F6 -> 264 | G7: =G5+G6 -> 262 | H7: =H5+H6 -> 265 | I7: =I5+I6 -> 261 | J7: =J5+J6 -> 262 | K7: =K5+K6 -> 268 | L7: =L5+L6 -> 274 | ... BX7: =BX5+BX6 -> 256
A8: Hospice Census Equivalent (HCE) | C8: Benchmark
D9: HH+Palliative | E9: =E7/2.5 -> 106.4 | F9: =F7/2.5 -> 105.6 | G9: =G7/2.5 -> 104.8 | H9: =H7/2.5 -> 106 | I9: =I7/2.5 -> 104.4 | J9: =J7/2.5 -> 104.8 | K9: =K7/2.5 -> 107.2 | L9: =L7/2.5 -> 109.6 | ... BX9: =BX7/2.5 -> 102.4
A10: Weekly Admission | C10: Benchmark
D11: HH | E11: ='Company Scorecard'!K20 -> 9 | F11: ='Company Scorecard'!L20 -> 9 | G11: ='Company Scorecard'!M20 -> 9 | H11: 9 | I11: 10 | J11: ='Company Scorecard'!P20 -> 12 | K11: ='Company Scorecard'!Q20 -> 13 | L11: ='Company Scorecard'!R20 -> 13 | M11: ='Company Scorecard'!S20 -> 10 | N11: ='Company Scorecard'!$T$20 -> 50 | O11: ='Company Scorecard'!U20 -> 0 | P11: ='Company Scorecard'!V20 -> 0 | Q11: ='Company Scorecard'!W20 -> 0 | R11: ='Company Scorecard'!X20 -> 1 | S11: ='Company Scorecard'!Y20 -> 0 | T11: ='Company Scorecard'!Z$20 -> 1 | U11: ='Company Scorecard'!AA20 -> 0 | V11: ='Company Scorecard'!AB20 -> 0 | W11: ='Company Scorecard'!AC20 -> 0 | X11: ='Company Scorecard'!AD20 -> 0 | Y11: ='Company Scorecard'!AE$20 -> 0 | Z11: ='Company Scorecard'!AF20 -> 0 | AA11: ='Company Scorecard'!AG20 -> 0 | AB11: ='Company Scorecard'!AH20 -> 0 | AC11: ='Company Scorecard'!AI20 -> 0 | AD11: ='Company Scorecard'!AJ$20 -> 0 | AE11: ='Company Scorecard'!AK20 -> 1 | AF11: ='Company Scorecard'!AL20 -> 0 | AG11: ='Company Scorecard'!AM20 -> 0 | AH11: ='Company Scorecard'!AN20 -> 1 | AI11: ='Company Scorecard'!AO20 -> 0 | AJ11: ='Company Scorecard'!AP$20 -> 2 | AK11: ='Company Scorecard'!AQ20 -> 0 | AL11: ='Company Scorecard'!AR20 -> 1 | AM11: ='Company Scorecard'!AS20 -> 1 | AN11: ='Company Scorecard'!AT20 -> 1 | AO11: ='Company Scorecard'!AU$20 -> 3 | AP11: ='Company Scorecard'!AV20 -> 3 | AQ11: ='Company Scorecard'!AW20 -> 0 | AR11: ='Company Scorecard'!AX20 -> 1 | AS11: ='Company Scorecard'!AY20 -> 6 | AT11: ='Company Scorecard'!AZ$20 -> 16 | AU11: ='Company Scorecard'!BA20 -> 17 | AV11: ='Company Scorecard'!BB20 -> 17 | AW11: ='Company Scorecard'!BC20 -> 9 | AX11: ='Company Scorecard'!BD20 -> 19 | AY11: ='Company Scorecard'!BE20 -> 22 | AZ11: ='Company Scorecard'!BF$20 -> 74 | BA11: ='Company Scorecard'!BG20 -> 21 | BB11: ='Company Scorecard'!BH20 -> 21 | BC11: ='Company Scorecard'!BI20 -> 22 | BD11: ='Company Scorecard'!BJ20 -> 13 | BE11: ='Company Scorecard'!BK$20 -> 83 | BF11: ='Company Scorecard'!BL20 -> 19 | BG11: ='Company Scorecard'!BM20 -> 14 | BH11: ='Company Scorecard'!BN20 -> 18 | BI11: ='Company Scorecard'!BO20 -> 6 | BJ11: ='Company Scorecard'!BP20 -> 8 | BK11: ='Company Scorecard'!BQ$20 -> 62 | BL11: ='Company Scorecard'!BR20 -> 17 | BM11: ='Company Scorecard'!BS20 -> 22 | BN11: ='Company Scorecard'!BT20 -> 10 | BO11: ='Company Scorecard'!BU20 -> 18 | BP11: ='Company Scorecard'!BV$20 -> 71 | BQ11: ='Company Scorecard'!BW$20 -> 11 | BR11: ='Company Scorecard'!BX$20 -> 0 | BS11: ='Company Scorecard'!BY$20 -> 1 | BT11: ='Company Scorecard'!BZ$20 -> 0 | BU11: ='Company Scorecard'!CA$20 -> 11 | BV11: ='Company Scorecard'!CB$20 -> 0 | BW11: ='Company Scorecard'!CC$20 -> 0 | BX11: ='Company Scorecard'!CD$20 -> 0
D12: Palliative | E12: ='Company Scorecard'!K21 -> 11 | F12: ='Company Scorecard'!L21 -> 10 | G12: ='Company Scorecard'!M21 -> 12 | H12: ='Company Scorecard'!N21 -> 10 | I12: ='Company Scorecard'!O21 -> 43 | J12: ='Company Scorecard'!P21 -> 9 | K12: ='Company Scorecard'!Q21 -> 7 | L12: ='Company Scorecard'!R21 -> 8 | M12: ='Company Scorecard'!S21 -> 5 | N12: ='Company Scorecard'!$T$21 -> 32 | O12: ='Company Scorecard'!U21 -> 28 | P12: ='Company Scorecard'!V21 -> 20 | Q12: ='Company Scorecard'!W21 -> 19 | R12: ='Company Scorecard'!X21 -> 23 | S12: ='Company Scorecard'!Y21 -> 25 | T12: ='Company Scorecard'!Z$21 -> 107 | U12: ='Company Scorecard'!AA21 -> 22 | V12: ='Company Scorecard'!AB21 -> 19 | W12: ='Company Scorecard'!AC21 -> 17 | X12: ='Company Scorecard'!AD21 -> 18 | Y12: ='Company Scorecard'!AE$21 -> 80 | Z12: ='Company Scorecard'!AF21 -> 10 | AA12: ='Company Scorecard'!AG21 -> 15 | AB12: ='Company Scorecard'!AH21 -> 21 | AC12: ='Company Scorecard'!AI21 -> 22 | AD12: ='Company Scorecard'!AJ$21 -> 72 | AE12: ='Company Scorecard'!AK21 -> 17 | AF12: ='Company Scorecard'!AL21 -> 11 | AG12: ='Company Scorecard'!AM21 -> 18 | AH12: ='Company Scorecard'!AN21 -> 14 | AI12: ='Company Scorecard'!AO21 -> 17 | AJ12: ='Company Scorecard'!AP$21 -> 65 | AK12: ='Company Scorecard'!AQ21 -> 14 | AL12: ='Company Scorecard'!AR21 -> 20 | AM12: ='Company Scorecard'!AS21 -> 8 | AN12: ='Company Scorecard'!AT21 -> 12 | AO12: ='Company Scorecard'!AU$21 -> 60 | AP12: ='Company Scorecard'!AV21 -> 15 | AQ12: ='Company Scorecard'!AW21 -> 18 | AR12: ='Company Scorecard'!AX21 -> 14 | AS12: ='Company Scorecard'!AY21 -> 4 | AT12: ='Company Scorecard'!AZ$21 -> 55 | AU12: ='Company Scorecard'!BA21 -> 6 | AV12: ='Company Scorecard'!BB21 -> 1 | AW12: ='Company Scorecard'!BC21 -> 6 | AX12: ='Company Scorecard'!BD21 -> 4 | AY12: ='Company Scorecard'!BE21 -> 3 | AZ12: ='Company Scorecard'!BF$21 -> 15 | BA12: ='Company Scorecard'!BG21 -> 2 | BB12: ='Company Scorecard'!BH21 -> 1 | BC12: ='Company Scorecard'!BI21 -> 0 | BD12: ='Company Scorecard'!BJ21 -> 0 | BE12: ='Company Scorecard'!BK$21 -> 4 | BF12: ='Company Scorecard'!BL21 -> 3 | BG12: ='Company Scorecard'!BM21 -> 8 | BH12: ='Company Scorecard'!BN21 -> 0 | BI12: ='Company Scorecard'!BO21 -> 5 | BJ12: ='Company Scorecard'!BP21 -> 0 | BK12: ='Company Scorecard'!BQ$21 -> 16 | BL12: ='Company Scorecard'!BR21 -> 7 | BM12: ='Company Scorecard'!BS21 -> 2 | BN12: ='Company Scorecard'!BT21 -> 8 | BO12: ='Company Scorecard'!BU21 -> 3 | BP12: ='Company Scorecard'!BV$21 -> 20 | BQ12: ='Company Scorecard'!BW$21 -> 15 | BR12: ='Company Scorecard'!BX$21 -> 20 | BS12: ='Company Scorecard'!BY$21 -> 22 | BT12: ='Company Scorecard'!BZ$21 -> 19 | BU12: ='Company Scorecard'!CA$21 -> 73 | BV12: ='Company Scorecard'!CB$21 -> 17 | BW12: ='Company Scorecard'!CC$21 -> 24 | BX12: ='Company Scorecard'!CD$21 -> 15
A13: Intake Conversion | C13: Benchmark
B14: Analytics: Intake -Referral Conversion | D14: HH | I14: 0.424 | J14: =9/21 -> 0.42857143 | N14: 0.467 | T14: 0.5 | Y14: 0 | AD14: 0 | AJ14: 0.5 | AO14: 0.494 | AT14: 0.322 | AZ14: 0.418 | BE14: 0.452 | BK14: 0.382 | BP14: 0.391 | BU14: 0.5
D15: Palliative | I15: 0.686 | J15: =7/26 -> 0.26923077 | N15: 0.662 | T15: 0.568 | Y15: 0.457 | AD15: 0.736 | AJ15: 0.632 | AO15: 0.603 | AT15: 0.436 | AZ15: 0.412 | BE15: 0.292 | BK15: 0.481 | BP15: 0.5 | BU15: 0.534
A16: Billing Holds | C16: Benchmark
C17: 0% >30 days | D17: HH | O17: fill in | BX17: =(168.5-108.8)/168.5 -> 0.35430267
D18: Palliative | BX18: =(256.1-184.1)/256.1 -> 0.28114018
A19: Order Tracking (signed within 30days) | C19: Benchmark
B20: Ana/Bryan | C20: 1 | D20: HH | BY20: Admins to fill in | CA20: Chris and Bryan
D21: Palliative
A22: Contribution Margin | C22: Benchmark
B23: Doug | D23: HH | AZ23: 0.17 | BE23: 0.31 | BK23: 0.28 | BP23: 0.2 | BU23: 0.24
A24: Revenue per patient | C24: Benchmark
D25: HH | I25: 2033 | N25: 2542 | T25: 2040 | Y25: 2139 | AD25: 2158.5 | AJ25: 1895.34 | AO25: 518.44 | AT25: 1884.9 | AZ25: =+'Company Scorecard'!BF56 -> 88.16 | BA25: =+'Company Scorecard'!BG56 -> 0 | BB25: =+'Company Scorecard'!BH56 -> 0 | BC25: =+'Company Scorecard'!BI56 -> 0 | BD25: =+'Company Scorecard'!BJ56 -> 0 | BE25: =+'Company Scorecard'!BK56 -> 88.233523 | BF25: =+'Company Scorecard'!BL56 -> 0 | BG25: =+'Company Scorecard'!BM56 -> 0 | ... BU25: =+'Company Scorecard'!CA56 -> 75.074102
D26: Palliative | I26: 2261 | N26: 2569 | T26: 2614 | Y26: 2722 | AD26: 2545.01 | AJ26: 2344.61 | AO26: 1968.29 | AT26: 2172.01 | AZ26: =+'Company Scorecard'!BF57 -> 66.8 | BA26: =+'Company Scorecard'!BG57 -> 0 | BB26: =+'Company Scorecard'!BH57 -> 0 | BC26: =+'Company Scorecard'!BI57 -> 0 | BD26: =+'Company Scorecard'!BJ57 -> 0 | BE26: =+'Company Scorecard'!BK57 -> 65.560147 | BF26: =+'Company Scorecard'!BL57 -> 0 | BG26: =+'Company Scorecard'!BM57 -> 0 | ... BU26: =+'Company Scorecard'!CA57 -> 91.686333
A27: Oasis Exports - Timely Submission | C27: Benchmark
A28: (Ana will enter source) | C28: 0.97 | D28: HH
C29: 0.97 | D29: Palliative
A30: NOA - Timely Submission | C30: Benchmark
A31: (Ana will enter source) | C31: 1 | D31: HH
